Workbook
Name Export_Data: #REF!
Name Export_Name: #REF!
Name Import_Data: #REF!
Name Import_Name: #REF!
Name Print_Area_MI: #REF!
Name Table1LinktoTop: #REF!
Name Table1Notes: #REF!
Name Use_Data: #REF!
Name Use_Names: #REF!

Sheet Index
A1: Vegetables and Pulses Yearbook Tables
A2: Sheet Names Hyperlinked Index | B2: Table Names
A3: =HYPERLINK("#'"&TableSheetNames!A3&"'!A1",TableSheetNames!A3) -> Table 1a-PerCapitaAvail,Major | B3: Table 1a--U.S. per capita availability of commercially produced, all utilizations vegetables and dry pulse crops by major commodity group
A4: =HYPERLINK("#'"&TableSheetNames!A4&"'!A1",TableSheetNames!A4) -> Table 1b-PerCapitaAvail,Minor | B4: Table 1b--U.S. per capita availability of commercially produced, all utilizations vegetables and dry pulse crops by commodity or commodity group
A5: =HYPERLINK("#'"&TableSheetNames!A5&"'!A1",TableSheetNames!A5) -> Table 2a-PerCapitaAvail, Fresh | B5: Table 2a--Vegetables, fresh market (including mushrooms): Selected U.S. per capita availability
A6: =HYPERLINK("#'"&TableSheetNames!A6&"'!A1",TableSheetNames!A6) -> Table 2b-PerCapitaAvail, Pr | B6: Table 2b--Vegetables, processing: Selected U.S. per capita availability
A7: =HYPERLINK("#'"&TableSheetNames!A7&"'!A1",TableSheetNames!A7) -> Table 2c-PerCapitaAvail, Potato | B7: Table 2c--Potatoes: U.S. per capita availability
A8: =HYPERLINK("#'"&TableSheetNames!A8&"'!A1",TableSheetNames!A8) -> Table 2d-PerCapitaAvail, Pulse | B8: Table 2d--Selected dry pulse crops: U.S. per capita availability
A9: =HYPERLINK("#'"&TableSheetNames!A9&"'!A1",TableSheetNames!A9) -> Table 3-Plant, Harvest, Prod | B9: Table 3--U.S. vegetable and dry pulse crop industry: Total harvested area, production, and crop value
A10: =HYPERLINK("#'"&TableSheetNames!A10&"'!A1",TableSheetNames!A10) -> Table 4a-Import Value | B10: Table 4a--Vegetable imports: U.S. value, by group, by month
A11: =HYPERLINK("#'"&TableSheetNames!A11&"'!A1",TableSheetNames!A11) -> Table 4b-Import Value | B11: Table 4b--Vegetable seed imports: U.S. value, by group, by month
A12: =HYPERLINK("#'"&TableSheetNames!A12&"'!A1",TableSheetNames!A12) -> Table 4c-Import Volume | B12: Table 4c--Vegetable imports: U.S. volume, by group, by month
A13: =HYPERLINK("#'"&TableSheetNames!A13&"'!A1",TableSheetNames!A13) -> Table 4d-Import Volume | B13: Table 4d--Vegetable seed imports: U.S. volume, by group, by month
A14: =HYPERLINK("#'"&TableSheetNames!A14&"'!A1",TableSheetNames!A14) -> Table 5a-Export Value | B14: Table 5a--Vegetable exports: U.S. value, by group, by month
... A101: =HYPERLINK("#'"&TableSheetNames!A101&"'!A1",TableSheetNames!A101) -> Table 72-Other | B101: Table 72--U.S. cranberry and other beans, dry: supply, availability, and price, farm weight
A102: Note: Cn = canned. Dehy = dehydrated. Fz = freezing. PerCapitaAvail = per capita availability. Pr = processing. Prod = production. Veg = vegetable.

Sheet TableSheetNames
A1: Sheet Names
A3: Table 1a-PerCapitaAvail,Major
A4: Table 1b-PerCapitaAvail,Minor
A5: Table 2a-PerCapitaAvail, Fresh
A6: Table 2b-PerCapitaAvail, Pr
A7: Table 2c-PerCapitaAvail, Potato
A8: Table 2d-PerCapitaAvail, Pulse
A9: Table 3-Plant, Harvest, Prod
A10: Table 4a-Import Value
A11: Table 4b-Import Value
A12: Table 4c-Import Volume
A13: Table 4d-Import Volume
... A101: Table 72-Other

Sheet Table 1a-PerCapitaAvail,Major
A1: Table 1a--U.S. per capita availability of commercially produced, all utilizations vegetables and dry pulse crops by major commodity group/1 | O1: =HYPERLINK("#'"&"Index'!A1","INDEX") -> INDEX
A2: Year | B2: Fresh vegetables/2 | C2: Processing vegetables/3 | D2: Potatoes/4 | E2: Dry pulses/5 | F2: Mushrooms/6 | G2: Total vegetables and pulses
A3: 1980 | B3: 99.593 | C3: 116.619 | D3: 114.754 | E3: 5.995 | F3: 2.881 | G3: 339.842
A4: 1981 | B4: 98.481 | C4: 111.96 | D4: 116.517 | E4: 5.938 | F4: 2.739 | G4: 335.635
A5: 1982 | B5: 102.98 | C5: 109.777 | D5: 115.023 | E5: 7.691 | F5: 2.927 | G5: 338.398
A6: 1983 | B6: 100.564 | C6: 111.712 | D6: 118.639 | E6: 6.666 | F6: 2.968 | G6: 340.549
A7: 1984 | B7: 107.282 | C7: 119.694 | D7: 122.095 | E7: 5.836 | F7: 3.468 | G7: 358.375
A8: 1985 | B8: 111.16 | C8: 116.197 | D8: 122.402 | E8: 7.356 | F8: 3.542 | G8: 360.657
A9: 1986 | B9: 108.622 | C9: 116.239 | D9: 125.945 | E9: 7.062 | F9: 3.604 | G9: 361.472
A10: 1987 | B10: 118.983 | C10: 116.3 | D10: 125.964 | E10: 5.963 | F10: 3.782 | G10: 370.992
A11: 1988 | B11: 123.353 | C11: 114.067 | D11: 122.389 | E11: 7.548 | F11: 3.586 | G11: 370.943
A12: 1989 | B12: 128.937 | C12: 119.997 | D12: 126.997 | E12: 6.037 | F12: 3.544 | G12: 385.512
A13: 1990 | B13: 127.662 | C13: 129.595 | D13: 124 | E13: 7.195 | F13: 3.592 | G13: 392.044
A14: 1991 | B14: 124.063 | C14: 131.952 | D14: 133.956 | E14: 7.907 | F14: 3.716 | G14: 401.594
... A47: 2024 | B47: 147.669 | C47: 95.172 | D47: 116.296 | E47: 11.069 | F47: 3.314 | G47: 373.52
A48: Note: Most recent year is preliminary. Totals may not sum due to rounding.
A49: 1/ Unit of measure is pounds per person.
A50: 2/ Fresh vegetable availability includes all commodities and uses identified in table 2a excluding fresh mushrooms.
A51: 3/ Processing vegetable availability includes all commodities and uses identified in table 2b excluding processing mushrooms.
A52: 4/ Potato availability includes all potato uses identified in table 2c.
A53: 5/ Dry pulses availability includes all pulse types identified in table 2d.
A54: 6/ Mushroom availability includes both fresh and processing identified in tables 28 and 51.
A55: Source: USDA, Economic Research Service.

Sheet Table 1b-PerCapitaAvail,Minor
A1: Table 1b--U.S. per capita availability of commercially produced, all utilizations vegetables and dry pulse crops by commodity or commodity group/1 | O1: =HYPERLINK("#'"&"Index'!A1","INDEX") -> INDEX
A2: Year | B2: Artichokes (all uses) | C2: Asparagus (fresh and processing) | D2: Beans, lima green (fresh and processing) | E2: Beans, snap green (fresh and processing) | F2: Beets (processing) | G2: Black beans (dry) | H2: Blackeye beans (dry) | I2: Broccoli (fresh and processing) | J2: Brussels sprouts (fresh) | K2: Cabbage (fresh and processing) | L2: Carrots (fresh and processing) | M2: Cauliflower (fresh and processing) | N2: Celery (all uses) | O2: Chickpea/garbanzo (fresh and processing) | P2: Cucumbers (fresh and processing) | Q2: Dry peas and lentils (dry) | R2: Eggplant (all uses) | S2: Escarole and endive (fresh) | T2: Garlic (all uses) | U2: Great Northern beans (dry) | V2: Greens, collard (fresh) | W2: Greens, mustard (fresh) | X2: Greens, turnip (fresh) | Y2: Kale (fresh) | Z2: Lettuce, head/iceberg (fresh) | AA2: Lettuce, leaf and romaine (fresh) | AB2: Lima beans (dry) | AC2: Mushrooms (fresh and processing) | AD2: Navy beans (dry) | AE2: Okra (fresh) | AF2: Onions (fresh and processing) | AG2: Other unspecified beans including cranberry (dry) | AH2: Other, processing/2 | AI2: Peas, green (processing) | AJ2: Peppers, bell (fresh) | AK2: Peppers, chili (fresh) | AL2: Pink beans (dry) | AM2: Pinto beans (dry) | AN2: Potatoes (fresh and processing) | AO2: Pumpkins (all uses) | AP2: Radishes (all uses) | AQ2: Red kidney beans (dry) | AR2: Small red beans (dry) | AS2: Small white beans (dry) | AT2: Spinach (fresh and processing) | AU2: Squash (all uses) | AV2: Sweet corn (fresh and processing) | AW2: Sweet potatoes (all uses) | AX2: Tomatoes (fresh and processing) | AY2: Total vegetables and pulses (all uses)
A3: 1980 | B3: 0.58710907 | C3: 0.78546823 | D3: 1.3004049 | E3: 7.2317257 | F3: 1.8196923 | G3: 0.0059707719 | H3: 0.22893531 | I3: 2.8563294 | J3: 0.28543074 | K3: 9.9829067 | L3: 9.6244576 | M3: 1.9162554 | N3: 7.371644 | O3: 0.14290476 | P3: 9.259197 | Q3: 0.59898581 | R3: 0.47732802 | S3: 0.45141969 | T3: 0.86089423 | U3: 0.4135865 | V3: NA | W3: NA | X3: NA | Y3: NA | Z3: 25.745413 | AA3: NA | AB3: 0.30642137 | AC3: 2.881426 | AD3: 2.0068635 | AE3: 0.31082629 | AF3: 12.153255 | AG3: 0.68547289 | AH3: 1.4605271 | AI3: 4.4666446 | AJ3: 2.8854852 | AK3: 3.0490414 | AL3: 0.19247469 | AM3: 0.79197193 | AN3: 114.75343 | AO3: NA | AP3: 0.56509849 | AQ3: 0.49373739 | AR3: 0.1022271 | AS3: 0.025599078 | AT3: 1.8067498 | AU3: 2.307953 | AV3: 25.931497 | AW3: 4.3867077 | AX3: 76.982528 | AY3: 340.492
A4: 1981 | B4: 0.7475018 | C4: 0.79570541 | D4: 1.3804475 | E4: 7.5634999 | F4: 1.6143636 | G4: 0.070927876 | H4: 0.19408098 | I4: 3.220572 | J4: 0.363532 | K4: 10.179022 | L4: 9.5640272 | M4: 2.2777603 | N4: 7.2720054 | O4: 0.14685195 | P4: 9.3432796 | Q4: 0.51639989 | R4: 0.45832862 | S4: 0.44310898 | T4: 0.65922789 | U4: 0.28968178 | V4: NA | W4: NA | X4: NA | Y4: NA | Z4: 25.028482 | AA4: NA | AB4: 0.28250015 | AC4: 2.7390743 | AD4: 1.1464521 | AE4: 0.34366901 | AF4: 11.555312 | AG4: 0.41745301 | AH4: 1.5658837 | AI4: 4.43424 | AJ4: 2.786064 | AK4: 3.2675569 | AL4: 0.38674933 | AM4: 1.9816298 | AN4: 116.51684 | AO4: NA | AP4: 0.57450824 | AQ4: 0.31195716 | AR4: 0.15692452 | AS4: 0.035967651 | AT4: 1.7925976 | AU4: 2.3248561 | AV4: 24.648956 | AW4: 4.6715368 | AX4: 72.255274 | AY4: 336.32481
A5: 1982 | B5: 0.82303995 | C5: 0.72078912 | D5: 1.1410202 | E5: 6.9901009 | F5: 1.3451255 | G5: 0.043411374 | H5: 0.29001193 | I5: 3.5035912 | J5: 0.31956863 | K5: 10.253895 | L5: 9.5446119 | M5: 2.221161 | N5: 7.4119377 | O5: 0.11063183 | P5: 9.2929117 | Q5: 0.34396106 | R5: 0.51380778 | S5: 0.37728048 | T5: 0.75717953 | U5: 0.49405826 | V5: NA | W5: NA | X5: NA | Y5: NA | Z5: 25.023688 | AA5: NA | AB5: 0.34482216 | AC5: 2.927171 | AD5: 1.5579453 | AE5: 0.3157615 | AF5: 14.248509 | AG5: 0.26357951 | AH5: 1.5543439 | AI5: 4.1380077 | AJ5: 2.9721605 | AK5: 3.0546195 | AL5: 0.32950309 | AM5: 3.270771 | AN5: 115.02323 | AO5: NA | AP5: 0.50078349 | AQ5: 0.51535799 | AR5: 0.061328631 | AS5: 0.065378991 | AT5: 1.6757272 | AU5: 2.4567936 | AV5: 23.365937 | AW5: 5.3925603 | AX5: 73.41164 | AY5: 338.96771
A6: 1983 | B6: 0.73450644 | C6: 0.83826996 | D6: 0.9305415 | E6: 6.7793739 | F6: 1.2579724 | G6: 0.032917497 | H6: 0.26371152 | I6: 3.5988484 | J6: 0.29363186 | K6: 10.284658 | L6: 9.5383434 | M6: 2.2626989 | N6: 7.0013145 | O6: 0.13974955 | P6: 9.6924205 | Q6: 0.4186865 | R6: 0.51257538 | S6: 0.39478121 | T6: 0.9974606 | U6: 0.44604318 | V6: NA | W6: NA | X6: NA | Y6: NA | Z6: 22.524722 | AA6: NA | AB6: 0.27923794 | AC6: 2.9683079 | AD6: 1.6027554 | AE6: 0.45284079 | AF6: 13.822478 | AG6: 0.29107112 | AH6: 1.633754 | AI6: 4.2113234 | AJ6: 3.3255515 | AK6: 3.3093762 | AL6: 0.13710364 | AM6: 2.3524948 | AN6: 118.63891 | AO6: NA | AP6: 0.54659463 | AQ6: 0.53040404 | AR6: 0.097414516 | AS6: 0.074684315 | AT6: 1.6000872 | AU6: 2.5561191 | AV6: 24.417772 | AW6: 4.4851946 | AX6: 74.737968 | AY6: 341.01467
A7: 1984 | B7: 0.95452468 | C7: 0.81210634 | D7: 1.3647081 | E7: 6.8339595 | F7: 1.2442764 | G7: 0.02022103 | H7: 0.20605832 | I7: 4.2009889 | J7: 0.30675106 | K7: 10.265262 | L7: 10.664557 | M7: 2.7742211 | N7: 7.1150465 | O7: 0.10031793 | P7: 9.8802505 | Q7: 0.42888967 | R7: 0.46880024 | S7: 0.387141 | T7: 0.76888317 | U7: 0.48743717 | V7: NA | W7: NA | X7: NA | Y7: NA | Z7: 24.988999 | AA7: NA | AB7: 0.30701731 | AC7: 3.4680385 | AD7: 1.7217116 | AE7: 0.44552063 | AF7: 14.560113 | AG7: 0.20435967 | AH7: 1.3725523 | AI7: 4.0274449 | AJ7: 3.6247398 | AK7: 3.6141537 | AL7: 0.053137278 | AM7: 1.6965772 | AN7: 122.09527 | AO7: NA | AP7: 0.49504744 | AQ7: 0.35391203 | AR7: 0.039505347 | AS7: 0.21705529 | AT7: 1.3631699 | AU7: 2.6249691 | AV7: 24.638804 | AW7: 4.8320822 | AX7: 83.030233 | AY7: 359.05881
A8: 1985 | B8: 1.0227873 | C8: 0.86256047 | D8: 1.1449959 | E8: 6.8899835 | F8: 0.87434582 | G8: 0.012876049 | H8: 0.22823964 | I8: 4.5398526 | J8: 0.32876804 | K8: 10.32959 | L8: 9.6610023 | M8: 2.7673772 | N8: 6.8803519 | O8: 0.071852689 | P8: 10.2198 | Q8: 0.44383669 | R8: 0.45792692 | S8: 0.38915401 | T8: 1.0616188 | U8: 0.47081865 | V8: NA | W8: NA | X8: NA | Y8: NA | Z8: 23.750975 | AA8: 3.265455 | AB8: 0.36763258 | AC8: 3.541953 | AD8: 1.8513079 | AE8: 0.38268726 | AF8: 15.196806 | AG8: 0.23106019 | AH8: 1.3913933 | AI8: 4.1433268 | AJ8: 3.8001224 | AK8: 3.910612 | AL8: 0.099011588 | AM8: 2.7736421 | AN8: 122.40229 | AO8: NA | AP8: 0.51205497 | AQ8: 0.45248639 | AR8: 0.050460064 | AS8: 0.30251565 | AT8: 1.7230376 | AU8: 2.6724221 | AV8: 26.207508 | AW8: 5.2604073 | AX8: 78.287106 | AY8: 361.23401
A9: 1986 | B9: 0.93537945 | C9: 0.99025963 | D9: 1.1909146 | E9: 6.6347342 | F9: 1.0610853 | G9: 0.031182085 | H9: 0.19426848 | I9: 4.8314249 | J9: 0.32661406 | K9: 10.191561 | L9: 9.465912 | M9: 3.1111565 | N9: 6.4927634 | O9: 0.093016273 | P9: 9.9508811 | Q9: 0.70291094 | R9: 0.46665088 | S9: 0.36609031 | T9: 0.7660471 | U9: 0.46614292 | V9: NA | W9: NA | X9: NA | Y9: NA | Z9: 22.007804 | AA9: 2.3735617 | AB9: 0.34858855 | AC9: 3.6035972 | AD9: 1.1888253 | AE9: 0.28527349 | AF9: 15.626765 | AG9: 0.30625262 | AH9: 1.6255906 | AI9: 4.0799128 | AJ9: 3.9654936 | AK9: 4.1749172 | AL9: 0.30487625 | AM9: 2.6275426 | AN9: 125.94605 | AO9: NA | AP9: 0.46356455 | AQ9: 0.50566173 | AR9: 0.16001704 | AS9: 0.13178686 | AT9: 1.4836156 | AU9: 2.775282 | AV9: 25.706652 | AW9: 4.2620809 | AX9: 79.843084 | AY9: 362.06579
A10: 1987 | B10: 0.99298199 | C10: 0.9470657 | D10: 1.0777447 | E10: 6.6506326 | F10: 0.76173066 | G10: 0.049285844 | H10: 0.23420233 | I10: 5.3034588 | J10: 0.25864483 | K10: 10.688579 | L10: 11.437094 | M10: 3.077091 | N10: 6.5935734 | O10: 0.10066382 | P10: 10.601884 | Q10: 0.57932702 | R10: 0.47280934 | S10: 0.34142765 | T10: 1.187501 | U10: 0.20494555 | V10: NA | W10: NA | X10: NA | Y10: NA | Z10: 25.796527 | AA10: 2.5246701 | AB10: 0.18291659 | AC10: 3.7815963 | AD10: 1.4407872 | AE10: 0.21370764 | AF10: 14.930119 | AG10: 0.1915125 | AH10: 1.5872885 | AI10: 3.7311688 | AJ10: 4.2293372 | AK10: 4.1653638 | AL10: 0.18311744 | AM10: 2.2505568 | AN10: 125.96359 | AO10: 3.0136901 | AP10: 0.51295693 | AQ10: 0.36922415 | AR10: 0.077182672 | AS10: 0.099068216 | AT10: 1.3575154 | AU10: 2.8793512 | AV10: 24.731517 | AW10: 4.3022853 | AX10: 81.453764 | AY10: 371.52946
A11: 1988 | B11: 0.91461548 | C11: 1.0374863 | D11: 0.86427502 | E11: 6.6923982 | F11: 0.88849527 | G11: 0.0097922219 | H11: 0.35295957 | I11: 6.1898858 | J11: 0.25589643 | K11: 10.441079 | L11: 10.453272 | M11: 3.1380167 | N11: 7.1528563 | O11: 0.13342237 | P11: 10.103129 | Q11: 0.70132501 | R11: 0.39017064 | S11: 0.35752038 | T11: 1.0862824 | U11: 0.54492472 | V11: NA | W11: NA | X11: NA | Y11: NA | Z11: 27.167467 | AA11: 3.200542 | AB11: 0.19852384 | AC11: 3.5859676 | AD11: 1.1190518 | AE11: 0.41480809 | AF11: 16.216632 | AG11: 0.29344424 | AH11: 2.0137049 | AI11: 3.6565375 | AJ11: 4.4755348 | AK11: 4.3147526 | AL11: 0.19767824 | AM11: 3.3391273 | AN11: 122.38942 | AO11: 3.8059173 | AP11: 0.54979865 | AQ11: 0.32100391 | AR11: 0.099355173 | AS11: 0.23743809 | AT11: 1.5232961 | AU11: 3.0774864 | AV11: 24.919327 | AW11: 3.9309917 | AX11: 78.618006 | AY11: 371.37361
A12: 1989 | B12: 0.97436828 | C12: 0.95084498 | D12: 0.7860221 | E12: 7.0745135 | F12: 0.81506578 | G12: 0.06404385 | H12: 0.30017747 | I12: 5.9729584 | J12: 0.33678065 | K12: 9.8856973 | L12: 11.469962 | M12: 3.0623994 | N12: 7.4742664 | O12: 0.12506322 | P12: 9.9740369 | Q12: 0.61755996 | R12: 0.39904262 | S12: 0.33022532 | T12: 1.0146194 | U12: 0.44334889 | V12: NA | W12: NA | X12: NA | Y12: NA | Z12: 28.685383 | AA12: 3.563487 | AB12: 0.29813705 | AC12: 3.5437935 | AD12: 1.0607467 | AE12: 0.43835044 | AF12: 16.376521 | AG12: 0.21306531 | AH12: 1.8480485 | AI12: 3.710079 | AJ12: 4.6885731 | AK12: 4.5038993 | AL12: 0.071244211 | AM12: 2.125595 | AN12: 126.9976 | AO12: 4.8200063 | AP12: 0.707875 | AQ12: 0.40413759 | AR12: 0.16897393 | AS12: 0.14508402 | AT12: 1.4131079 | AU12: 3.4519138 | AV12: 24.434181 | AW12: 3.9246786 | AX12: 86.240714 | AY12: 385.90619
A13: 1990 | B13: 0.84581544 | C13: 1.0060941 | D13: 0.67902819 | E13: 6.7009817 | F13: 0.85514848 | G13: 0.10049336 | H13: 0.26767867 | I13: 5.6007652 | J13: 0.31703261 | K13: 9.5307934 | L13: 12.376207 | M13: 2.9486189 | N13: 7.1944573 | O13: 0.10435605 | P13: 9.6682207 | Q13: 0.46645409 | R13: 0.39938912 | S13: 0.26232847 | T13: 1.4071459 | U13: 0.3632642 | V13: NA | W13: NA | X13: NA | Y13: NA | Z13: 27.746879 | AA13: 3.7702632 | AB13: 0.24055899 | AC13: 3.5915714 | AD13: 1.2587786 | AE13: 0.24350829 | AF13: 17.194251 | AG13: 0.2306782 | AH13: 2.5320449 | AI13: 4.1620932 | AJ13: 5.8810651 | AK13: 4.8310338 | AL13: 0.25642564 | AM13: 3.0750962 | AN13: 123.99975 | AO13: 4.4334634 | AP13: 0.65856476 | AQ13: 0.59251507 | AR13: 0.12315101 | AS13: 0.11675594 | AT13: 1.3211155 | AU13: 3.5056748 | AV13: 26.289875 | AW13: 4.3992863 | AX13: 90.835762 | AY13: 392.38443
A14: 1991 | B14: 0.8268557 | C14: 0.96879545 | D14: 0.81754388 | E14: 6.9893316 | F14: 0.76017878 | G14: 0.14541927 | H14: 0.27509635 | I14: 5.2949199 | J14: 0.29902206 | K14: 9.6392773 | L14: 11.280566 | M14: 2.5333603 | N14: 6.7326987 | O14: 0.10611894 | P14: 9.6137997 | Q14: 0.55979746 | R14: 0.4114512 | S14: 0.24675195 | T14: 1.4871594 | U14: 0.49515529 | V14: NA | W14: NA | X14: NA | Y14: NA | Z14: 26.044844 | AA14: 3.9967137 | AB14: 0.24744567 | AC14: 3.7157235 | AD14: 1.4667166 | AE14: 0.24635167 | AF14: 17.258669 | AG14: 0.27890316 | AH14: 2.890139 | AI14: 4.1544665 | AJ14: 6.3012046 | AK14: 4.5134084 | AL14: 0.22017345 | AM14: 3.2821338 | AN14: 133.95551 | AO14: 4.4291907 | AP14: 0.54758981 | AQ14: 0.54057953 | AR14: 0.17276875 | AS14: 0.11671433 | AT14: 1.7982879 | AU14: 3.6718586 | AV14: 26.332843 | AW14: 3.8666558 | AX14: 92.470101 | AY14: 402.00229
A15: 1992 | B15: 0.87886863 | C15: 0.98859235 | D15: 0.94734576 | E15: 7.1639277 | F15: 0.91648696 | G15: 0.13853639 | H15: 0.28917678 | I15: 5.798692 | J15: 0.28221757 | K15: 9.8106257 | L15: 12.322738 | M15: 2.4634717 | N15: 7.3233586 | O15: 0.10185251 | P15: 9.47319 | Q15: 0.55897747 | R15: 0.46984359 | S15: 0.32000233 | T15: 1.4605521 | U15: 0.48550453 | V15: NA | W15: NA | X15: NA | Y15: NA | Z15: 25.790598 | AA15: 4.6696133 | AB15: 0.21924814 | AC15: 3.6813101 | AD15: 1.5362009 | AE15: 0.28337809 | AF15: 17.536673 | AG15: 0.42235319 | AH15: 2.4029678 | AI15: 4.0921547 | AJ15: 7.1018735 | AK15: 5.5822789 | AL15: 0.16387576 | AM15: 3.7883098 | AN15: 129.79711 | AO15: 4.0575383 | AP15: 0.4763766 | AQ15: 0.55886236 | AR15: 0.044491724 | AS15: 0.070323624 | AT15: 1.6269109 | AU15: 3.8059271 | AV15: 27.664175 | AW15: 4.0755863 | AX15: 88.761424 | AY15: 400.40352
A16: 1993 | B16: 0.86383358 | C16: 0.90918178 | D16: 0.86467343 | E16: 7.2117532 | F16: 0.83156904 | G16: 0.2075423 | H16: 0.24291152 | I16: 5.6043661 | J16: 0.34773587 | K16: 10.675451 | L16: 14.679961 | M16: 2.7783993 | N16: 7.2613997 | O16: 0.18360205 | P16: 9.5392824 | Q16: 0.5107358 | R16: 0.47146068 | S16: 0.30049785 | T16: 1.7456097 | U16: 0.4197514 | V16: NA | W16: NA | X16: NA | Y16: NA | Z16: 24.400035 | AA16: 5.0417061 | AB16: 0.22232974 | AC16: 3.6913502 | AD16: 1.2012849 | AE16: 0.3836143 | AF16: 19.166069 | AG16: 0.20672033 | AH16: 2.961367 | AI16: 3.4501031 | AJ16: 7.6309872 | AK16: 4.8971287 | AL16: 0.18240878 | AM16: 3.5489506 | AN16: 136.48924 | AO16: 5.1255779 | AP16: 0.51680086 | AQ16: 0.58491948 | AR16: 0.18557529 | AS16: 0.040344157 | AT16: 1.6686664 | AU16: 3.7846051 | AV16: 27.77307 | AW16: 3.6597012 | AX16: 92.07806 | AY16: 414.54033
A17: 1994 | B17: 1.2662966 | C17: 0.93530656 | D17: 0.96030422 | E17: 7.2691216 | F17: 1.1359116 | G17: 0.300676 | H17: 0.27944102 | I17: 6.7392852 | J17: 0.32379781 | K17: 10.307769 | L17: 16.90518 | M17: 2.6086002 | N17: 7.2366347 | O17: 0.16360481 | P17: 10.142108 | Q17: 0.44131233 | R17: 0.51625442 | S17: 0.3288263 | T17: 1.7971356 | U17: 0.35100105 | V17: NA | W17: NA | X17: NA | Y17: NA | Z17: 25.00662 | AA17: 5.6782245 | AB17: 0.19367947 | AC17: 3.7264672 | AD17: 1.8361925 | AE17: 0.24312568 | AF17: 17.86299 | AG17: 0.30595666 | AH17: 2.9391305 | AI17: 3.5722487 | AJ17: 7.0592418 | AK17: 4.1043643 | AL17: 0.21391668 | AM17: 3.3081968 | AN17: 136.46112 | AO17: 5.4914158 | AP17: 0.43575459 | AQ17: 0.61170082 | AR17: 0.11952528 | AS17: 0.024517909 | AT17: 1.71204 | AU17: 3.9297531 | AV17: 27.330661 | AW17: 4.462573 | AX17: 92.492958 | AY17: 419.13094
A18: 1995 | B18: 0.92478362 | C18: 0.89925542 | D18: 1.1346056 | E18: 6.8286681 | F18: 1.1254628 | G18: 0.42617689 | H18: 0.26343629 | I18: 6.8569003 | J18: 0.33501277 | K18: 9.4955639 | L18: 15.403302 | M18: 2.2439114 | N18: 6.9344657 | O18: 0.13369336 | P18: 10.654943 | Q18: 0.95085493 | R18: 0.4726944 | S18: 0.30408034 | T18: 1.8497981 | U18: 0.36258184 | V18: NA | W18: NA | X18: NA | Y18: NA | Z18: 22.167103 | AA18: 5.8945453 | AB18: 0.23648659 | AC18: 4.0611014 | AD18: 1.6487236 | AE18: 0.38204529 | AF18: 19.102666 | AG18: 0.29562157 | AH18: 2.6424177 | AI18: 3.6375219 | AJ18: 7.0105234 | AK18: 3.8340742 | AL18: 0.17627711 | AM18: 3.2187791 | AN18: 136.62411 | AO18: 5.8963229 | AP18: 0.41383618 | AQ18: 0.5613297 | AR18: 0.13645069 | AS18: 0.046266134 | AT18: 1.6583817 | AU18: 3.7457673 | AV18: 28.560595 | AW18: 4.2075966 | AX18: 91.405199 | AY18: 415.16393
A19: 1996 | B19: 0.98941365 | C19: 0.91194311 | D19: 1.1629401 | E19: 7.2049385 | F19: 0.93352171 | G19: 0.3560823 | H19: 0.25701865 | I19: 7.0349565 | J19: 0.3304075 | K19: 9.2467854 | L19: 16.924301 | M19: 2.2002083 | N19: 7.0272566 | O19: 0.25927014 | P19: 10.006672 | Q19: 0.6496202 | R19: 0.59888678 | S19: 0.31911182 | T19: 2.2946341 | U19: 0.54026556 | V19: NA | W19: NA | X19: NA | Y19: NA | Z19: 21.574936 | AA19: 5.8176096 | AB19: 0.19952012 | AC19: 3.7821425 | AD19: 1.2668872 | AE19: 0.33671025 | AF19: 19.164961 | AG19: 0.24140885 | AH19: 2.7990299 | AI19: 3.396385 | AJ19: 8.0689195 | AK19: 4.7303682 | AL19: 0.14501215 | AM19: 3.3991545 | AN19: 144.8891 | AO19: 5.7748518 | AP19: 0.4070195 | AQ19: 0.55238403 | AR19: 0.16572879 | AS19: 0.051996288 | AT19: 1.7684161 | AU19: 3.689598 | AV19: 29.037586 | AW19: 4.2873826 | AX19: 90.849866 | AY19: 425.64521
A20: 1997 | B20: 1.0097108 | C20: 0.93754797 | D20: 1.1059849 | E20: 6.7388561 | F20: 0.89406109 | G20: 0.33622026 | H20: 0.23822376 | I20: 7.2487319 | J20: 0.24769889 | K20: 10.449814 | L20: 18.162089 | M20: 2.2006904 | N20: 6.5491764 | O20: 0.2441772 | P20: 11.658628 | Q20: 0.89886315 | R20: 0.65016379 | S20: 0.29943237 | T20: 1.9951143 | U20: 0.39961737 | V20: 0.79496688 | W20: 0.68184323 | X20: 0.52824354 | Y20: 0.42355411 | Z20: 23.901619 | AA20: 6.5947438 | AB20: 0.2095174 | AC20: 3.9276834 | AD20: 1.3732881 | AE20: 0.23038354 | AF20: 19.732785 | AG20: 0.18137715 | AH20: 2.6805175 | AI20: 3.4983958 | AJ20: 7.333958 | AK20: 4.5860384 | AL20: 0.20298074 | AM20: 3.474068 | AN20: 137.71126 | AO20: 5.6483839 | AP20: 0.50624526 | AQ20: 0.54476488 | AR20: 0.14483121 | AS20: 0.047534363 | AT20: 1.9252052 | AU20: 3.8504536 | AV20: 27.497253 | AW20: 4.260937 | AX20: 89.867085 | AY20: 424.62471
A21: 1998 | B21: 1.179916 | C21: 0.97956756 | D21: 1.0733064 | E21: 7.3401245 | F21: 0.74990493 | G21: 0.52565659 | H21: 0.21916083 | I21: 7.1241326 | J21: 0.28140449 | K21: 9.8099372 | L21: 13.735433 | M21: 2.2333696 | N21: 6.4673904 | O21: 0.16308539 | P21: 10.502961 | Q21: 0.80174557 | R21: 0.69975191 | S21: 0.30421735 | T21: 2.5842585 | U21: 0.35309078 | V21: 0.78734585 | W21: 0.68503167 | X21: 0.5147913 | Y21: 0.40420875 | Z21: 22.324952 | AA21: 6.614551 | AB21: 0.21445999 | AC21: 3.991809 | AD21: 1.1104224 | AE21: 0.28518904 | AF21: 19.49434 | AG21: 0.16 | AH21: 2.7309749 | AI21: 3.3404476 | AJ21: 7.7627909 | AK21: 4.7581953 | AL21: 0.21040282 | AM21: 3.441908 | AN21: 137.55073 | AO21: 6.3565421 | AP21: 0.44469635 | AQ21: 0.61237 | AR21: 0.20964536 | AS21: 0.038667309 | AT21: 1.7468997 | AU21: 4.1602632 | AV21: 28.340068 | AW21: 3.8476933 | AX21: 92.526774 | AY21: 421.79459
A22: 1999 | B22: 1.3208194 | C22: 1.123902 | D22: 1.0223257 | E22: 7.5269341 | F22: 0.83925598 | G22: 0.61909061 | H22: 0.25031071 | I22: 8.2702862 | J22: 0.25779194 | K22: 8.7888492 | L22: 13.070633 | M22: 2.2673975 | N22: 6.5317241 | O22: 0.15935476 | P22: 10.931359 | Q22: 0.57943197 | R22: 0.6660198 | S22: 0.22510256 | T22: 3.2924124 | U22: 0.53294175 | V22: 0.77996384 | W22: 0.68820366 | X22: 0.5139323 | Y22: 0.3853388 | Z22: 24.909064 | AA22: 7.5915765 | AB22: 0.2099456 | AC22: 3.8685256 | AD22: 1.2231847 | AE22: 0.27126852 | AF22: 20.732694 | AG22: 0.24597648 | AH22: 3.8024772 | AI22: 3.4496217 | AJ22: 7.7191554 | AK22: 4.7045733 | AL22: 0.27590925 | AM22: 3.4587234 | AN22: 136.15684 | AO22: 5.9205161 | AP22: 0.39181833 | AQ22: 0.58217205 | AR22: 0.22057936 | AS22: 0.023721531 | AT22: 1.8234045 | AU22: 4.0979396 | AV22: 28.237925 | AW22: 3.7182722 | AX22: 90.253098 | AY22: 424.53236
A23: 2000 | B23: 1.2417402 | C23: 1.2524692 | D23: 1.0771679 | E23: 7.8626935 | F23: 0.8014602 | G23: 0.63750711 | H23: 0.22138513 | I23: 8.1418316 | J23: 0.28310671 | K23: 10.273098 | L23: 12.992484 | M23: 2.3004939 | N23: 6.2689816 | O23: 0.41241622 | P23: 11.243334 | Q23: 0.91088496 | R23: 0.80699224 | S23: 0.34464491 | T23: 2.2203011 | U23: 0.47028971 | V23: 0.77299547 | W23: 0.73493192 | X23: 0.51525477 | Y23: 0.38471754 | Z23: 23.460663 | AA23: 8.3850164 | AB23: 0.17769382 | AC23: 4.0718351 | AD23: 1.1629528 | AE23: 0.21457933 | AF23: 20.43121 | AG23: 0.33323349 | AH23: 3.4896983 | AI23: 3.6744645 | AJ23: 8.1856582 | AK23: 5.1535461 | AL23: 0.15247924 | AM23: 3.4653147 | AN23: 138.00733 | AO23: 4.5988917 | AP23: 0.48062262 | AQ23: 0.49039295 | AR23: 0.13449 | AS23: 0.025113936 | AT23: 2.4477887 | AU23: 4.4308357 | AV23: 27.09017 | AW23: 4.2046242 | AX23: 89.124123 | AY23: 425.56392
A24: 2001 | B24: 1.229626 | C24: 1.2044382 | D24: 0.8671286 | E24: 7.8309002 | F24: 0.77936548 | G24: 0.56352091 | H24: 0.22151976 | I24: 7.4366247 | J24: 0.22985233 | K24: 10.091556 | L24: 12.73594 | M24: 2.0210956 | N24: 6.4123287 | O24: 0.35518163 | P24: 10.001275 | Q24: 0.71003829 | R24: 0.83239202 | S24: 0.35020843 | T24: 2.4156995 | U24: 0.44883077 | V24: 0.7666214 | W24: 0.78110058 | X24: 0.41498863 | Y24: 0.36680719 | Z24: 22.988083 | AA24: 8.0272375 | AB24: 0.21559928 | AC24: 4.0819029 | AD24: 1.0009821 | AE24: 0.27470434 | AF24: 19.505 | AG24: 0.25656392 | AH24: 4.3535777 | AI24: 3.3350569 | AJ24: 8.119456 | AK24: 5.1788425 | AL24: 0.093859412 | AM24: 3.2283475 | AN24: 138.7317 | AO24: 4.1023444 | AP24: 0.5075386 | AQ24: 0.52891682 | AR24: 0.11766803 | AS24: 0.010693855 | AT24: 1.9186483 | AU24: 4.1968831 | AV24: 27.1566 | AW24: 4.3690055 | AX24: 84.732656 | AY24: 416.09891
A25: 2002 | B25: 1.3238016 | C25: 1.2429903 | D25: 1.0285467 | E25: 7.2120935 | F25: 0.46664961 | G25: 0.52752045 | H25: 0.1835105 | I25: 7.4487127 | J25: 0.20080839 | K25: 9.4731648 | L25: 11.517709 | M25: 1.7280266 | N25: 6.3019613 | O25: 0.27827588 | P25: 12.027469 | Q25: 0.99883919 | R25: 0.71906532 | S25: 0.3097366 | T25: 2.4999251 | U25: 0.35861638 | V25: 0.76034596 | W25: 0.69869756 | X25: 0.45786114 | Y25: 0.34571388 | Z25: 22.542564 | AA25: 9.5939436 | AB25: 0.14297448 | AC25: 3.9330662 | AD25: 0.90269636 | AE25: 0.22404751 | AF25: 20.402904 | AG25: 0.45573691 | AH25: 5.5975739 | AI25: 2.7960349 | AJ25: 8.2645699 | AK25: 5.8265534 | AL25: 0.12268484 | AM25: 3.2454874 | AN25: 131.83637 | AO25: 4.0127416 | AP25: 0.51293276 | AQ25: 0.48938797 | AR25: 0.088787079 | AS25: 0.017103831 | AT25: 2.2051589 | AU25: 4.6079797 | AV25: 26.143183 | AW25: 3.75595 | AX25: 89.648237 | AY25: 415.47871
A26: 2003 | B26: 1.4360411 | C26: 1.3434836 | D26: 0.93621957 | E26: 7.5059999 | F26: 0.57105911 | G26: 0.46381929 | H26: 0.22685474 | I26: 7.9397167 | J26: 0.23743906 | K26: 8.48847 | L26: 11.904888 | M26: 1.9199537 | N26: 6.2685697 | O26: 0.17191024 | P26: 10.602225 | Q26: 0.68072716 | R26: 0.72546447 | S26: 0.32366112 | T26: 2.8271753 | U26: 0.50706653 | V26: 0.8695613 | W26: 0.79904157 | X26: 0.52254796 | Y26: 0.30920214 | Z26: 22.231501 | AA26: 10.820557 | AB26: 0.15067018 | AC26: 4.1130991 | AD26: 0.85090163 | AE26: 0.33498534 | AF26: 21.354958 | AG26: 0.35623455 | AH26: 5.2914761 | AI26: 3.134738 | AJ26: 8.4142154 | AK26: 5.609558 | AL26: 0.21684978 | AM26: 3.0554251 | AN26: 137.85107 | AO26: 3.7609234 | AP26: 0.3500224 | AQ26: 0.58481689 | AR26: 0.16783063 | AS26: 0.018430694 | AT26: 2.4990858 | AU26: 4.2856275 | AV26: 26.497498 | AW26: 4.6957125 | AX26: 89.23892 | AY26: 423.4662
A27: 2004 | B27: 1.3633075 | C27: 1.396604 | D27: 0.65005859 | E27: 7.5586934 | F27: 0.37280042 | G27: 0.53884891 | H27: 0.12730018 | I27: 7.980533 | J27: 0.24517408 | K27: 9.1271912 | L27: 11.767568 | M27: 1.9415886 | N27: 6.2303707 | O27: 0.24585391 | P27: 11.313241 | Q27: 1.1319828 | R27: 0.72473673 | S27: 0.3117344 | T27: 2.5670262 | U27: 0.33713075 | V27: 0.84885582 | W27: 0.77998415 | X27: 0.5080345 | Y27: 0.32169489 | Z27: 21.258023 | AA27: 11.983333 | AB27: 0.13560709 | AC27: 4.1638461 | AD27: 0.5520755 | AE27: 0.39059313 | AF27: 23.377555 | AG27: 0.46206818 | AH27: 5.2897494 | AI27: 2.8203082 | AJ27: 8.6367858 | AK27: 6.1240995 | AL27: 0.18915418 | AM27: 2.7310228 | AN27: 134.61143 | AO27: 4.5124711 | AP27: 0.48506882 | AQ27: 0.49242825 | AR27: 0.15631049 | AS27: 0.02101713 | AT27: 2.8548331 | AU27: 4.2593103 | AV27: 26.242489 | AW27: 4.7031067 | AX27: 90.485076 | AY27: 425.32808
A28: 2005 | B28: 1.3951786 | C28: 1.3658 | D28: 0.68405656 | E28: 7.5983205 | F28: 0.59819462 | G28: 0.49462403 | H28: 0.15772012 | I28: 8.052033 | J28: 0.28764682 | K28: 8.9703435 | L28: 11.76641 | M28: 2.1155911 | N28: 5.9227596 | O28: 0.28852449 | P28: 10.035095 | Q28: 1.3603154 | R28: 0.84986249 | S28: 0.252825 | T28: 2.4365966 | U28: 0.29348198 | V28: 0.7410587 | W28: 0.68092964 | X28: 0.44328675 | Y28: 0.28409605 | Z28: 20.91306 | AA28: 9.665888 | AB28: 0.13335882 | AC28: 4.1687921 | AD28: 0.66062915 | AE28: 0.44304867 | AF28: 22.034631 | AG28: 0.45174283 | AH28: 6.0100998 | AI28: 2.6831304 | AJ28: 9.2056335 | AK28: 6.0518108 | AL28: 0.20587615 | AM28: 2.5154364 | AN28: 125.37006 | AO28: 4.7908426 | AP28: 0.50152866 | AQ28: 0.65861427 | AR28: 0.25305399 | AS28: 0.0092801211 | AT28: 3.0500634 | AU28: 4.4169199 | AV28: 26.68069 | AW28: 4.5403531 | AX28: 93.85837 | AY28: 416.34766
A29: 2006 | B29: 1.6776827 | C29: 1.4102261 | D29: 0.82673705 | E29: 7.9233256 | F29: 0.42718991 | G29: 0.54151384 | H29: 0.1651047 | I29: 8.0141549 | J29: 0.28227196 | K29: 8.9595334 | L29: 11.142395 | M29: 2.0550378 | N29: 6.0832415 | O29: 0.44430978 | P29: 9.1303872 | Q29: 1.0318847 | R29: 0.85108399 | S29: 0.31254395 | T29: 2.6943022 | U29: 0.20668089 | V29: 0.64688876 | W29: 0.75200937 | X29: 0.58055133 | Y29: 0.36593514 | Z29: 20.053726 | AA29: 11.980201 | AB29: 0.10402388 | AC29: 3.9486519 | AD29: 0.94327442 | AE29: 0.4071388 | AF29: 21.682215 | AG29: 0.3247537 | AH29: 5.9064807 | AI29: 2.7531573 | AJ29: 9.4574366 | AK29: 6.3575342 | AL29: 0.19469841 | AM29: 2.9105297 | AN29: 123.65144 | AO29: 4.6777262 | AP29: 0.52358321 | AQ29: 0.40412792 | AR29: 0.19231314 | AS29: 0.015479247 | AT29: 2.4848843 | AU29: 4.5765957 | AV29: 26.114594 | AW29: 4.654487 | AX29: 84.279698 | AY29: 405.12374
A30: 2007 | B30: 1.5485782 | C30: 1.395533 | D30: 0.77098018 | E30: 7.8106939 | F30: 0.33186656 | G30: 0.55369926 | H30: 0.1646911 | I30: 8.312236 | J30: 0.30096193 | K30: 8.9569336 | L30: 10.477436 | M30: 2.0448789 | N30: 6.2879438 | O30: 0.44634805 | P30: 10.156349 | Q30: 1.3943325 | R30: 0.85513085 | S30: 0.26642274 | T30: 2.7199912 | U30: 0.26917835 | V30: 1.0299874 | W30: 0.60619424 | X30: 0.50254829 | Y30: 0.39337138 | Z30: 18.37564 | AA30: 11.542505 | AB30: 0.097865138 | AC30: 4.0498222 | AD30: 0.98366954 | AE30: 0.45139366 | AF30: 22.635361 | AG30: 0.28344003 | AH30: 5.7896311 | AI30: 3.0304288 | AJ30: 9.3643227 | AK30: 5.8565452 | AL30: 0.18013464 | AM30: 2.7084082 | AN30: 124.34935 | AO30: 4.9667032 | AP30: 0.51905351 | AQ30: 0.48577432 | AR30: 0.18196555 | AS30: 0.010988567 | AT30: 2.4236556 | AU30: 4.1253599 | AV30: 26.053411 | AW30: 5.0900309 | AX30: 87.902579 | AY30: 409.05433
A31: 2008 | B31: 1.536883 | C31: 1.4815874 | D31: 0.73628547 | E31: 7.3870541 | F31: 0.47164661 | G31: 0.53488515 | H31: 0.18419999 | I31: 8.7307869 | J31: 0.32334531 | K31: 8.9881327 | L31: 10.563825 | M31: 2.014759 | N31: 6.2226889 | O31: 0.33863146 | P31: 9.9317921 | Q31: 0 | R31: 0.77653373 | S31: 0.21427061 | T31: 2.7649058 | U31: 0.20119297 | V31: 1.0516746 | W31: 0.46967322 | X31: 0.41633482 | Y31: 0.38189369 | Z31: 16.849552 | AA31: 10.406753 | AB31: 0.12415441 | AC31: 3.9074103 | AD31: 0.99394868 | AE31: 0.44916993 | AF31: 21.693139 | AG31: 0.23 | AH31: 5.7578437 | AI31: 2.9324092 | AJ31: 9.4721644 | AK31: 6.1913232 | AL31: 0.17740356 | AM31: 2.7571174 | AN31: 118.28555 | AO31: 4.6774003 | AP31: 0.51007165 | AQ31: 0.65280605 | AR31: 0.24853499 | AS31: 0.0069968076 | AT31: 2.558338 | AU31: 4.1458613 | AV31: 24.998267 | AW31: 5.0688895 | AX31: 85.623984 | AY31: 394.44207
... A46: 2023 | B46: 1.1521747 | C46: 1.5832905 | D46: 0.27528021 | E46: 4.983105 | F46: 0.52619792 | G46: 1.4324435 | H46: 0.099356776 | I46: 8.4168675 | J46: 1.281661 | K46: 6.3536729 | L46: 10.13618 | M46: 2.584998 | N46: 4.6490801 | O46: 1.4438038 | P46: 11.650783 | Q46: 3.8204095 | R46: 0.98595361 | S46: 0.21197667 | T46: 2.0249773 | U46: 0.20165257 | V46: 1.2486295 | W46: 0.57472705 | X46: 0.34524723 | Y46: 0.84239024 | Z46: 13.154749 | AA46: 17.880828 | AB46: 0.092863227 | AC46: 3.5430186 | AD46: 0.61398486 | AE46: 0.6377096 | AF46: 22.689234 | AG46: 1.32482e-05 | AH46: 12.606657 | AI46: 1.8172362 | AJ46: 10.85162 | AK46: 7.6486386 | AL46: 0.1253232 | AM46: 2.2041053 | AN46: 116.15247 | AO46: 5.7916389 | AP46: 0.99655881 | AQ46: 0.20929919 | AR46: 0.25844135 | AS46: 0.036711789 | AT46: 2.9499173 | AU46: 5.2267052 | AV46: 18.058636 | AW46: 5.2706073 | AX46: 71.850119 | AY46: 387.49194
A47: 2024 | B47: 1.1374669 | C47: 1.4951891 | D47: 0.25565821 | E47: 4.3221444 | F47: 0.51892503 | G47: 1.8799281 | H47: 0.092998523 | I47: 7.9825164 | J47: 1.4051895 | K47: 6.455015 | L47: 8.8229203 | M47: 2.5560014 | N47: 4.717101 | O47: 1.3169734 | P47: 10.761023 | Q47: 3.1339494 | R47: 1.0301793 | S47: 0.21181832 | T47: 1.9676982 | U47: 0.25272611 | V47: 1.2463787 | W47: 0.55879238 | X47: 0.36868744 | Y47: 0.35665802 | Z47: 12.398241 | AA47: 16.169088 | AB47: NA | AC47: 3.3136457 | AD47: 0.41365095 | AE47: 0.70582218 | AF47: 22.937444 | AG47: 0.11184839 | AH47: 12.906797 | AI47: 1.6724451 | AJ47: 10.825994 | AK47: 7.835532 | AL47: 0.13386565 | AM47: 3.1559024 | AN47: 116.29635 | AO47: 5.1343853 | AP47: 0.96517433 | AQ47: 0.27525762 | AR47: 0.3013793 | AS47: NA | AT47: 2.1291619 | AU47: 5.140522 | AV47: 14.972304 | AW47: 5.5184446 | AX47: 67.363681 | AY47: 373.52288
A48: NA = Not available. Most recent year is preliminary. Totals may not sum due to rounding.
A49: 1/ Unit of measure is pounds per person.
A50: 2/ Other processing includes all other canned and frozen vegetables for processing except potatoes, sweet potatoes, and dry pulse crops. Beginning with 2017, also includes miscellaneous vegetables for dehydrating.
A51: Source: USDA, Economic Research Service.

Sheet Table 2a-PerCapitaAvail, Fresh
A1: Table 2a--Vegetables, fresh market (including mushrooms and sweet potatoes): Selected U.S. per capita availability/1,2 | O1: =HYPERLINK("#'"&"Index'!A1","INDEX") -> INDEX
A2: Year | B2: Artichoke/3 | C2: Asparagus | D2: Beans, snap green | E2: Broccoli | F2: Cabbage | G2: Carrot | H2: Cauliflower | I2: Celery/3 | J2: Cucumber | K2: Eggplant/3 | L2: Escarole /Endive | M2: Garlic/3 | N2: Greens, southern and other leafy/4 | O2: Lettuce, head | P2: Lettuce, leaf/ romaine | Q2: Mushrooms | R2: Onions | S2: Peppers, bell/3 | T2: Pumpkin | U2: Radish | V2: Spinach | W2: Squash | X2: Sweet corn | Y2: Sweet potatoes, all uses | Z2: Tomato/5 | AA2: Other fresh vegetables, all/6 | AB2: Fresh vegetables, total
A3: 1980 | B3: 0.587 | C3: 0.294 | D3: 1.315 | E3: 1.401 | F3: 7.997 | G3: 6.151 | H3: 1.134 | I3: 7.372 | J3: 3.862 | K3: 0.477 | L3: 0.451 | M3: 0.861 | N3: NA | O3: 25.745 | P3: NA | Q3: 1.137 | R3: 11.383 | S3: 2.885 | T3: NA | U3: 0.565 | V3: 0.444 | W3: 2.308 | X3: 6.498 | Y3: 4.387 | Z3: 12.88 | AA3: 0.596 | AB3: 100.73
A4: 1981 | B4: 0.748 | C4: 0.31 | D4: 1.257 | E4: 1.657 | F4: 8.152 | G4: 6.119 | H4: 1.368 | I4: 7.272 | J4: 4 | K4: 0.458 | L4: 0.443 | M4: 0.659 | N4: NA | O4: 25.028 | P4: NA | Q4: 1.203 | R4: 10.734 | S4: 2.786 | T4: NA | U4: 0.575 | V4: 0.527 | W4: 2.325 | X4: 6.233 | Y4: 4.672 | Z4: 12.451 | AA4: 0.707 | AB4: 99.684
A5: 1982 | B5: 0.823 | C5: 0.377 | D5: 1.26 | E5: 1.987 | F5: 8.557 | G5: 6.603 | H5: 1.327 | I5: 7.412 | J5: 4.186 | K5: 0.514 | L5: 0.377 | M5: 0.757 | N5: NA | O5: 25.024 | P5: NA | Q5: 1.386 | R5: 12.244 | S5: 2.972 | T5: NA | U5: 0.501 | V5: 0.55 | W5: 2.457 | X5: 6.018 | Y5: 5.393 | Z5: 13.006 | AA5: 0.635 | AB5: 104.366
A6: 1983 | B6: 0.735 | C6: 0.432 | D6: 1.239 | E6: 2.031 | F6: 8.206 | G6: 6.49 | H6: 1.415 | I6: 7.001 | J6: 4.537 | K6: 0.513 | L6: 0.395 | M6: 0.997 | N6: NA | O6: 22.525 | P6: NA | Q6: 1.449 | R6: 12.165 | S6: 3.326 | T6: NA | U6: 0.547 | V6: 0.513 | W6: 2.556 | X6: 6.145 | Y6: 4.485 | Z6: 13.565 | AA6: 0.746 | AB6: 102.013
A7: 1984 | B7: 0.955 | C7: 0.406 | D7: 1.343 | E7: 2.458 | F7: 8.568 | G7: 6.684 | H7: 1.824 | I7: 7.115 | J7: 4.653 | K7: 0.469 | L7: 0.387 | M7: 0.769 | N7: NA | O7: 24.989 | P7: NA | Q7: 1.654 | R7: 13.077 | S7: 3.625 | T7: NA | U7: 0.495 | V7: 0.53 | W7: 2.625 | X7: 6.436 | Y7: 4.832 | Z7: 14.29 | AA7: 0.752 | AB7: 108.936
A8: 1985 | B8: 1.023 | C8: 0.465 | D8: 1.26 | E8: 2.579 | F8: 8.737 | G8: 6.491 | H8: 1.839 | I8: 6.88 | J8: 4.394 | K8: 0.458 | L8: 0.389 | M8: 1.062 | N8: NA | O8: 23.751 | P8: 3.265 | Q8: 1.773 | R8: 13.624 | S8: 3.8 | T8: NA | U8: 0.512 | V8: 0.674 | W8: 2.672 | X8: 6.413 | Y8: 5.26 | Z8: 14.901 | AA8: 0.711 | AB8: 112.933
A9: 1986 | B9: 0.935 | C9: 0.603 | D9: 1.256 | E9: 3.047 | F9: 8.641 | G9: 6.484 | H9: 2.185 | I9: 6.493 | J9: 4.625 | K9: 0.467 | L9: 0.366 | M9: 0.766 | N9: NA | O9: 22.008 | P9: 2.374 | Q9: 1.785 | R9: 13.736 | S9: 3.965 | T9: NA | U9: 0.464 | V9: 0.585 | W9: 2.775 | X9: 6.061 | Y9: 4.262 | Z9: 15.912 | AA9: 0.612 | AB9: 110.407
A10: 1987 | B10: 0.993 | C10: 0.566 | D10: 1.217 | E10: 3.088 | F10: 9.078 | G10: 8.296 | H10: 2.132 | I10: 6.594 | J10: 5.067 | K10: 0.473 | L10: 0.341 | M10: 1.188 | N10: NA | O10: 25.797 | P10: 2.525 | Q10: 1.892 | R10: 13.411 | S10: 4.229 | T10: 3.014 | U10: 0.513 | V10: 0.583 | W10: 2.879 | X10: 6.262 | Y10: 4.302 | Z10: 15.963 | AA10: 0.472 | AB10: 120.875
A11: 1988 | B11: 0.915 | C11: 0.582 | D11: 1.19 | E11: 3.774 | F11: 9.007 | G11: 7.094 | H11: 2.194 | I11: 7.153 | J11: 4.824 | K11: 0.39 | L11: 0.358 | M11: 1.086 | N11: NA | O11: 27.167 | P11: 3.201 | Q11: 1.935 | R11: 14.549 | S11: 4.476 | T11: 3.806 | U11: 0.55 | V11: 0.596 | W11: 3.077 | X11: 5.819 | Y11: 3.931 | Z11: 16.943 | AA11: 0.671 | AB11: 125.288
A12: 1989 | B12: 0.974 | C12: 0.57 | D12: 1.194 | E12: 3.804 | F12: 8.603 | G12: 8.086 | H12: 2.311 | I12: 7.474 | J12: 4.784 | K12: 0.399 | L12: 0.33 | M12: 1.015 | N12: NA | O12: 28.685 | P12: 3.563 | Q12: 1.992 | R12: 14.763 | S12: 4.689 | T12: 4.82 | U12: 0.708 | V12: 0.642 | W12: 3.452 | X12: 6.528 | Y12: 3.925 | Z12: 16.843 | AA12: 0.775 | AB12: 130.929
A13: 1990 | B13: 0.846 | C13: 0.587 | D13: 1.069 | E13: 3.368 | F13: 8.337 | G13: 8.291 | H13: 2.191 | I13: 7.194 | J13: 4.674 | K13: 0.399 | L13: 0.262 | M13: 1.407 | N13: NA | O13: 27.747 | P13: 3.77 | Q13: 2.054 | R13: 15.06 | S13: 5.881 | T13: 4.433 | U13: 0.659 | V13: 0.756 | W13: 3.506 | X13: 6.742 | Y13: 4.399 | Z13: 15.523 | AA13: 0.561 | AB13: 129.716
A14: 1991 | B14: 0.827 | C14: 0.601 | D14: 1.123 | E14: 3.043 | F14: 8.204 | G14: 7.713 | H14: 1.952 | I14: 6.733 | J14: 4.558 | K14: 0.411 | L14: 0.247 | M14: 1.487 | N14: NA | O14: 26.045 | P14: 3.997 | Q14: 2.005 | R14: 15.687 | S14: 6.301 | T14: 4.429 | U14: 0.548 | V14: 0.804 | W14: 3.672 | X14: 5.908 | Y14: 3.867 | Z14: 15.361 | AA14: 0.545 | AB14: 126.068
A15: 1992 | B15: 0.879 | C15: 0.596 | D15: 1.447 | E15: 3.416 | F15: 8.663 | G15: 8.29 | H15: 1.807 | I15: 7.323 | J15: 4.928 | K15: 0.47 | L15: 0.32 | M15: 1.461 | N15: NA | O15: 25.791 | P15: 4.67 | Q15: 1.938 | R15: 16.101 | S15: 7.102 | T15: 4.058 | U15: 0.476 | V15: 0.817 | W15: 3.806 | X15: 6.869 | Y15: 4.076 | Z15: 15.446 | AA15: 0.613 | AB15: 131.363
A16: 1993 | B16: 0.864 | C16: 0.567 | D16: 1.515 | E16: 3.333 | F16: 9.323 | G16: 10.847 | H16: 2.091 | I16: 7.261 | J16: 5.212 | K16: 0.471 | L16: 0.3 | M16: 1.746 | N16: NA | O16: 24.4 | P16: 5.042 | Q16: 1.998 | R16: 17.174 | S16: 7.631 | T16: 5.126 | U16: 0.517 | V16: 0.665 | W16: 3.785 | X16: 6.977 | Y16: 3.66 | Z16: 16.303 | AA16: 0.769 | AB16: 137.577
A17: 1994 | B17: 1.266 | C17: 0.559 | D17: 1.539 | E17: 4.43 | F17: 9.082 | G17: 12.677 | H17: 2.021 | I17: 7.237 | J17: 5.363 | K17: 0.516 | L17: 0.329 | M17: 1.797 | N17: NA | O17: 25.007 | P17: 5.678 | Q17: 1.986 | R17: 16.918 | S17: 7.059 | T17: 5.491 | U17: 0.436 | V17: 0.752 | W17: 3.93 | X17: 8.155 | Y17: 4.463 | Z17: 16.212 | AA17: 0.624 | AB17: 143.527
A18: 1995 | B18: 0.925 | C18: 0.557 | D18: 1.636 | E18: 4.307 | F18: 8.123 | G18: 11.191 | H18: 1.637 | I18: 6.934 | J18: 5.609 | K18: 0.473 | L18: 0.304 | M18: 1.85 | N18: NA | O18: 22.167 | P18: 5.895 | Q18: 2.033 | R18: 17.781 | S18: 7.011 | T18: 5.896 | U18: 0.414 | V18: 0.671 | W18: 3.746 | X18: 7.823 | Y18: 4.208 | Z18: 16.842 | AA18: 0.78 | AB18: 138.813
A19: 1996 | B19: 0.989 | C19: 0.578 | D19: 1.452 | E19: 4.516 | F19: 8.258 | G19: 12.37 | H19: 1.721 | I19: 7.027 | J19: 5.93 | K19: 0.599 | L19: 0.319 | M19: 2.295 | N19: NA | O19: 21.575 | P19: 5.818 | Q19: 2.036 | R19: 18.323 | S19: 8.069 | T19: 5.775 | U19: 0.407 | V19: 0.628 | W19: 3.69 | X19: 8.326 | Y19: 4.287 | Z19: 17.403 | AA19: 0.704 | AB19: 143.095
A20: 1997 | B20: 1.01 | C20: 0.659 | D20: 1.35 | E20: 4.965 | F20: 9.013 | G20: 14.114 | H20: 1.765 | I20: 6.549 | J20: 6.423 | K20: 0.65 | L20: 0.299 | M20: 1.995 | N20: 2.429 | O20: 23.902 | P20: 6.595 | Q20: 2.092 | R20: 18.839 | S20: 7.334 | T20: 5.648 | U20: 0.506 | V20: 1.107 | W20: 3.85 | X20: 8.29 | Y20: 4.261 | Z20: 17.295 | AA20: 0.507 | AB20: 151.447
A21: 1998 | B21: 1.18 | C21: 0.731 | D21: 1.641 | E21: 5.045 | F21: 8.428 | G21: 9.527 | H21: 1.459 | I21: 6.467 | J21: 6.49 | K21: 0.7 | L21: 0.304 | M21: 2.584 | N21: 2.391 | O21: 22.325 | P21: 6.615 | Q21: 2.328 | R21: 18.4 | S21: 7.763 | T21: 6.357 | U21: 0.445 | V21: 0.97 | W21: 4.16 | X21: 9.334 | Y21: 3.848 | Z21: 18.497 | AA21: 0.583 | AB21: 148.572
A22: 1999 | B22: 1.321 | C22: 0.894 | D22: 1.895 | E22: 6.159 | F22: 7.554 | G22: 9.253 | H22: 1.764 | I22: 6.532 | J22: 6.729 | K22: 0.666 | L22: 0.225 | M22: 3.292 | N22: 2.367 | O22: 24.909 | P22: 7.592 | Q22: 2.464 | R22: 18.478 | S22: 7.719 | T22: 5.921 | U22: 0.392 | V22: 0.972 | W22: 4.098 | X22: 9.095 | Y22: 3.718 | Z22: 19.068 | AA22: 0.554 | AB22: 153.631
A23: 2000 | B23: 1.242 | C23: 0.957 | D23: 2.016 | E23: 5.888 | F23: 8.9 | G23: 9.204 | H23: 1.737 | I23: 6.269 | J23: 6.351 | K23: 0.807 | L23: 0.345 | M23: 2.22 | N23: 2.408 | O23: 23.461 | P23: 8.385 | Q23: 2.492 | R23: 18.874 | S23: 8.186 | T23: 4.599 | U23: 0.481 | V23: 1.375 | W23: 4.431 | X23: 9.04 | Y23: 4.205 | Z23: 18.985 | AA23: 0.547 | AB23: 153.405
A24: 2001 | B24: 1.23 | C24: 0.92 | D24: 2.165 | E24: 5.399 | F24: 8.828 | G24: 9.38 | H24: 1.519 | I24: 6.412 | J24: 6.268 | K24: 0.832 | L24: 0.35 | M24: 2.416 | N24: 2.33 | O24: 22.988 | P24: 8.027 | Q24: 2.591 | R24: 18.468 | S24: 8.119 | T24: 4.102 | U24: 0.508 | V24: 1.073 | W24: 4.197 | X24: 9.173 | Y24: 4.369 | Z24: 19.203 | AA24: 0.558 | AB24: 151.425
A25: 2002 | B25: 1.324 | C25: 0.964 | D25: 2.093 | E25: 5.351 | F25: 8.295 | G25: 8.417 | H25: 1.425 | I25: 6.302 | J25: 6.623 | K25: 0.719 | L25: 0.31 | M25: 2.5 | N25: 2.263 | O25: 22.543 | P25: 9.594 | Q25: 2.582 | R25: 19.323 | S25: 8.265 | T25: 4.013 | U25: 0.513 | V25: 1.431 | W25: 4.608 | X25: 8.974 | Y25: 3.756 | Z25: 20.311 | AA25: 0.494 | AB25: 152.993
A26: 2003 | B26: 1.436 | C26: 1.043 | D26: 1.967 | E26: 5.347 | F26: 7.397 | G26: 8.779 | H26: 1.559 | I26: 6.269 | J26: 6.158 | K26: 0.725 | L26: 0.324 | M26: 2.827 | N26: 2.5 | O26: 22.232 | P26: 10.821 | Q26: 2.62 | R26: 19.507 | S26: 8.414 | T26: 3.761 | U26: 0.35 | V26: 1.607 | W26: 4.286 | X26: 9.166 | Y26: 4.696 | Z26: 19.412 | AA26: 0.633 | AB26: 153.836
A27: 2004 | B27: 1.363 | C27: 1.125 | D27: 1.882 | E27: 5.314 | F27: 8.043 | G27: 8.721 | H27: 1.559 | I27: 6.23 | J27: 6.43 | K27: 0.725 | L27: 0.312 | M27: 2.567 | N27: 2.459 | O27: 21.258 | P27: 11.983 | Q27: 2.644 | R27: 21.917 | S27: 8.637 | T27: 4.512 | U27: 0.485 | V27: 1.845 | W27: 4.259 | X27: 8.962 | Y27: 4.703 | Z27: 19.95 | AA27: 0.702 | AB27: 158.587
A28: 2005 | B28: 1.395 | C28: 1.116 | D28: 1.801 | E28: 5.342 | F28: 7.757 | G28: 8.665 | H28: 1.751 | I28: 5.923 | J28: 6.193 | K28: 0.85 | L28: 0.253 | M28: 2.437 | N28: 2.149 | O28: 20.913 | P28: 9.666 | Q28: 2.608 | R28: 20.897 | S28: 9.206 | T28: 4.791 | U28: 0.502 | V28: 2.329 | W28: 4.417 | X28: 8.652 | Y28: 4.54 | Z28: 20.151 | AA28: 0.764 | AB28: 155.068
A29: 2006 | B29: 1.678 | C29: 1.134 | D29: 2.08 | E29: 5.761 | F29: 7.751 | G29: 8.108 | H29: 1.697 | I29: 6.083 | J29: 6.14 | K29: 0.851 | L29: 0.313 | M29: 2.694 | N29: 2.345 | O29: 20.054 | P29: 11.98 | Q29: 2.638 | R29: 19.916 | S29: 9.457 | T29: 4.678 | U29: 0.524 | V29: 1.962 | W29: 4.577 | X29: 8.326 | Y29: 4.654 | Z29: 19.77 | AA29: 0.725 | AB29: 155.896
A30: 2007 | B30: 1.549 | C30: 1.161 | D30: 2.198 | E30: 5.636 | F30: 7.951 | G30: 8.05 | H30: 1.68 | I30: 6.288 | J30: 6.423 | K30: 0.855 | L30: 0.266 | M30: 2.72 | N30: 2.532 | O30: 18.376 | P30: 11.543 | Q30: 2.569 | R30: 21.612 | S30: 9.364 | T30: 4.967 | U30: 0.519 | V30: 1.614 | W30: 4.125 | X30: 9.225 | Y30: 5.09 | Z30: 19.208 | AA30: 0.78 | AB30: 156.301
A31: 2008 | B31: 1.537 | C31: 1.185 | D31: 1.987 | E31: 6.035 | F31: 8.051 | G31: 8.067 | H31: 1.572 | I31: 6.223 | J31: 6.388 | K31: 0.777 | L31: 0.214 | M31: 2.765 | N31: 2.32 | O31: 16.85 | P31: 10.407 | Q31: 2.47 | R31: 20.185 | S31: 9.472 | T31: 4.677 | U31: 0.51 | V31: 1.708 | W31: 4.146 | X31: 9.012 | Y31: 5.069 | Z31: 18.514 | AA31: 0.793 | AB31: 150.934
... A47: 2024 | B47: 1.137 | C47: 1.433 | D47: 1.315 | E47: 5.596 | F47: 5.539 | G47: 7.066 | H47: 2.074 | I47: 4.717 | J47: 8.318 | K47: 1.03 | L47: 0.212 | M47: 1.968 | N47: 2.531 | O47: 12.398 | P47: 16.169 | Q47: 2.275 | R47: 21.257 | S47: 10.826 | T47: 5.134 | U47: 0.965 | V47: 1.541 | W47: 5.141 | X47: 4.565 | Y47: 5.518 | Z47: 19.102 | AA47: 2.117 | AB47: 149.944
A48: NA = Not available. Most recent year is preliminary. Totals may not sum due to rounding.
A49: 1/ Unit of measure is pounds per person.
A50: 2/ Excludes potatoes.
A51: 3/ Includes fresh and dual use, which includes both fresh and processing.
A52: 4/ Collards, kale, mustard greens, and turnip greens.
A53: 5/ After 1996, includes an USDA, ERS estimate of domestically produced hothouse tomatoes. Hothouse tomato imports are included in all years.
A54: 6/ Other includes brussels sprouts, okra, and fresh green limas.
A55: Source: USDA, Economic Research Service.

Sheet Table 2b-PerCapitaAvail, Pr
A1: Table 2b--Vegetables, processing: Selected U.S. per capita availability/1 | O1: =HYPERLINK("#'"&"Index'!A1","INDEX") -> INDEX
A2: Year | B2: Asparagus, processing | C2: Beans, green lima, processing | D2: Beans, snap green, processing | E2: Beets, processing | F2: Broccoli, processing | G2: Cabbage, processing | H2: Carrots, processing | I2: Cauliflower, processing | J2: Corn, sweet, processing | K2: Cucumbers, processing | L2: Mushrooms, processing | M2: Onions, dehydrating/2 | N2: Peas, green, processing | O2: Peppers, chili/3 | P2: Spinach, processing | Q2: Tomatoes, processing | R2: Other, processing/4 | S2: Processing, total/5
A3: 1980 | B3: 0.492 | C3: 0.65 | D3: 5.917 | E3: 1.82 | F3: 1.455 | G3: 1.986 | H3: 3.474 | I3: 0.782 | J3: 19.433 | K3: 5.397 | L3: 1.744 | M3: 0.771 | N3: 4.467 | O3: 3.049 | P3: 1.363 | Q3: 64.102 | R3: 1.461 | S3: 118.363
A4: 1981 | B4: 0.485 | C4: 0.69 | D4: 6.306 | E4: 1.614 | F4: 1.564 | G4: 2.027 | H4: 3.445 | I4: 0.91 | J4: 18.416 | K4: 5.344 | L4: 1.536 | M4: 0.821 | N4: 4.434 | O4: 3.268 | P4: 1.266 | Q4: 59.804 | R4: 1.566 | S4: 113.496
A5: 1982 | B5: 0.343 | C5: 0.571 | D5: 5.73 | E5: 1.345 | F5: 1.517 | G5: 1.697 | H5: 2.941 | I5: 0.895 | J5: 17.348 | K5: 5.107 | L5: 1.542 | M5: 2.004 | N5: 4.138 | O5: 3.055 | P5: 1.126 | Q5: 60.406 | R5: 1.554 | S5: 111.319
A6: 1983 | B6: 0.406 | C6: 0.465 | D6: 5.54 | E6: 1.258 | F6: 1.568 | G6: 2.078 | H6: 3.049 | I6: 0.848 | J6: 18.273 | K6: 5.156 | L6: 1.519 | M6: 1.657 | N6: 4.211 | O6: 3.309 | P6: 1.087 | Q6: 61.173 | R6: 1.634 | S6: 113.231
A7: 1984 | B7: 0.406 | C7: 0.682 | D7: 5.491 | E7: 1.244 | F7: 1.743 | G7: 1.698 | H7: 3.98 | I7: 0.95 | J7: 18.202 | K7: 5.227 | L7: 1.814 | M7: 1.484 | N7: 4.027 | O7: 3.614 | P7: 0.833 | Q7: 68.74 | R7: 1.373 | S7: 121.508
A8: 1985 | B8: 0.397 | C8: 0.572 | D8: 5.63 | E8: 0.874 | F8: 1.961 | G8: 1.592 | H8: 3.17 | I8: 0.928 | J8: 19.794 | K8: 5.826 | L8: 1.769 | M8: 1.573 | N8: 4.143 | O8: 3.911 | P8: 1.049 | Q8: 63.386 | R8: 1.391 | S8: 117.966
A9: 1986 | B9: 0.387 | C9: 0.595 | D9: 5.378 | E9: 1.061 | F9: 1.785 | G9: 1.551 | H9: 2.982 | I9: 0.926 | J9: 19.646 | K9: 5.326 | L9: 1.818 | M9: 1.891 | N9: 4.08 | O9: 4.175 | P9: 0.899 | Q9: 63.931 | R9: 1.626 | S9: 118.057
A10: 1987 | B10: 0.381 | C10: 0.539 | D10: 5.434 | E10: 0.762 | F10: 2.216 | G10: 1.611 | H10: 3.141 | I10: 0.945 | J10: 18.47 | K10: 5.535 | L10: 1.889 | M10: 1.519 | N10: 3.731 | O10: 4.165 | P10: 0.774 | Q10: 65.49 | R10: 1.587 | S10: 118.189
A11: 1988 | B11: 0.455 | C11: 0.432 | D11: 5.503 | E11: 0.888 | F11: 2.416 | G11: 1.434 | H11: 3.359 | I11: 0.944 | J11: 19.1 | K11: 5.279 | L11: 1.651 | M11: 1.668 | N11: 3.657 | O11: 4.315 | P11: 0.928 | Q11: 61.675 | R11: 2.014 | S11: 115.718
A12: 1989 | B12: 0.38 | C12: 0.393 | D12: 5.881 | E12: 0.815 | F12: 2.169 | G12: 1.283 | H12: 3.384 | I12: 0.751 | J12: 17.907 | K12: 5.19 | L12: 1.551 | M12: 1.614 | N12: 3.71 | O12: 4.504 | P12: 0.771 | Q12: 69.397 | R12: 1.848 | S12: 121.548
A13: 1990 | B13: 0.419 | C13: 0.34 | D13: 5.632 | E13: 0.855 | F13: 2.233 | G13: 1.194 | H13: 4.085 | I13: 0.758 | J13: 19.548 | K13: 4.994 | L13: 1.537 | M13: 2.134 | N13: 4.162 | O13: 4.831 | P13: 0.565 | Q13: 75.313 | R13: 2.532 | S13: 131.132
A14: 1991 | B14: 0.368 | C14: 0.409 | D14: 5.866 | E14: 0.76 | F14: 2.252 | G14: 1.435 | H14: 3.567 | I14: 0.582 | J14: 20.425 | K14: 5.056 | L14: 1.71 | M14: 1.572 | N14: 4.154 | O14: 4.513 | P14: 0.994 | Q14: 77.109 | R14: 2.89 | S14: 133.662
... A47: 2024 | B47: 0.062 | C47: 0.249 | D47: 3.007 | E47: 0.519 | F47: 2.386 | G47: 0.916 | H47: 1.757 | I47: 0.482 | J47: 10.407 | K47: 2.443 | L47: 1.039 | M47: 1.68 | N47: 1.672 | O47: 7.836 | P47: 0.588 | Q47: 48.261 | R47: 12.907 | S47: 96.211
A48: Most recent year is preliminary. Totals may not sum due to rounding.
A49: 1/ Unit of measure is pounds per person.
A50: 2/ Excludes onions used for canning and freezing.
A51: 3/ Includes use expressed on a fresh-weight equivalent basis.
A52: 4/ Includes all other canned and frozen vegetables for processing except potatoes, sweet potatoes, and dry pulse crops. Beginning with 2017, also includes miscellaneous vegetables for dehydrating.
A53: 5/ Excludes potatoes, sweet potatoes, and dry pulse crops.
A54: Source: USDA, Economic Research Service.

Sheet Table 2c-PerCapitaAvail, Potato
A1: Table 2c--Potatoes: U.S. per capita availability/1 | O1: =HYPERLINK("#'"&"Index'!A1","INDEX") -> INDEX
A2: Year | B2: Fresh potatoes | C2: Canning potatoes | D2: Chipping potatoes | E2: Dehydrating potatoes | F2: Freezing potatoes | G2: Processing potatoes, total | H2: All potatoes
A3: 1970 | B3: 61.8 | C3: 1.964 | D3: 17.4 | E3: 12 | F3: 28.5 | G3: 59.864 | H3: 121.664
A4: 1971 | B4: 56.1 | C4: 2.121 | D4: 17.2 | E4: 12.3 | F4: 30.1 | G4: 61.721 | H4: 117.821
A5: 1972 | B5: 57.9 | C5: 2.113 | D5: 16.7 | E5: 12.4 | F5: 30.3 | G5: 61.513 | H5: 119.413
A6: 1973 | B6: 52.4 | C6: 2.244 | D6: 16.3 | E6: 13.1 | F6: 34.2 | G6: 65.844 | H6: 118.244
A7: 1974 | B7: 49.4 | C7: 2.296 | D7: 15.7 | E7: 14.5 | F7: 35.3 | G7: 67.796 | H7: 117.196
A8: 1975 | B8: 52.6 | C8: 1.999 | D8: 15.5 | E8: 14.7 | F8: 37.1 | G8: 69.299 | H8: 121.899
A9: 1976 | B9: 49.4 | C9: 1.947 | D9: 15.8 | E9: 16.3 | F9: 41.8 | G9: 75.847 | H9: 125.247
A10: 1977 | B10: 50.1 | C10: 2.212 | D10: 16.2 | E10: 11.4 | F10: 42.2 | G10: 72.012 | H10: 122.112
A11: 1978 | B11: 46 | C11: 2.26 | D11: 16.5 | E11: 12.1 | F11: 42.6 | G11: 73.46 | H11: 119.46
A12: 1979 | B12: 49.3 | C12: 2.114 | D12: 16.7 | E12: 11.2 | F12: 38.5 | G12: 68.514 | H12: 117.814
A13: 1980 | B13: 51.122 | C13: 1.927 | D13: 16.5 | E13: 9.8 | F13: 35.405 | G13: 63.632 | H13: 114.754
A14: 1981 | B14: 45.845 | C14: 1.786 | D14: 16.6 | E14: 10.8 | F14: 41.486 | G14: 70.672 | H14: 116.517
... A57: 2024 | B57: 28.52 | C57: 0.293 | D57: 17.403 | E57: 11.09 | F57: 58.99 | G57: 87.776 | H57: 116.296
A58: Most recent year is preliminary.
A59: 1/ Unit of measure is pounds per person.
A60: Source: USDA, Economic Research Service.

Sheet Table 2d-PerCapitaAvail, Pulse
A1: Table 2d--Selected dry pulse crops: U.S. per capita availability/1 | O1: =HYPERLINK("#'"&"Index'!A1","INDEX") -> INDEX
A2: Year | B2: Black beans | C2: Blackeye beans | D2: Chickpeas (garbanzo) | E2: Great Northern beans | F2: Lima beans, all | G2: Navy beans | H2: Pink beans | I2: Pinto beans | J2: Red kidney beans, all | K2: Small red beans | L2: Other beans/2 | M2: All dry edible beans | N2: Dry bean total, less garbanzo | O2: Dry peas and lentils | P2: All dry pulses
A3: 1970 | B3: 0.006 | C3: NA | D3: NA | E3: 0.389 | F3: 0.357 | G3: 1.687 | H3: NA | I3: 2.242 | J3: 0.445 | K3: NA | L3: 1.117 | M3: 6.243 | N3: 6.243 | O3: 0.713 | P3: 6.956
A4: 1971 | B4: 0.03 | C4: NA | D4: NA | E4: 0.455 | F4: 0.306 | G4: 1.775 | H4: NA | I4: 2.453 | J4: 0.548 | K4: NA | L4: 1.187 | M4: 6.754 | N4: 6.754 | O4: 0.656 | P4: 7.41
A5: 1972 | B5: 0.025 | C5: NA | D5: NA | E5: 0.367 | F5: 0.258 | G5: 1.844 | H5: NA | I5: 1.955 | J5: 0.29 | K5: NA | L5: 1.026 | M5: 5.765 | N5: 5.765 | O5: 0.791 | P5: 6.556
A6: 1973 | B6: 0.01 | C6: NA | D6: NA | E6: 0.404 | F6: 0.339 | G6: 2.363 | H6: NA | I6: 2.485 | J6: 0.448 | K6: NA | L6: 1.391 | M6: 7.44 | N6: 7.44 | O6: 0.546 | P6: 7.986
A7: 1974 | B7: 0.024 | C7: NA | D7: NA | E7: 0.566 | F7: 0.38 | G7: 1.22 | H7: NA | I7: 1.317 | J7: 0.5 | K7: NA | L7: 1.477 | M7: 5.484 | N7: 5.484 | O7: 0.69 | P7: 6.174
A8: 1975 | B8: 0.026 | C8: NA | D8: NA | E8: 0.588 | F8: 0.411 | G8: 2.302 | H8: NA | I8: 1.682 | J8: 0.509 | K8: NA | L8: 1.269 | M8: 6.787 | N8: 6.787 | O8: 0.376 | P8: 7.163
A9: 1976 | B9: 0.007 | C9: NA | D9: NA | E9: 0.433 | F9: 0.268 | G9: 1.369 | H9: NA | I9: 2.53 | J9: 0.594 | K9: NA | L9: 1.029 | M9: 6.23 | N9: 6.23 | O9: 0.568 | P9: 6.798
A10: 1977 | B10: 0.009 | C10: NA | D10: NA | E10: 0.376 | F10: 0.266 | G10: 2.119 | H10: NA | I10: 2.031 | J10: 0.535 | K10: NA | L10: 1.297 | M10: 6.633 | N10: 6.633 | O10: 0.327 | P10: 6.96
A11: 1978 | B11: 0.028 | C11: NA | D11: NA | E11: 0.326 | F11: 0.294 | G11: 1.164 | H11: NA | I11: 1.852 | J11: 0.521 | K11: NA | L11: 0.879 | M11: 5.064 | N11: 5.064 | O11: 0.614 | P11: 5.678
A12: 1979 | B12: 0.02 | C12: NA | D12: NA | E12: 0.404 | F12: 0.325 | G12: 1.982 | H12: NA | I12: 1.896 | J12: 0.497 | K12: NA | L12: 1.111 | M12: 6.235 | N12: 6.235 | O12: 0.497 | P12: 6.732
A13: 1980 | B13: 0.006 | C13: 0.229 | D13: 0.143 | E13: 0.414 | F13: 0.306 | G13: 2.007 | H13: 0.192 | I13: 0.792 | J13: 0.494 | K13: 0.102 | L13: 0.711 | M13: 5.396 | N13: 5.253 | O13: 0.599 | P13: 5.995
A14: 1981 | B14: 0.071 | C14: 0.194 | D14: 0.147 | E14: 0.29 | F14: 0.283 | G14: 1.146 | H14: 0.387 | I14: 1.982 | J14: 0.312 | K14: 0.157 | L14: 0.453 | M14: 5.422 | N14: 5.275 | O14: 0.516 | P14: 5.938
A15: 1982 | B15: 0.043 | C15: 0.29 | D15: 0.111 | E15: 0.494 | F15: 0.345 | G15: 1.558 | H15: 0.33 | I15: 3.271 | J15: 0.515 | K15: 0.061 | L15: 0.329 | M15: 7.347 | N15: 7.236 | O15: 0.344 | P15: 7.691
A16: 1983 | B16: 0.033 | C16: 0.264 | D16: 0.14 | E16: 0.446 | F16: 0.279 | G16: 1.603 | H16: 0.137 | I16: 2.352 | J16: 0.53 | K16: 0.097 | L16: 0.366 | M16: 6.247 | N16: 6.107 | O16: 0.419 | P16: 6.666
A17: 1984 | B17: 0.02 | C17: 0.206 | D17: 0.1 | E17: 0.487 | F17: 0.307 | G17: 1.722 | H17: 0.053 | I17: 1.697 | J17: 0.354 | K17: 0.04 | L17: 0.421 | M17: 5.407 | N17: 5.307 | O17: 0.429 | P17: 5.836
A18: 1985 | B18: 0.013 | C18: 0.228 | D18: 0.072 | E18: 0.471 | F18: 0.368 | G18: 1.851 | H18: 0.099 | I18: 2.774 | J18: 0.452 | K18: 0.05 | L18: 0.534 | M18: 6.912 | N18: 6.84 | O18: 0.444 | P18: 7.356
A19: 1986 | B19: 0.031 | C19: 0.194 | D19: 0.093 | E19: 0.466 | F19: 0.349 | G19: 1.189 | H19: 0.305 | I19: 2.628 | J19: 0.506 | K19: 0.16 | L19: 0.438 | M19: 6.359 | N19: 6.266 | O19: 0.703 | P19: 7.062
A20: 1987 | B20: 0.049 | C20: 0.234 | D20: 0.101 | E20: 0.205 | F20: 0.183 | G20: 1.441 | H20: 0.183 | I20: 2.251 | J20: 0.369 | K20: 0.077 | L20: 0.291 | M20: 5.384 | N20: 5.283 | O20: 0.579 | P20: 5.963
A21: 1988 | B21: 0.01 | C21: 0.353 | D21: 0.133 | E21: 0.545 | F21: 0.199 | G21: 1.119 | H21: 0.198 | I21: 3.339 | J21: 0.321 | K21: 0.099 | L21: 0.531 | M21: 6.847 | N21: 6.714 | O21: 0.701 | P21: 7.548
A22: 1989 | B22: 0.064 | C22: 0.3 | D22: 0.125 | E22: 0.443 | F22: 0.298 | G22: 1.061 | H22: 0.071 | I22: 2.126 | J22: 0.404 | K22: 0.169 | L22: 0.358 | M22: 5.419 | N22: 5.294 | O22: 0.618 | P22: 6.037
A23: 1990 | B23: 0.1 | C23: 0.268 | D23: 0.104 | E23: 0.363 | F23: 0.241 | G23: 1.259 | H23: 0.256 | I23: 3.075 | J23: 0.593 | K23: 0.123 | L23: 0.347 | M23: 6.729 | N23: 6.625 | O23: 0.466 | P23: 7.195
A24: 1991 | B24: 0.145 | C24: 0.275 | D24: 0.106 | E24: 0.495 | F24: 0.247 | G24: 1.467 | H24: 0.22 | I24: 3.282 | J24: 0.541 | K24: 0.173 | L24: 0.396 | M24: 7.347 | N24: 7.241 | O24: 0.56 | P24: 7.907
... A56: 2023 | B56: 1.432 | C56: 0.099 | D56: 1.444 | E56: 0.202 | F56: 0.093 | G56: 0.614 | H56: 0.125 | I56: 2.204 | J56: 0.209 | K56: 0.258 | L56: 0.037 | M56: 6.717 | N56: 5.273 | O56: 3.82 | P56: 10.537
A57: 2024 | B57: 1.88 | C57: 0.093 | D57: 1.317 | E57: 0.253 | F57: NA | G57: 0.414 | H57: 0.134 | I57: 3.156 | J57: 0.275 | K57: 0.301 | L57: 0.112 | M57: 7.935 | N57: 6.618 | O57: 3.134 | P57: 11.069
A58: NA = Not available. Most recent year is preliminary. Totals may not sum due to rounding. All data are expressed on a calendar-year basis.
A59: 1/ Unit of measure is pounds per person.
A60: 2/ Includes small white, cranberry, and beans classified by USDA, National Agricultural Statistics Service as other.
A61: Source: USDA, Economic Research Service.

Sheet Table 3-Plant, Harvest, Prod
A1: Table 3--U.S. vegetable and dry pulse crop industry: Total harvested area, production, and crop value | S1: =HYPERLINK("#'"&"Index'!A1","INDEX") -> INDEX
A2: Item | B2: 2008 | C2: 2009 | D2: 2010 | E2: 2011 | F2: 2012 | G2: 2013 | H2: 2014 | I2: 2015 | J2: 2016 | K2: 2017 | L2: 2018 | M2: 2019 | N2: 2020 | O2: 2021 | P2: 2022 | Q2: 2023 | R2: 2024 | S2: Percent Change 2023–24
A3: Harvested area (1,000 acres)
A4: Fresh and processing/1 | B4: 2721.064 | C4: 2733.743 | D4: 2602.885 | E4: 2478.645 | F4: 2569.285 | G4: 2484.49 | H4: 2485.63 | I4: 2454.15 | J4: 2591 | K4: 2525.03 | L4: 2463.15 | M4: 2259.9 | N4: 2271 | O4: 2271.3 | P4: 2239.7 | Q4: 2140.2 | R4: 2023.8 | S4: =(R4/Q4-1)*100 -> -5.438744
A5: Potatoes | B5: 1046.9 | C5: 1044 | D5: 1008.9 | E5: 1078.5 | F5: 1138.5 | G5: 1060.9 | H5: 1064.7 | I5: 1070.9 | J5: 1037.7 | K5: 1044.5 | L5: 1014.8 | M5: 934.3 | N5: 911.6 | O5: 929.6 | P5: 918.2 | Q5: 961.1 | R5: 925.4 | S5: =(R5/Q5-1)*100 -> -3.7144938
A6: Sweet potatoes/2 | B6: 97.3 | C6: 96.9 | D6: 116.9 | E6: 129.7 | F6: 126.6 | G6: 113 | H6: 134.6 | I6: 153.1
A7: Dry beans/3 | B7: 1363.1 | C7: 1370.1 | D7: 1698.6 | E7: 1033.4 | F7: 1484.1 | G7: 1096.4 | H7: 1436.5 | I7: 1506.1 | J7: 1238.1 | K7: 1411.7 | L7: 1181.7 | M7: 1170 | N7: 1653.8 | O7: 1320.1 | P7: 1219.2 | Q7: 1156.1 | R7: 1503.6 | S7: =(R7/Q7-1)*100 -> 30.057953
A8: Dry peas/4 | B8: 847.3 | C8: 837.9 | D8: 711.4 | E8: 342.8 | F8: 621.5 | G8: 797 | H8: 899.5 | I8: 1083.5 | J8: 1330.8 | K8: 1051.5 | L8: 851.3 | M8: 1079 | N8: 1001 | O8: 894 | P8: 888 | Q8: 933 | R8: 939.9 | S8: =(R8/Q8-1)*100 -> 0.73954984
A9: Lentils | B9: 261 | C9: 406 | D9: 634 | E9: 411 | F9: 450 | G9: 347 | H9: 259 | I9: 475 | J9: 905 | K9: 1022 | L9: 715 | M9: 426 | N9: 515 | O9: 577 | P9: 619 | Q9: 523 | R9: 903 | S9: =(R9/Q9-1)*100 -> 72.657744
A10: Chickpeas | B10: 82.1 | C10: 93.9 | D10: 144.1 | E10: 134.5 | F10: 206.3 | G10: 218.6 | H10: 212.1 | I10: 202.3 | J10: 320 | K10: 611 | L10: 846.4 | M10: 404.2 | N10: 251 | O10: 349.2 | P10: 341.7 | Q10: 356.8 | R10: 492.4 | S10: =(R10/Q10-1)*100 -> 38.004484
A11: Mushrooms, all/5 | B11: 3.1223829 | C11: 3.0884527 | D11: 2.9675849 | E11: 3.0823232 | F11: 3.2794335 | G11: 3.3216127 | H11: 3.0919366 | I11: 3.2895258 | J11: 3.2632402 | K11: 3.2942319 | L11: 2.7479568 | M11: 2.7361111 | N11: 3.1011019 | O11: 3.0064738 | P11: 2.6269753 | Q11: 2.7424794 | R11: 2.8783508 | S11: =(R11/Q11-1)*100 -> 4.9543244
A12: Total | B12: 6421.8864 | C12: 6585.6315 | D12: 6919.7526 | E12: 5611.6273 | F12: 6599.5644 | G12: 6120.7116 | H12: 6495.1219 | I12: 6948.3395 | J12: 7425.8632 | K12: 7669.0242 | L12: 7075.098 | M12: =SUM(M4:M11) -> 6276.1361 | N12: =SUM(N4:N11) -> 6606.5011 | O12: =SUM(O4:O11) -> 6344.2065 | P12: =SUM(P4:P11) -> 6228.427 | Q12: =SUM(Q4:Q11) -> 6072.9425 | R12: =SUM(R4:R11) -> 6790.9784 | S12: =(R12/Q12-1)*100 -> 11.823525
A13: Production (million cwt.)
A14: Fresh and processing/1 | B14: 732.1004 | C14: 766.6936 | D14: 726.1108 | E14: 708.2398 | F14: 738.3585 | G14: 703.5006 | H14: 743.4632 | I14: 739.2259 | J14: 772.5614 | K14: 730.299 | L14: 724.5411 | M14: 678.3764 | N14: 691.2044 | O14: 659.0438 | P14: 661.1911 | Q14: 698.5965 | R14: 636.669 | S14: =(R14/Q14-1)*100 -> -8.8645592
A15: Potatoes | B15: 415.055 | C15: 432.601 | D15: 404.549 | E15: 430.037 | F15: 464.97 | G15: 438.662 | H15: 448.693 | I15: 448.611 | J15: 450.324 | K15: 450.921 | L15: 450.02 | M15: 423.189 | N15: 419.781 | O15: 412.639 | P15: 402.054 | Q15: 440.132 | R15: 420.242 | S15: =(R15/Q15-1)*100 -> -4.5190988
A16: Sweet potatoes/2 | B16: 18.443 | C16: 19.469 | D16: 23.845 | E16: 26.964 | F16: 26.482 | G16: 24.749 | H16: 29.464 | I16: 31.016
A17: Dry beans/3 | B17: 24.44 | C17: 23.983 | D17: 29.862 | E17: 17.688 | F17: 28.593 | G17: 21.009 | H17: 26.104 | I17: 27.544 | J17: 23.256 | K17: 28.904 | L17: 24.958 | M17: 20.604 | N17: 32.38 | O17: 22.407 | P17: 25.734 | Q17: 23.893 | R17: 31.289 | S17: =(R17/Q17-1)*100 -> 30.954673
A18: Dry peas/4 | B18: 12.954 | C18: 18.193 | D18: 15.038 | E18: 6.314 | F18: 11.575 | G18: 16.123 | H18: 18.005 | I18: 18.927 | J18: 28.66 | K18: 14.652 | L18: 16.84 | M18: 22.977 | N18: 22.389 | O18: 9.161 | P18: 15.517 | Q18: 17.947 | R18: 16.679 | S18: =(R18/Q18-1)*100 -> -7.0652477
A19: Lentils | B19: 2.393 | C19: 5.844 | D19: 8.657 | E19: 4.732 | F19: 5.302 | G19: 5.019 | H19: 3.446 | I19: 5.263 | J19: 12.794 | K19: 7.482 | L19: 8.433 | M19: 5.297 | N19: 7.473 | O19: 3.47 | P19: 5.65 | Q19: 5.697 | R19: 9.049 | S19: =(R19/Q19-1)*100 -> 58.837985
A20: Chickpeas | B20: 1.118 | C20: 1.444 | D20: 1.939 | E20: 2.202 | F20: 3.332 | G20: 3.558 | H20: 2.806 | I20: 2.513 | J20: 5.447 | K20: 7.057 | L20: 12.79 | M20: 6.248 | N20: 4.093 | O20: 2.848 | P20: 3.686 | Q20: 4.66 | R20: 5.632 | S20: =(R20/Q20-1)*100 -> 20.858369
A21: Mushrooms, all | B21: 8.12604 | C21: 8.19775 | D21: 7.92493 | E21: 8.63762 | F21: 8.9997 | G21: 8.88252 | H21: 8.99833 | I21: 9.2782336 | J21: 9.4341435 | K21: 9.3335532 | L21: 8.46491 | M21: 8.3236687 | N21: 8.1695434 | O21: 7.5892669 | P21: 7.0349392 | Q21: 7.250796 | R21: 6.5912911 | S21: =(R21/Q21-1)*100 -> -9.095621
A22: Total | B22: 1214.6294 | C22: 1276.4253 | D22: 1217.9257 | E22: 1204.8144 | F22: 1287.6122 | G22: 1221.5031 | H22: 1280.9795 | I22: 1282.3781 | J22: 1302.4765 | K22: 1248.6486 | L22: 1246.047 | M22: =SUM(M14:M21) -> 1165.0151 | N22: =SUM(N14:N21) -> 1185.4899 | O22: =SUM(O14:O21) -> 1117.1581 | P22: =SUM(P14:P21) -> 1120.867 | Q22: =SUM(Q14:Q21) -> 1198.1763 | R22: =SUM(R14:R21) -> 1126.1513 | S22: =(R22/Q22-1)*100 -> -6.0112193
A23: Crop value (million U.S. dollars)
A24: Fresh and processing/1 | B24: 11273.122 | C24: 12007.679 | D24: 11574.746 | E24: 11376.038 | F24: 10935.52 | G24: 12671.159 | H24: 12215.952 | I24: 13810.313 | J24: 13372.968 | K24: 14321.22 | L24: 12719.077 | M24: 13528.085 | N24: 14913.941 | O24: 13367.84 | P24: 18128.538 | Q24: 17971.367 | R24: 17202.296 | S24: =(R24/Q24-1)*100 -> -4.279424
A25: Potatoes | B25: 3770.462 | C25: 3557.574 | D25: 3724.821 | E25: 4044.869 | F25: 4017.245 | G25: 4332.91 | H25: 4024.448 | I25: 3941.82 | J25: 4090.689 | K25: 4133.073 | L25: 4006.34 | M25: 4202.757 | N25: 3902.277 | O25: 4204.117 | P25: 5166.427 | Q25: 5393.342 | R25: 5078.798 | S25: =(R25/Q25-1)*100 -> -5.8320796
A26: Sweet potatoes/2 | B26: 390.572 | C26: 423.677 | D26: 472.218 | E26: 505.938 | F26: 461.861 | G26: 596.058 | H26: 703.772 | I26: 675.583
A27: Dry beans/3 | B27: 875.228 | C27: 750.342 | D27: 843.416 | E27: 766.692 | F27: 1121.613 | G27: 880.609 | H27: 896.295 | I27: 805.178 | J27: 713.562 | K27: 783.223 | L27: 651 | M27: 670.882 | N27: 1035.758 | O27: 922.951 | P27: 1053.714 | Q27: 991.27 | R27: 1171.884 | S27: =(R27/Q27-1)*100 -> 18.220465
A28: Dry peas/4 | B28: 187.143 | C28: 179.884 | D28: 158.956 | E28: 103.795 | F28: 186.281 | G28: 240.142 | H28: 228.54 | I28: 246.83 | J28: 326.692 | K28: 178.893 | L28: 173.506 | M28: 217.615 | N28: 220.111 | O28: 161.465 | P28: 231.557 | Q28: 269.017 | R28: 226.36 | S28: =(R28/Q28-1)*100 -> -15.856619
A29: Lentils | B29: 80.943 | C29: 156.751 | D29: 219.073 | E29: 118.636 | F29: 111.541 | G29: 100.032 | H29: 86.404 | I29: 162.247 | J29: 366.564 | K29: 188.906 | L29: 131.922 | M29: 83.217 | N29: 136.337 | O29: 125.323 | P29: 189.514 | Q29: 218.524 | R29: 324.906 | S29: =(R29/Q29-1)*100 -> 48.682067
A30: Chickpeas | B30: 34.972 | C30: 39.908 | D30: 55.842 | E30: 84.439 | F30: 113.642 | G30: 101.776 | H30: 84.327 | I30: 61.044 | J30: 149.869 | K30: 223.13 | L30: 281.451 | M30: 115.897 | N30: 88.709 | O30: 102.308 | P30: 128.134 | Q30: 171.796 | R30: 179.578 | S30: =(R30/Q30-1)*100 -> 4.5297911
A31: Mushrooms, all | B31: 962.756 | C31: 958.896 | D31: 923.889 | E31: 1017.884 | F31: 1099.4 | G31: 1103.886 | H31: 1115.628 | I31: 1191.357 | J31: 1191.317 | K31: 1226.127 | L31: 1131.564 | M31: 1114.71 | N31: 1153.296 | O31: 1063.8489 | P31: 1018.2807 | Q31: 1128.4838 | R31: 1088.0034 | S31: =(R31/Q31-1)*100 -> -3.5871503
A32: Total | B32: 17575.198 | C32: 18074.711 | D32: 17972.961 | E32: 18018.291 | F32: 18047.103 | G32: 20026.572 | H32: 19355.366 | I32: 20894.372 | J32: 20211.661 | K32: 21054.572 | L32: 19094.86 | M32: =SUM(M24:M31) -> 19933.163 | N32: =SUM(N24:N31) -> 21450.429 | O32: =SUM(O24:O31) -> 19947.853 | P32: =SUM(P24:P31) -> 25916.165 | Q32: =SUM(Q24:Q31) -> 26143.8 | R32: =SUM(R24:R31) -> 25271.825 | S32: =(R32/Q32-1)*100 -> -3.335301
A33: Most recent year is preliminary. Cwt = hundredweight.
A34: 1/ Excludes potatoes, pulse crops, mushrooms, melons, and vegetables not included in USDA, NASS annual estimates. Excludes sweet potatoes from 2008 to 2015.
A35: 2/ Starting in 2016, sweet potatoes are included in fresh and processing vegetable total. The crop mix includes 23 principal vegetable crops identified in USDA, NASS, Vegetables Annual Summary, February 2024 (2023 summary year), excluding cantaloupes, honeydews, and watermelons.
A36: 3/ Includes black-eyed peas but excludes chickpeas.
A37: 4/ Beginning in 2019, includes Austrian winter peas. Excludes chickpeas and blackeye peas. Production and value includes wrinkled seed peas.
A38: 5/ Mushroom area equal to total fillings (multiple varieties).
A39: Source: USDA, Economic Research Service calculations using USDA, National Agricultural Statistics Service data.

Sheet Table 4a-Import Value
A1: Table 4a--Vegetable imports: U.S. value, by group, by month | O1: =HYPERLINK("#'"&"Index'!A1","INDEX") -> INDEX
A2: Month and Year | B2: Fresh vegetables, excluding potatoes and mushrooms/1 | C2: Fresh potatoes/2 | D2: Fresh mushrooms | E2: Processed vegetables, excluding potatoes and mushrooms/1,3 | F2: Processed potatoes/4 | G2: Processed mushrooms/5 | H2: Dry peas, chickpeas, and lentils | I2: Dry beans/6 | J2: Fresh Vegetable Total | K2: Processed Vegetable Total | L2: Vegetable and Pulses Total
B3: —————————————————————————————————— $ millions ——————————————————————————————————
A4: 2017
A5: January | B5: 694.49631 | C5: 21.178627 | D5: 16.317934 | E5: 281.54922 | F5: 88.89136 | G5: 15.984704 | H5: 9.016484 | I5: 11.843781 | J5: 731.99287 | K5: 386.42528 | L5: 1139.2784
A6: February | B6: 715.30893 | C6: 20.620192 | D6: 15.465788 | E6: 245.55804 | F6: 83.110974 | G6: 14.320056 | H6: 8.60313 | I6: 11.069788 | J6: 751.39491 | K6: 342.98907 | L6: 1114.0569
A7: March | B7: 804.09269 | C7: 27.057396 | D7: 17.562693 | E7: 264.84134 | F7: 96.24572 | G7: 12.977387 | H7: 11.606166 | I7: 12.371171 | J7: 848.71278 | K7: 374.06444 | L7: 1246.7546
A8: April | B8: 673.6275 | C8: 24.651809 | D8: 16.610758 | E8: 251.48381 | F8: 100.04327 | G8: 13.738202 | H8: 9.965519 | I8: 11.709688 | J8: 714.89006 | K8: 365.26529 | L8: 1101.8306
A9: May | B9: 616.94128 | C9: 19.774994 | D9: 18.0205 | E9: 257.20925 | F9: 104.98258 | G9: 13.127203 | H9: 11.721395 | I9: 12.391652 | J9: 654.73677 | K9: 375.31903 | L9: 1054.1688
A10: June | B10: 513.42489 | C10: 11.59498 | D10: 16.674756 | E10: 244.36932 | F10: 101.17161 | G10: 12.508749 | H10: 8.612747 | I10: 11.406141 | J10: 541.69463 | K10: 358.04968 | L10: 919.7632
A11: July | B11: 493.5134 | C11: 7.40147 | D11: 16.856833 | E11: 226.81059 | F11: 97.997054 | G11: 14.105216 | H11: 10.118695 | I11: 11.938422 | J11: 517.77171 | K11: 338.91286 | L11: 878.74168
A12: August | B12: 480.14608 | C12: 9.667373 | D12: 15.76662 | E12: 241.10967 | F12: 95.276243 | G12: 13.503942 | H12: 10.378435 | I12: 13.029904 | J12: 505.58007 | K12: 349.88985 | L12: 878.87827
A13: September | B13: 515.51336 | C13: 13.484441 | D13: 16.639221 | E13: 236.76381 | F13: 89.63418 | G13: 13.415195 | H13: 11.853184 | I13: 12.429418 | J13: 545.63702 | K13: 339.81319 | L13: 909.73281
A14: October | B14: 611.59927 | C14: 17.534225 | D14: 21.700244 | E14: 268.60663 | F14: 102.04329 | G14: 13.805119 | H14: 21.318457 | I14: 10.962869 | J14: 650.83374 | K14: 384.45504 | L14: 1067.5701
A15: November | B15: 656.70969 | C15: 22.875973 | D15: 23.321829 | E15: 273.98031 | F15: 100.1269 | G15: 14.363875 | H15: 10.796041 | I15: 9.658251 | J15: 702.90749 | K15: 388.47108 | L15: 1111.8329
A16: December | B16: 732.14383 | C16: 20.033663 | D16: 24.480539 | E16: 262.9242 | F16: 91.180892 | G16: 14.353972 | H16: 10.725822 | I16: 10.191505 | J16: 776.65803 | K16: 368.45907 | L16: 1166.0344
A17: Annual | B17: =SUM(B5:B16) -> 7507.5172 | C17: =SUM(C5:C16) -> 215.87514 | D17: =SUM(D5:D16) -> 219.41771 | E17: =SUM(E5:E16) -> 3055.2062 | F17: =SUM(F5:F16) -> 1150.7041 | G17: =SUM(G5:G16) -> 166.20362 | H17: =SUM(H5:H16) -> 134.71607 | I17: =SUM(I5:I16) -> 139.00259 | ... L17: =SUM(L5:L16) -> 12588.643
A18: 2018
A19: January | B19: 905.11155 | C19: 25.556295 | D19: 22.371675 | E19: 284.1599 | F19: 100.07731 | G19: 11.844228 | H19: 12.566863 | I19: 11.882478 | J19: 953.03952 | K19: 396.08144 | L19: 1373.5703
A20: February | B20: 750.53187 | C20: 20.417605 | D20: 19.685298 | E20: 259.76738 | F20: 95.690288 | G20: 12.475136 | H20: 10.727809 | I20: 10.442535 | J20: 790.63478 | K20: 367.93281 | L20: 1179.7379
A21: March | B21: 822.13724 | C21: 25.893951 | D21: 21.070953 | E21: 282.50556 | F21: 108.90623 | G21: 13.627018 | H21: 11.231336 | I21: 11.232953 | J21: 869.10214 | K21: 405.03881 | L21: 1296.6052
A22: April | B22: 670.78971 | C22: 24.88162 | D22: 19.146417 | E22: 271.66454 | F22: 112.5246 | G22: 14.448788 | H22: 13.86401 | I22: 12.043707 | J22: 714.81775 | K22: 398.63792 | L22: 1139.3634
A23: May | B23: 638.36974 | C23: 21.620375 | D23: 19.686015 | E23: 276.12493 | F23: 115.91099 | G23: 14.893592 | H23: 13.706296 | I23: 11.386742 | J23: 679.67613 | K23: 406.9295 | L23: 1111.6987
A24: June | B24: 538.24579 | C24: 13.381179 | D24: 18.995721 | E24: 261.8277 | F24: 112.1662 | G24: 14.55342 | H24: 10.027824 | I24: 10.44884 | J24: 570.62269 | K24: 388.54732 | L24: 979.64668
A25: July | B25: 509.75068 | C25: 12.189435 | D25: 20.18725 | E25: 262.69985 | F25: 112.31227 | G25: 16.057233 | H25: 17.646404 | I25: 9.992849 | J25: 542.12736 | K25: 391.06936 | L25: 960.83597
A26: August | B26: 523.23827 | C26: 11.015249 | D26: 20.48586 | E26: 261.28593 | F26: 106.87882 | G26: 13.11748 | H26: 10.378618 | I26: 10.392643 | J26: 554.73938 | K26: 381.28223 | L26: 956.79287
A27: September | B27: 511.95723 | C27: 14.023704 | D27: 20.648447 | E27: 248.48029 | F27: 99.51863 | G27: 13.61623 | H27: 9.82339 | I27: 9.112233 | J27: 546.62938 | K27: 361.61515 | L27: 927.18015
A28: October | B28: 618.95898 | C28: 18.437025 | D28: 26.014576 | E28: 289.689 | F28: 113.5308 | G28: 14.937388 | H28: 13.326923 | I28: 12.64419 | J28: 663.41058 | K28: 418.15719 | L28: 1107.5389
A29: November | B29: 671.32971 | C29: 19.850425 | D29: 26.619838 | E29: 271.02885 | F29: 106.42123 | G29: 14.917743 | H29: 10.207262 | I29: 8.855043 | J29: 717.79998 | K29: 392.36783 | L29: 1129.2301
A30: December | B30: 782.78797 | C30: 19.780653 | D30: 28.949672 | E30: 298.34404 | F30: 100.38977 | G30: 14.639746 | H30: 8.284702 | I30: 12.88763 | J30: 831.5183 | K30: 413.37355 | L30: 1266.0642
A31: Annual | B31: =SUM(B19:B30) -> 7943.2087 | C31: =SUM(C19:C30) -> 227.04752 | D31: =SUM(D19:D30) -> 263.86172 | E31: =SUM(E19:E30) -> 3267.578 | F31: =SUM(F19:F30) -> 1284.3271 | G31: =SUM(G19:G30) -> 169.128 | H31: =SUM(H19:H30) -> 141.79144 | I31: =SUM(I19:I30) -> 131.32184 | ... L31: =SUM(L19:L30) -> 13428.264
A32: 2019
A33: January | B33: 936.36024 | C33: 20.949728 | D33: 26.994379 | E33: 266.07743 | F33: 107.96687 | G33: 11.359774 | H33: 11.262878 | I33: 11.74077 | J33: 984.30435 | K33: 385.40408 | L33: 1392.7121
A34: February | B34: 791.5827 | C34: 18.116466 | D34: 23.158966 | E34: 244.32867 | F34: 98.462314 | G34: 10.793062 | H34: 7.665838 | I34: 10.044137 | J34: 832.85813 | K34: 353.58404 | L34: 1204.1522
A35: March | B35: 926.69304 | C35: 22.835833 | D35: 24.481168 | E35: 267.55358 | F35: 111.44367 | G35: 13.749761 | H35: 8.864116 | I35: 9.678571 | J35: 974.01004 | K35: 392.74701 | L35: 1385.2997
A36: April | B36: 778.91147 | C36: 22.142631 | D36: 22.512773 | E36: 269.55647 | F36: 113.72378 | G36: 16.784425 | H36: 16.517187 | I36: 9.965325 | J36: 823.56687 | K36: 400.06468 | L36: 1250.1141
A37: May | B37: 669.36539 | C37: 17.146934 | D37: 23.456471 | E37: 277.36833 | F37: 116.1605 | G37: 14.896481 | H37: 10.127419 | I37: 11.945691 | J37: 709.9688 | K37: 408.42531 | L37: 1140.4672
A38: June | B38: 552.2181 | C38: 9.915271 | D38: 22.47843 | E38: 252.11224 | F38: 111.9741 | G38: 13.03785 | H38: 8.364883 | I38: 8.183791 | J38: 584.6118 | K38: 377.12419 | L38: 978.28466
A39: July | B39: 562.29517 | C39: 6.494112 | D39: 23.379334 | E39: 269.82871 | F39: 114.10594 | G39: 14.166813 | H39: 7.238947 | I39: 10.161469 | J39: 592.16862 | K39: 398.10146 | L39: 1007.6705
A40: August | B40: 548.13201 | C40: 7.79322 | D40: 22.7915 | E40: 252.9576 | F40: 100.22722 | G40: 13.624451 | H40: 9.389562 | I40: 8.698527 | J40: 578.71673 | K40: 366.80927 | L40: 963.61409
A41: September | B41: 561.26241 | C41: 14.989411 | D41: 22.993195 | E41: 260.98903 | F41: 102.49548 | G41: 14.204302 | H41: 8.176261 | I41: 11.871454 | J41: 599.24502 | K41: 377.68881 | L41: 996.98154
A42: October | B42: 664.34 | C42: 19.99848 | D42: 28.124517 | E42: 294.57205 | F42: 118.08195 | G42: 14.983868 | H42: 8.031933 | I42: 13.210067 | J42: 712.463 | K42: 427.63788 | L42: 1161.3429
A43: November | B43: 713.15059 | C43: 24.880644 | D43: 30.723295 | E43: 260.64773 | F43: 110.76884 | G43: 12.069096 | H43: 6.098089 | I43: 9.391162 | J43: 768.75453 | K43: 383.48566 | L43: 1167.7294
A44: December | B44: 807.15232 | C44: 23.000532 | D44: 33.369118 | E44: 286.2585 | F44: 115.72487 | G44: 12.684116 | H44: 7.05118 | I44: 10.786519 | J44: 863.52197 | K44: 414.66749 | L44: 1296.0272
A45: Annual | B45: =SUM(B33:B44) -> 8511.4634 | C45: =SUM(C33:C44) -> 208.26326 | D45: =SUM(D33:D44) -> 304.46315 | E45: =SUM(E33:E44) -> 3202.2503 | F45: =SUM(F33:F44) -> 1321.1355 | G45: =SUM(G33:G44) -> 162.354 | H45: =SUM(H33:H44) -> 108.78829 | I45: =SUM(I33:I44) -> 125.67748 | ... L45: =SUM(L33:L44) -> 13944.396
A46: 2020
A47: January | B47: 1034.6661 | C47: 24.894037 | D47: 30.6881 | E47: 294.33798 | F47: 120.50465 | G47: 12.681847 | H47: 11.086168 | I47: 12.369606 | J47: 1090.2483 | K47: 427.52447 | L47: 1541.2285
A48: February | B48: 912.52101 | C48: 23.387463 | D48: 26.391639 | E48: 261.4854 | F48: 117.05473 | G48: 11.409587 | H48: 8.379754 | I48: 11.927631 | J48: 962.30011 | K48: 389.94971 | L48: 1372.5572
A49: March | B49: 962.05786 | C49: 38.716814 | D49: 28.020216 | E49: 308.61478 | F49: 120.84494 | G49: 13.112552 | H49: 10.342793 | I49: 24.013229 | J49: 1028.7949 | K49: 442.57227 | L49: 1505.7232
A50: April | B50: 712.68776 | C50: 32.496544 | D50: 24.564951 | E50: 317.59044 | F50: 102.07443 | G50: 13.964428 | H50: 10.174771 | I50: 21.439527 | J50: 769.74926 | K50: 433.62929 | L50: 1234.9929
A51: May | B51: 780.51215 | C51: 21.703146 | D51: 26.286227 | E51: 301.25839 | F51: 120.86848 | G51: 12.547281 | H51: 9.005938 | I51: 18.347152 | J51: 828.50152 | K51: 434.67415 | L51: 1290.5288
A52: June | B52: 712.33529 | C52: 12.282473 | D52: 26.219513 | E52: 280.03599 | F52: 126.72417 | G52: 12.859521 | H52: 9.076084 | I52: 19.339363 | J52: 750.83728 | K52: 419.61968 | L52: 1198.8724
A53: July | B53: 691.1273 | C53: 11.33993 | D53: 26.918463 | E53: 283.07169 | F53: 129.79401 | G53: 13.199682 | H53: 8.405072 | I53: 19.325051 | J53: 729.3857 | K53: 426.06538 | L53: 1183.1812
A54: August | B54: 636.13387 | C54: 11.394979 | D54: 26.935209 | E54: 289.98392 | F54: 119.62696 | G54: 14.446962 | H54: 7.000882 | I54: 13.52812 | J54: 674.46406 | K54: 424.05784 | L54: 1119.0509
A55: September | B55: 663.17314 | C55: 17.796418 | D55: 26.699537 | E55: 293.63688 | F55: 124.00278 | G55: 15.825651 | H55: 7.182244 | I55: 14.944921 | J55: 707.66909 | K55: 433.46531 | L55: 1163.2616
A56: October | B56: 767.92535 | C56: 22.567268 | D56: 28.81366 | E56: 319.95179 | F56: 126.73619 | G56: 15.112234 | H56: 8.613238 | I56: 17.186572 | J56: 819.30628 | K56: 461.80021 | L56: 1306.9063
A57: November | B57: 802.68848 | C57: 31.051719 | D57: 31.22808 | E57: 322.18438 | F57: 129.80394 | G57: 15.259355 | H57: 8.126418 | I57: 16.085644 | J57: 864.96828 | K57: 467.24767 | L57: 1356.428
A58: December | B58: 847.37958 | C58: 23.962144 | D58: 32.381688 | E58: 321.02246 | F58: 124.21332 | G58: 15.981462 | H58: 11.2279 | I58: 15.297143 | J58: 903.72341 | K58: 461.21724 | L58: 1391.4657
A59: Annual | B59: =SUM(B47:B58) -> 9523.2079 | C59: =SUM(C47:C58) -> 271.59294 | D59: =SUM(D47:D58) -> 335.14728 | E59: =SUM(E47:E58) -> 3593.1741 | F59: =SUM(F47:F58) -> 1462.2486 | G59: =SUM(G47:G58) -> 166.40056 | H59: =SUM(H47:H58) -> 108.62126 | I59: =SUM(I47:I58) -> 203.80396 | ... L59: =SUM(L47:L58) -> 15664.197
A60: 2021
A61: January | B61: 1019.1584 | C61: 26.874958 | D61: 31.30117 | E61: 315.27315 | F61: 130.95148 | G61: 14.446318 | H61: 8.176003 | I61: 11.725634 | J61: 1077.3346 | K61: 460.67095 | L61: 1557.9072
A62: February | B62: 928.52196 | C62: 23.638214 | D62: 28.363029 | E62: 288.70126 | F62: 120.11382 | G62: 13.526766 | H62: 6.120723 | I62: 12.500803 | J62: 980.52321 | K62: 422.34184 | L62: 1421.4866
A63: March | B63: 972.45104 | C63: 32.270536 | D63: 31.125905 | E63: 336.2392 | F63: 140.91822 | G63: 17.447055 | H63: 8.955594 | I63: 16.9088 | J63: 1035.8475 | K63: 494.60447 | L63: 1556.3163
A64: April | B64: 864.64526 | C64: 25.636035 | D64: 28.495163 | E64: 339.08203 | F64: 153.61427 | G64: 17.204824 | H64: 9.96778 | I64: 17.611547 | J64: 918.77646 | K64: 509.90113 | L64: 1456.2569
A65: May | B65: 822.91866 | C65: 19.20179 | D65: 29.715486 | E65: 334.65642 | F65: 158.23815 | G65: 16.425784 | H65: 11.602549 | I65: 17.538936 | J65: 871.83593 | K65: 509.32035 | L65: 1410.2978
A66: June | B66: 735.3809 | C66: 15.656311 | D66: 29.495426 | E66: 344.31706 | F66: 155.06279 | G66: 18.644974 | H66: 8.109939 | I66: 17.829974 | J66: 780.53263 | K66: 518.02482 | L66: 1324.4974
A67: July | B67: 726.29179 | C67: 11.293548 | D67: 29.138813 | E67: 296.5964 | F67: 147.77353 | G67: 18.132968 | H67: 9.799048 | I67: 16.98078 | J67: 766.72415 | K67: 462.5029 | L67: 1256.0069
A68: August | B68: 689.0099 | C68: 13.797874 | D68: 30.557674 | E68: 306.93395 | F68: 143.44605 | G68: 19.890574 | H68: 11.413086 | I68: 18.492798 | J68: 733.36545 | K68: 470.27058 | L68: 1233.5419
A69: September | B69: 704.45403 | C69: 19.191027 | D69: 31.367817 | E69: 304.76441 | F69: 142.49387 | G69: 14.022771 | H69: 12.913487 | I69: 15.572875 | J69: 755.01288 | K69: 461.28106 | L69: 1244.7803
A70: October | B70: 801.26103 | C70: 24.525463 | D70: 38.127089 | E70: 338.68136 | F70: 148.08559 | G70: 15.254886 | H70: 16.651141 | I70: 17.111208 | J70: 863.91358 | K70: 502.02184 | L70: 1399.6978
A71: November | B71: 833.20485 | C71: 31.807469 | D71: 41.777515 | E71: 330.63446 | F71: 164.14946 | G71: 18.757893 | H71: 35.979722 | I71: 15.934204 | J71: 906.78983 | K71: 513.54181 | L71: 1472.2456
A72: December | B72: 906.5703 | C72: 24.127974 | D72: 44.247428 | E72: 332.78491 | F72: 149.47006 | G72: 17.046295 | H72: 18.296156 | I72: 16.393984 | J72: 974.9457 | K72: 499.30127 | L72: 1508.9371
A73: Annual | B73: =SUM(B61:B72) -> 10003.868 | C73: =SUM(C61:C72) -> 268.0212 | D73: =SUM(D61:D72) -> 393.71251 | E73: =SUM(E61:E72) -> 3868.6646 | F73: =SUM(F61:F72) -> 1754.3173 | G73: =SUM(G61:G72) -> 200.80111 | H73: =SUM(H61:H72) -> 157.98523 | I73: =SUM(I61:I72) -> 194.60154 | ... L73: =SUM(L61:L72) -> 16841.972
A74: 2022
A75: January | B75: 963.14807 | C75: 29.325568 | D75: 38.471922 | E75: 351.04772 | F75: 153.96724 | G75: 16.05692 | H75: 12.339444 | I75: 16.096693 | J75: 1030.9456 | K75: 521.07188 | L75: 1580.4536
A76: February | B76: 912.17227 | C76: 26.564629 | D76: 36.170136 | E76: 335.21505 | F76: 139.40981 | G76: 16.45168 | H76: 12.905926 | I76: 15.322856 | J76: 974.90704 | K76: 491.07654 | L76: 1494.2124
A77: March | B77: 1032.4981 | C77: 36.027676 | D77: 36.818996 | E77: 400.26139 | F77: 183.07195 | G77: 21.053379 | H77: 25.668678 | I77: 17.671373 | J77: 1105.3448 | K77: 604.38672 | L77: 1753.0715
A78: April | B78: 955.28311 | C78: 36.703402 | D78: 33.124762 | E78: 376.90861 | F78: 175.5671 | G78: 19.204399 | H78: 23.329853 | I78: 18.552617 | J78: 1025.1113 | K78: 571.6801 | L78: 1638.6738
A79: May | B79: 857.10269 | C79: 35.647681 | D79: 36.17961 | E79: 396.47764 | F79: 191.07749 | G79: 17.690864 | H79: 14.947121 | I79: 18.562296 | J79: 928.92998 | K79: 605.246 | L79: 1567.6854
A80: June | B80: 778.80102 | C80: 30.680444 | D80: 33.081863 | E80: 384.87233 | F80: 178.97913 | G80: 19.550733 | H80: 14.617195 | I80: 19.796068 | J80: 842.56333 | K80: 583.40219 | L80: 1460.3788
A81: July | B81: 733.97104 | C81: 25.570598 | D81: 32.587422 | E81: 343.90101 | F81: 177.25488 | G81: 18.383276 | H81: 12.970446 | I81: 15.466257 | J81: 792.12905 | K81: 539.53917 | L81: 1360.1049
A82: August | B82: 755.89918 | C82: 28.947827 | D82: 33.967894 | E82: 340.44313 | F82: 168.83875 | G82: 19.424405 | H82: 15.382035 | I82: 15.61861 | J82: 818.8149 | K82: 528.70629 | L82: 1378.5218
A83: September | B83: 757.37096 | C83: 28.480546 | D83: 34.645693 | E83: 337.66402 | F83: 180.59864 | G83: 21.591034 | H83: 14.402012 | I83: 16.238178 | J83: 820.4972 | K83: 539.85369 | L83: 1390.9911
A84: October | B84: 878.90729 | C84: 33.969631 | D84: 40.05031 | E84: 404.15924 | F84: 203.59696 | G84: 21.78425 | H84: 14.646931 | I84: 19.037461 | J84: 952.92724 | K84: 629.54044 | L84: 1616.1521
A85: November | B85: 977.01783 | C85: 42.913079 | D85: 43.708084 | E85: 367.44099 | F85: 198.25733 | G85: 16.174764 | H85: 20.926811 | I85: 16.19796 | J85: 1063.639 | K85: 581.87309 | L85: 1682.6369
A86: December | B86: 1081.1497 | C86: 41.301991 | D86: 42.440183 | E86: 355.28735 | F86: 187.22057 | G86: 15.719642 | H86: 14.205383 | I86: 16.536107 | J86: 1164.8918 | K86: 558.22757 | L86: 1753.8609
A87: Annual | B87: =SUM(B75:B86) -> 10683.321 | C87: =SUM(C75:C86) -> 396.13307 | D87: =SUM(D75:D86) -> 441.24687 | E87: =SUM(E75:E86) -> 4393.6785 | F87: =SUM(F75:F86) -> 2137.8398 | G87: =SUM(G75:G86) -> 223.08535 | H87: =SUM(H75:H86) -> 196.34183 | I87: =SUM(I75:I86) -> 205.09648 | ... L87: =SUM(L75:L86) -> 18676.743
A88: 2023
A89: January | B89: 1179.6481 | C89: 45.122671 | D89: 39.527134 | E89: 374.97821 | F89: 223.12137 | G89: 14.22788 | H89: 19.778258 | I89: 16.523535 | J89: 1264.2979 | K89: 612.32746 | L89: 1912.9272
A90: February | B90: 1064.1491 | C90: 43.523554 | D90: 36.063752 | E90: 317.35638 | F90: 203.30532 | G90: 13.720495 | H90: 17.013075 | I90: 18.065172 | J90: 1143.7364 | K90: 534.3822 | L90: 1713.1969
A91: March | B91: 1193.1349 | C91: 56.975973 | D91: 37.065386 | E91: 376.11205 | F91: 232.57524 | G91: 14.413675 | H91: 16.972189 | I91: 21.468161 | J91: 1287.1762 | K91: 623.10097 | L91: 1948.7175
A92: April | B92: 1025.5896 | C92: 44.306291 | D92: 33.606278 | E92: 367.53936 | F92: 230.43774 | G92: 17.289485 | H92: 23.248914 | I92: 18.992242 | J92: 1103.5021 | K92: 615.26658 | L92: 1761.0099
A93: May | B93: 985.35086 | C93: 42.237625 | D93: 34.174992 | E93: 378.37851 | F93: 231.45567 | G93: 18.817735 | H93: 13.505341 | I93: 23.520629 | J93: 1061.7635 | K93: 628.65191 | L93: 1727.4414
A94: June | B94: 846.54939 | C94: 32.123875 | D94: 33.750281 | E94: 365.20982 | F94: 236.30002 | G94: 15.149476 | H94: 12.503558 | I94: 18.884739 | J94: 912.42355 | K94: 616.65932 | L94: 1560.4712
A95: July | B95: 803.70711 | C95: 23.726364 | D95: 33.214751 | E95: 356.56887 | F95: 225.61025 | G95: 18.766397 | H95: 11.78832 | I95: 15.831869 | J95: 860.64822 | K95: 600.94552 | L95: 1489.2139
A96: August | B96: 797.62835 | C96: 19.762334 | D96: 33.760781 | E96: 364.34809 | F96: 202.80131 | G96: 17.418531 | H96: 10.838112 | I96: 15.639035 | J96: 851.15147 | K96: 584.56794 | L96: 1462.1966
A97: September | B97: 808.10855 | C97: 23.418063 | D97: 32.604284 | E97: 356.35375 | F97: 211.13992 | G97: 17.035948 | H97: 13.111854 | I97: 18.343158 | J97: 864.1309 | K97: 584.52962 | L97: 1480.1155
A98: October | B98: 864.61425 | C98: 30.979801 | D98: 38.30582 | E98: 413.81684 | F98: 230.21736 | G98: 17.257881 | H98: 11.651692 | I98: 19.516833 | J98: 933.89987 | K98: 661.29208 | L98: 1626.3605
A99: November | B99: 890.22199 | C99: 35.62974 | D99: 39.295122 | E99: 389.80147 | F99: 225.08415 | G99: 16.669695 | H99: 16.488063 | I99: 19.378738 | J99: 965.14685 | K99: 631.55531 | L99: 1632.569
A100: December | B100: 969.33223 | C100: 32.999992 | D100: 42.44966 | E100: 381.8639 | F100: 212.83336 | G100: 13.964938 | H100: 13.475735 | I100: 18.13111 | J100: 1044.7819 | K100: 608.6622 | L100: 1685.0509
...

Sheet Table 4b-Import Value
A1: Table 4b--Vegetable seed imports: U.S. value, by group, by month | G1: =HYPERLINK("#'"&"Index'!A1","INDEX") -> INDEX
A2: Month and year | B2: Leguminous vegetable seeds | C2: Other vegetable seeds/1 | D2: Total
B3: ————————— Million U.S. dollars —————————
A4: 2017
A5: January | B5: 9.304717 | C5: 37.659258 | D5: 46.963975
A6: February | B6: 11.038041 | C6: 35.728325 | D6: 46.766366
A7: March | B7: 12.20582 | C7: 35.199552 | D7: 47.405372
A8: April | B8: 9.476624 | C8: 31.071418 | D8: 40.548042
A9: May | B9: 9.200669 | C9: 42.3803 | D9: 51.580969
A10: June | B10: 8.199826 | C10: 46.672103 | D10: 54.871929
A11: July | B11: 7.466833 | C11: 41.996485 | D11: 49.463318
A12: August | B12: 10.760186 | C12: 36.640476 | D12: 47.400662
A13: September | B13: 11.602907 | C13: 26.399056 | D13: 38.001963
A14: October | B14: 12.180392 | C14: 42.064442 | D14: 54.244834
A15: November | B15: 10.979594 | C15: 39.168843 | D15: 50.148437
A16: December | B16: 9.013058 | C16: 43.232642 | D16: 52.2457
A17: Annual | B17: =SUM(B5:B16) -> 121.42867 | C17: =SUM(C5:C16) -> 458.2129 | D17: =SUM(D5:D16) -> 579.64157
A18: 2018
A19: January | B19: 13.974074 | C19: 37.905037 | D19: 51.879111
A20: February | B20: 11.503277 | C20: 31.408908 | D20: 42.912185
A21: March | B21: 13.191093 | C21: 34.319109 | D21: 47.510202
A22: April | B22: 14.767801 | C22: 37.288037 | D22: 52.055838
A23: May | B23: 11.22365 | C23: 48.43382 | D23: 59.65747
A24: June | B24: 9.962419 | C24: 52.776684 | D24: 62.739103
A25: July | B25: 8.969814 | C25: 45.284565 | D25: 54.254379
A26: August | B26: 6.702776 | C26: 35.891331 | D26: 42.594107
A27: September | B27: 7.015823 | C27: 37.767876 | D27: 44.783699
A28: October | B28: 9.330202 | C28: 33.664249 | D28: 42.994451
A29: November | B29: 7.820244 | C29: 34.25856 | D29: 42.078804
A30: December | B30: 7.263379 | C30: 48.859846 | D30: 56.123225
A31: Annual | B31: =SUM(B19:B30) -> 121.72455 | C31: =SUM(C19:C30) -> 477.85802 | D31: =SUM(D19:D30) -> 599.58257
A32: 2019
A33: January | B33: 10.062963 | C33: 35.187251 | D33: 45.250214
A34: February | B34: 9.142316 | C34: 26.730985 | D34: 35.873301
A35: March | B35: 11.837379 | C35: 39.647475 | D35: 51.484854
A36: April | B36: 10.876818 | C36: 35.766506 | D36: 46.643324
A37: May | B37: 9.590295 | C37: 48.666906 | D37: 58.257201
A38: June | B38: 8.811213 | C38: 38.924021 | D38: 47.735234
A39: July | B39: 7.266719 | C39: 44.631602 | D39: 51.898321
A40: August | B40: 5.216905 | C40: 35.872383 | D40: 41.089288
A41: September | B41: 6.97727 | C41: 31.77556 | D41: 38.75283
A42: October | B42: 8.089024 | C42: 28.985553 | D42: 37.074577
A43: November | B43: 7.896645 | C43: 35.733587 | D43: 43.630232
A44: December | B44: 7.488057 | C44: 48.858381 | D44: 56.346438
A45: Annual | B45: =SUM(B33:B44) -> 103.2556 | C45: =SUM(C33:C44) -> 450.78021 | D45: =SUM(D33:D44) -> 554.03581
A46: 2020
A47: January | B47: 10.409783 | C47: 28.776615 | D47: 39.186398
A48: February | B48: 8.6065 | C48: 27.151064 | D48: 35.757564
A49: March | B49: 16.073423 | C49: 32.578523 | D49: 48.651946
A50: April | B50: 14.834569 | C50: 27.409012 | D50: 42.243581
A51: May | B51: 9.199713 | C51: 32.297787 | D51: 41.4975
A52: June | B52: 9.701135 | C52: 36.946285 | D52: 46.64742
A53: July | B53: 7.785938 | C53: 32.670293 | D53: 40.456231
A54: August | B54: 7.09871 | C54: 27.448352 | D54: 34.547062
A55: September | B55: 9.808142 | C55: 26.937245 | D55: 36.745387
A56: October | B56: 9.378276 | C56: 33.992969 | D56: 43.371245
A57: November | B57: 8.541336 | C57: 25.889891 | D57: 34.431227
A58: December | B58: 7.34973 | C58: 39.174457 | D58: 46.524187
A59: Annual | B59: =SUM(B47:B58) -> 118.78725 | C59: =SUM(C47:C58) -> 371.27249 | D59: =SUM(D47:D58) -> 490.05975
A60: 2021
A61: January | B61: 9.062058 | C61: 33.598247 | D61: 42.660305
A62: February | B62: 8.032536 | C62: 37.377899 | D62: 45.410435
A63: March | B63: 11.804314 | C63: 36.578587 | D63: 48.382901
A64: April | B64: 10.074539 | C64: 38.11788 | D64: 48.192419
A65: May | B65: 9.385378 | C65: 29.168847 | D65: 38.554225
A66: June | B66: 10.283497 | C66: 39.799614 | D66: 50.083111
A67: July | B67: 11.478123 | C67: 34.845811 | D67: 46.323934
A68: August | B68: 17.158147 | C68: 36.089368 | D68: 53.247515
A69: September | B69: 20.885503 | C69: 33.763061 | D69: 54.648564
A70: October | B70: 21.365529 | C70: 43.078778 | D70: 64.444307
A71: November | B71: 18.696769 | C71: 47.730916 | D71: 66.427685
A72: December | B72: 16.80368 | C72: 49.349564 | D72: 66.153244
A73: Annual | B73: =SUM(B61:B72) -> 165.03007 | C73: =SUM(C61:C72) -> 459.49857 | D73: =SUM(D61:D72) -> 624.52864
A74: 2022
A75: January | B75: 16.649588 | C75: 40.142426 | D75: 56.792014
A76: February | B76: 17.051338 | C76: 28.735736 | D76: 45.787074
A77: March | B77: 21.605753 | C77: 33.236468 | D77: 54.842221
A78: April | B78: 22.88843 | C78: 29.602709 | D78: 52.491139
A79: May | B79: 27.676618 | C79: 39.118452 | D79: 66.79507
A80: June | B80: 29.335726 | C80: 45.024431 | D80: 74.360157
A81: July | B81: 20.34359 | C81: 40.856352 | D81: 61.199942
A82: August | B82: 17.74981 | C82: 37.864629 | D82: 55.614439
A83: September | B83: 16.714135 | C83: 35.848988 | D83: 52.563123
A84: October | B84: 17.009396 | C84: 35.517827 | D84: 52.527223
A85: November | B85: 17.733354 | C85: 43.653303 | D85: 61.386657
A86: December | B86: 13.311236 | C86: 37.351112 | D86: 50.662348
A87: Annual | B87: =SUM(B75:B86) -> 238.06897 | C87: =SUM(C75:C86) -> 446.95243 | D87: =SUM(D75:D86) -> 685.02141
A88: 2023
A89: January | B89: 19.172158 | C89: 38.200625 | D89: 57.372783
A90: February | B90: 20.490247 | C90: 35.968013 | D90: 56.45826
A91: March | B91: 19.492266 | C91: 39.47221 | D91: 58.964476
A92: April | B92: 17.351248 | C92: 38.489305 | D92: 55.840553
A93: May | B93: 16.550038 | C93: 46.654913 | D93: 63.204951
A94: June | B94: 16.190941 | C94: 53.819915 | D94: 70.010856
A95: July | B95: 14.455734 | C95: 37.107131 | D95: 51.562865
A96: August | B96: 15.390981 | C96: 36.994237 | D96: 52.385218
A97: September | B97: 17.037553 | C97: 29.857446 | D97: 46.894999
A98: October | B98: 19.097651 | C98: 36.949422 | D98: 56.047073
A99: November | B99: 19.300887 | C99: 41.988668 | D99: 61.289555
A100: December | B100: 17.324296 | C100: 41.567444 | D100: 58.89174
...

Sheet Table 4c-Import Volume
A1: Table 4c--Vegetable imports: U.S. volume, by group, by month | O1: =HYPERLINK("#'"&"Index'!A1","INDEX") -> INDEX
A2: Month and Year | B2: Fresh vegetables, excluding potatoes and mushrooms/1 | C2: Fresh potatoes/2 | D2: Fresh mushrooms | E2: Processed vegetables, excluding potatoes and mushrooms/1,3 | F2: Processed potatoes/4 | G2: Processed mushrooms/5 | H2: Dry peas, chickpeas, and lentils | I2: Dry beans/6 | J2: Fresh Vegetable Total | K2: Processed Vegetable Total | L2: Vegetable and Pulses Total
B3: —————————————————————————————————— Million pounds ——————————————————————————————————
A4: 2017
A5: January | B5: 1570.6292 | C5: 110.84731 | D5: 10.365924 | E5: 455.86405 | F5: 197.42322 | G5: 12.988666 | H5: 22.574059 | I5: 19.985599 | J5: 1691.8424 | K5: 666.27593 | L5: 2400.678
A6: February | B6: 1486.1943 | C6: 111.037 | D6: 9.5006426 | E6: 409.98163 | F6: 184.2081 | G6: 11.48738 | H6: 21.092687 | I6: 19.05503 | J6: 1606.732 | K6: 605.67711 | L6: 2252.5568
A7: March | B7: 1643.7544 | C7: 157.6454 | D7: 11.142103 | E7: 465.4275 | F7: 212.44382 | G7: 9.4408444 | H7: 30.402674 | I7: 21.542232 | J7: 1812.542 | K7: 687.31216 | L7: 2551.799
A8: April | B8: 1373.9801 | C8: 141.15762 | D8: 11.189509 | E8: 414.47771 | F8: 223.34607 | G8: 11.797571 | H8: 28.592882 | I8: 20.656589 | J8: 1526.3273 | K8: 649.62136 | L8: 2225.1981
A9: May | B9: 1276.8485 | C9: 120.92211 | D9: 12.31821 | E9: 430.42752 | F9: 231.43049 | G9: 11.896543 | H9: 28.650661 | I9: 23.097276 | J9: 1410.0888 | K9: 673.75456 | L9: 2135.5913
A10: June | B10: 1007.7032 | C10: 71.991442 | D10: 10.904925 | E10: 394.23998 | F10: 222.85861 | G10: 9.905817 | H10: 19.303292 | I10: 21.727059 | J10: 1090.5996 | K10: 627.0044 | L10: 1758.6343
A11: July | B11: 937.16861 | C11: 41.078676 | D11: 10.727374 | E11: 370.24273 | F11: 219.69523 | G11: 13.318434 | H11: 22.568246 | I11: 21.605381 | J11: 988.97466 | K11: 603.2564 | L11: 1636.4047
A12: August | B12: 956.016 | C12: 40.018045 | D12: 9.9637655 | E12: 379.46295 | F12: 209.33787 | G12: 12.639816 | H12: 24.075621 | I12: 24.942121 | J12: 1005.9978 | K12: 601.44064 | L12: 1656.4562
A13: September | B13: 1009.0869 | C13: 48.372022 | D13: 10.619927 | E13: 387.3003 | F13: 200.06344 | G13: 12.804049 | H13: 32.738344 | I13: 21.205641 | J13: 1068.0789 | K13: 600.16779 | L13: 1722.1906
A14: October | B14: 1278.2611 | C14: 72.025559 | D14: 12.585538 | E14: 426.29679 | F14: 218.68864 | G14: 12.155888 | H14: 99.62133 | I14: 19.602129 | J14: 1362.8722 | K14: 657.14132 | L14: 2139.237
A15: November | B15: 1382.8364 | C15: 98.719504 | D15: 12.021402 | E15: 429.72071 | F15: 220.38958 | G15: 12.055033 | H15: 35.388256 | I15: 16.665404 | J15: 1493.5773 | K15: 662.16532 | L15: 2207.7963
A16: December | B16: 1430.8842 | C16: 92.450779 | D16: 12.026843 | E16: 414.72971 | F16: 198.90949 | G16: 11.390119 | H16: 33.206332 | I16: 18.636696 | J16: 1535.3618 | K16: 625.02931 | L16: 2212.2341
A17: Annual | B17: =SUM(B5:B16) -> 15353.363 | C17: =SUM(C5:C16) -> 1106.2655 | D17: =SUM(D5:D16) -> 133.36616 | E17: =SUM(E5:E16) -> 4978.1716 | F17: =SUM(F5:F16) -> 2538.7946 | G17: =SUM(G5:G16) -> 141.88016 | H17: =SUM(H5:H16) -> 398.21438 | I17: =SUM(I5:I16) -> 248.72115 | ... L17: =SUM(L5:L16) -> 24898.776
A18: 2018
A19: January | B19: 1750.4243 | C19: 118.77616 | D19: 12.792768 | E19: 463.65523 | F19: 213.49889 | G19: 9.4821172 | H19: 38.894704 | I19: 20.647118 | J19: 1881.9933 | K19: 686.63623 | L19: 2628.1713
A20: February | B20: 1561.253 | C20: 98.303561 | D20: 11.178184 | E20: 428.49475 | F20: 204.10664 | G20: 9.3916769 | H20: 32.2823 | I20: 19.32103 | J20: 1670.7348 | K20: 641.99307 | L20: 2364.3312
A21: March | B21: 1754.5378 | C21: 126.32163 | D21: 12.401527 | E21: 462.84405 | F21: 232.97848 | G21: 10.566439 | H21: 32.844865 | I21: 21.090236 | J21: 1893.2609 | K21: 706.38896 | L21: 2653.585
A22: April | B22: 1468.8598 | C22: 127.7098 | D22: 12.02746 | E22: 458.14514 | F22: 238.50062 | G22: 11.646622 | H22: 39.8826 | I22: 22.734108 | J22: 1608.597 | K22: 708.29237 | L22: 2379.5061
A23: May | B23: 1343.2709 | C23: 118.4857 | D23: 12.238932 | E23: 445.58325 | F23: 241.16469 | G23: 11.560302 | H23: 45.151666 | I23: 23.223839 | J23: 1473.9956 | K23: 698.30825 | L23: 2240.6793
A24: June | B24: 1058.4845 | C24: 66.407539 | D24: 11.012143 | E24: 433.38244 | F24: 236.30195 | G24: 12.584632 | H24: 35.454869 | I24: 22.018316 | J24: 1135.9042 | K24: 682.26902 | L24: 1875.6464
A25: July | B25: 996.00141 | C25: 63.110934 | D25: 11.907021 | E25: 424.15131 | F25: 241.11726 | G25: 13.209371 | H25: 100.84133 | I25: 21.009438 | J25: 1071.0194 | K25: 678.47794 | L25: 1871.3481
A26: August | B26: 1019.3299 | C26: 48.635975 | D26: 12.054612 | E26: 417.86223 | F26: 225.48431 | G26: 11.180757 | H26: 37.634548 | I26: 22.74548 | J26: 1080.0205 | K26: 654.5273 | L26: 1794.9278
A27: September | B27: 1023.9414 | C27: 59.137523 | D27: 12.114364 | E27: 403.34395 | F27: 211.70317 | G27: 11.520364 | H27: 36.043157 | I27: 18.035336 | J27: 1095.1933 | K27: 626.56748 | L27: 1775.8392
A28: October | B28: 1281.3815 | C28: 72.098642 | D28: 14.703259 | E28: 457.60274 | F28: 236.32222 | G28: 12.007484 | H28: 44.030849 | I28: 26.10342 | J28: 1368.1834 | K28: 705.93245 | L28: 2144.2501
A29: November | B29: 1312.6393 | C29: 81.993901 | D29: 13.965286 | E29: 435.45172 | F29: 217.29774 | G29: 12.405114 | H29: 37.430299 | I29: 17.451253 | J29: 1408.5985 | K29: 665.15457 | L29: 2128.6346
A30: December | B30: 1494.6246 | C30: 91.452255 | D30: 14.184295 | E30: 509.72467 | F30: 208.01554 | G30: 12.287039 | H30: 31.723142 | I30: 25.868156 | J30: 1600.2611 | K30: 730.02726 | L30: 2387.8797
A31: Annual | B31: =SUM(B19:B30) -> 16064.748 | C31: =SUM(C19:C30) -> 1072.4336 | D31: =SUM(D19:D30) -> 150.57985 | E31: =SUM(E19:E30) -> 5340.2415 | F31: =SUM(F19:F30) -> 2706.4915 | G31: =SUM(G19:G30) -> 137.84192 | H31: =SUM(H19:H30) -> 512.21433 | I31: =SUM(I19:I30) -> 260.24773 | ... L31: =SUM(L19:L30) -> 26244.799
A32: 2019
A33: January | B33: 1753.3138 | C33: 93.699208 | D33: 15.276253 | E33: 435.44792 | F33: 221.31074 | G33: 10.805318 | H33: 42.519597 | I33: 22.181828 | J33: 1862.2893 | K33: 667.56397 | L33: 2594.5547
A34: February | B34: 1559.4306 | C34: 85.669426 | D34: 12.884628 | E34: 405.98778 | F34: 198.28105 | G34: 8.9230954 | H34: 28.06825 | I34: 18.896125 | J34: 1657.9847 | K34: 613.19193 | L34: 2318.141
A35: March | B35: 1775.5266 | C35: 110.46145 | D35: 13.948211 | E35: 448.04595 | F35: 226.46059 | G35: 12.160399 | H35: 33.244053 | I35: 19.259413 | J35: 1899.9363 | K35: 686.66693 | L35: 2639.1067
A36: April | B36: 1574.0139 | C36: 115.61731 | D36: 13.04585 | E36: 464.33775 | F36: 224.47031 | G36: 14.127843 | H36: 85.038225 | I36: 18.685718 | J36: 1702.677 | K36: 702.93591 | L36: 2509.3369
A37: May | B37: 1375.1113 | C37: 84.294238 | D37: 13.777615 | E37: 453.68911 | F37: 234.42644 | G37: 13.66318 | H37: 34.307074 | I37: 23.225027 | J37: 1473.1832 | K37: 701.77873 | L37: 2232.494
A38: June | B38: 1105.19 | C38: 45.457154 | D38: 12.927338 | E38: 415.99947 | F38: 224.16371 | G38: 11.774332 | H38: 29.833213 | I38: 15.620003 | J38: 1163.5745 | K38: 651.93751 | L38: 1860.9652
A39: July | B39: 1076.5547 | C39: 21.018374 | D39: 13.479649 | E39: 449.00211 | F39: 230.67068 | G39: 13.836741 | H39: 28.115206 | I39: 18.296478 | J39: 1111.0528 | K39: 693.50953 | L39: 1850.974
A40: August | B40: 1101.0597 | C40: 32.541967 | D40: 13.35634 | E40: 418.84186 | F40: 190.97903 | G40: 13.837226 | H40: 41.853202 | I40: 15.346964 | J40: 1146.958 | K40: 623.65812 | L40: 1827.8163
A41: September | B41: 1121.8106 | C41: 57.446859 | D41: 13.326159 | E41: 431.87774 | F41: 205.00231 | G41: 14.092594 | H41: 29.793755 | I41: 20.864939 | J41: 1192.5837 | K41: 650.97264 | L41: 1894.215
A42: October | B42: 1348.4889 | C42: 76.955836 | D42: 15.200516 | E42: 459.53502 | F42: 237.95493 | G42: 13.60759 | H42: 30.430728 | I42: 23.599292 | J42: 1440.6453 | K42: 711.09755 | L42: 2205.7729
A43: November | B43: 1392.2639 | C43: 93.431234 | D43: 15.299477 | E43: 411.80796 | F43: 226.1034 | G43: 9.4181721 | H43: 20.643114 | I43: 16.885447 | J43: 1500.9946 | K43: 647.32953 | L43: 2185.8527
A44: December | B44: 1504.61 | C44: 92.476919 | D44: 15.96873 | E44: 452.83287 | F44: 233.30896 | G44: 11.351692 | H44: 23.92805 | I44: 20.064636 | J44: 1613.0557 | K44: 697.49353 | L44: 2354.5419
A45: Annual | B45: =SUM(B33:B44) -> 16687.374 | C45: =SUM(C33:C44) -> 909.06998 | D45: =SUM(D33:D44) -> 168.49077 | E45: =SUM(E33:E44) -> 5247.4055 | F45: =SUM(F33:F44) -> 2653.1321 | G45: =SUM(G33:G44) -> 147.59818 | H45: =SUM(H33:H44) -> 427.77447 | I45: =SUM(I33:I44) -> 232.92587 | ... L45: =SUM(L33:L44) -> 26473.771
A46: 2020
A47: January | B47: 1764.2576 | C47: 102.46487 | D47: 17.25238 | E47: 477.38943 | F47: 243.23332 | G47: 11.426259 | H47: 42.105488 | I47: 22.486073 | J47: 1883.9748 | K47: 732.04901 | L47: 2680.6154
A48: February | B48: 1610.1989 | C48: 100.61601 | D48: 14.12115 | E48: 440.91436 | F48: 238.60082 | G48: 9.5538798 | H48: 33.998081 | I48: 22.056608 | J48: 1724.9361 | K48: 689.06907 | L48: 2470.0598
A49: March | B49: 1720.4437 | C49: 166.36175 | D49: 15.70151 | E49: 503.23887 | F49: 244.24276 | G49: 12.684054 | H49: 36.977379 | I49: 41.909179 | J49: 1902.5069 | K49: 760.16569 | L49: 2741.5592
A50: April | B50: 1325.208 | C50: 141.10505 | D50: 13.106404 | E50: 535.58244 | F50: 205.8317 | G50: 12.249302 | H50: 29.563518 | I50: 36.250217 | J50: 1479.4195 | K50: 753.66345 | L50: 2298.8967
A51: May | B51: 1387.7231 | C51: 96.642884 | D51: 13.740487 | E51: 515.94037 | F51: 244.34847 | G51: 10.634286 | H51: 25.091566 | I51: 29.151277 | J51: 1498.1065 | K51: 770.92313 | L51: 2323.2724
A52: June | B52: 1239.1954 | C52: 52.48419 | D52: 13.896437 | E52: 460.17904 | F52: 261.65512 | G52: 11.038614 | H52: 27.76533 | I52: 30.705536 | J52: 1305.576 | K52: 732.87278 | L52: 2096.9197
A53: July | B53: 1190.6858 | C53: 41.452278 | D53: 14.569586 | E53: 458.51815 | F53: 264.54636 | G53: 12.75441 | H53: 23.924752 | I53: 31.101784 | J53: 1246.7077 | K53: 735.81893 | L53: 2037.5532
A54: August | B54: 1112.2137 | C54: 37.688809 | D54: 14.798115 | E54: 471.32487 | F54: 236.13407 | G54: 12.548529 | H54: 19.893309 | I54: 23.859222 | J54: 1164.7006 | K54: 720.00747 | L54: 1928.4606
A55: September | B55: 1196.2467 | C55: 63.063391 | D55: 14.290057 | E55: 462.10335 | F55: 246.70092 | G55: 13.802113 | H55: 21.893796 | I55: 23.78755 | J55: 1273.6002 | K55: 722.60638 | L55: 2041.8879
A56: October | B56: 1406.5986 | C56: 85.627016 | D56: 14.968063 | E56: 490.69499 | F56: 250.95674 | G56: 14.13748 | H56: 25.117462 | I56: 27.508862 | J56: 1507.1937 | K56: 755.78921 | L56: 2315.6092
A57: November | B57: 1513.7745 | C57: 120.35828 | D57: 15.663442 | E57: 524.96787 | F57: 257.84479 | G57: 14.089761 | H57: 23.202075 | I57: 25.329374 | J57: 1649.7962 | K57: 796.90242 | L57: 2495.2301
A58: December | B58: 1593.1552 | C58: 97.582043 | D58: 16.471274 | E58: 513.99026 | F58: 243.01783 | G58: 13.431311 | H58: 47.747992 | I58: 23.590754 | J58: 1707.2085 | K58: 770.4394 | L58: 2548.9866
A59: Annual | B59: =SUM(B47:B58) -> 17059.701 | C59: =SUM(C47:C58) -> 1105.4466 | D59: =SUM(D47:D58) -> 178.57891 | E59: =SUM(E47:E58) -> 5854.844 | F59: =SUM(F47:F58) -> 2937.1129 | G59: =SUM(G47:G58) -> 148.35 | H59: =SUM(H47:H58) -> 357.28075 | I59: =SUM(I47:I58) -> 337.73644 | ... L59: =SUM(L47:L58) -> 27979.051
A60: 2021
A61: January | B61: 1866.3283 | C61: 105.5178 | D61: 16.594225 | E61: 503.60981 | F61: 254.14453 | G61: 13.224845 | H61: 27.988586 | I61: 19.049476 | J61: 1988.4403 | K61: 770.97919 | L61: 2806.4576
A62: February | B62: 1746.8241 | C62: 100.1014 | D62: 14.755881 | E62: 478.19672 | F62: 233.80331 | G62: 11.452699 | H62: 17.449127 | I62: 18.950905 | J62: 1861.6814 | K62: 723.45273 | L62: 2621.5342
A63: March | B63: 1963.3254 | C63: 140.30925 | D63: 16.608485 | E63: 545.23917 | F63: 273.29946 | G63: 15.415561 | H63: 29.634672 | I63: 27.975539 | J63: 2120.2431 | K63: 833.95419 | L63: 3011.8075
A64: April | B64: 1664.2089 | C64: 113.99165 | D64: 15.100699 | E64: 554.02606 | F64: 302.03753 | G64: 13.56852 | H64: 34.310174 | I64: 29.953068 | J64: 1793.3012 | K64: 869.63211 | L64: 2727.1966
A65: May | B65: 1531.4962 | C65: 89.252008 | D65: 15.651555 | E65: 546.86359 | F65: 302.91395 | G65: 14.810071 | H65: 43.356371 | I65: 28.748424 | J65: 1636.3998 | K65: 864.5876 | L65: 2573.0922
A66: June | B66: 1317.8598 | C66: 65.666982 | D66: 15.565163 | E66: 532.1729 | F66: 299.96753 | G66: 16.362932 | H66: 28.924503 | I66: 28.779904 | J66: 1399.0919 | K66: 848.50336 | L66: 2305.2997
A67: July | B67: 1281.0628 | C67: 38.13054 | D67: 15.070921 | E67: 452.01384 | F67: 288.13206 | G67: 15.417808 | H67: 33.832375 | I67: 26.417636 | J67: 1334.2642 | K67: 755.5637 | L67: 2150.078
A68: August | B68: 1233.8555 | C68: 38.670992 | D68: 15.908857 | E68: 478.02384 | F68: 267.06444 | G68: 15.827671 | H68: 40.68639 | I68: 28.003912 | J68: 1288.4354 | K68: 760.91595 | L68: 2118.0416
A69: September | B69: 1271.8713 | C69: 60.386856 | D69: 16.026956 | E69: 495.53107 | F69: 266.08862 | G69: 11.409859 | H69: 41.876798 | I69: 24.10782 | J69: 1348.2851 | K69: 773.02955 | L69: 2187.2993
A70: October | B70: 1417.6159 | C70: 83.099389 | D70: 17.612805 | E70: 517.25469 | F70: 276.36767 | G70: 11.377819 | H70: 50.699945 | I70: 27.06165 | J70: 1518.328 | K70: 805.00018 | L70: 2401.0898
A71: November | B71: 1498.1685 | C71: 111.17985 | D71: 17.967692 | E71: 491.62019 | F71: 311.10686 | G71: 14.656876 | H71: 166.1803 | I71: 26.746052 | J71: 1627.316 | K71: 817.38392 | L71: 2637.6263
A72: December | B72: 1659.3091 | C72: 84.32861 | D72: 18.403837 | E72: 511.03458 | F72: 275.83127 | G72: 14.353414 | H72: 61.769084 | I72: 27.749056 | J72: 1762.0416 | K72: 801.21927 | L72: 2652.779
A73: Annual | B73: =SUM(B61:B72) -> 18451.926 | C73: =SUM(C61:C72) -> 1030.6353 | D73: =SUM(D61:D72) -> 195.26708 | E73: =SUM(E61:E72) -> 6105.5864 | F73: =SUM(F61:F72) -> 3350.7572 | G73: =SUM(G61:G72) -> 167.87808 | H73: =SUM(H61:H72) -> 576.70833 | I73: =SUM(I61:I72) -> 313.54344 | ... L73: =SUM(L61:L72) -> 30192.302
A74: 2022
A75: January | B75: 1866.2268 | C75: 102.36925 | D75: 19.099267 | E75: 555.62032 | F75: 285.36297 | G75: 12.605847 | H75: 35.994126 | I75: 27.0434 | J75: 1987.6953 | K75: 853.58914 | L75: 2904.322
A76: February | B76: 1739.7573 | C76: 93.23124 | D76: 17.715955 | E76: 527.78134 | F76: 245.53948 | G76: 13.340579 | H76: 34.645565 | I76: 23.737721 | J76: 1850.7045 | K76: 786.6614 | L76: 2695.7492
A77: March | B77: 1926.7472 | C77: 135.19231 | D77: 17.011604 | E77: 604.42351 | F77: 335.2898 | G77: 15.422347 | H77: 75.693562 | I77: 29.042664 | J77: 2078.9511 | K77: 955.13566 | L77: 3138.823
A78: April | B78: 1703.2689 | C78: 154.60995 | D78: 15.559226 | E78: 590.2806 | F78: 318.18888 | G78: 14.148939 | H78: 73.644601 | I78: 30.083178 | J78: 1873.4381 | K78: 922.61842 | L78: 2899.7843
A79: May | B79: 1552.4518 | C79: 151.96218 | D79: 17.849008 | E79: 589.62164 | F79: 335.10987 | G79: 13.779246 | H79: 37.074484 | I79: 30.606064 | J79: 1722.263 | K79: 938.51076 | L79: 2728.4543
A80: June | B80: 1334.83 | C80: 120.03679 | D80: 16.062389 | E80: 611.4501 | F80: 307.86898 | G80: 13.945096 | H80: 33.465803 | I80: 30.763961 | J80: 1470.9292 | K80: 933.26418 | L80: 2468.4232
A81: July | B81: 1247.0152 | C81: 69.43483 | D81: 15.330419 | E81: 504.52367 | F81: 311.66238 | G81: 14.318528 | H81: 26.787203 | I81: 23.258043 | J81: 1331.7804 | K81: 830.50458 | L81: 2212.3302
A82: August | B82: 1302.7322 | C82: 77.072319 | D82: 15.840926 | E82: 499.76442 | F82: 281.7375 | G82: 13.213869 | H82: 36.677147 | I82: 23.673191 | J82: 1395.6454 | K82: 794.71579 | L82: 2250.7116
A83: September | B83: 1298.8702 | C83: 76.607589 | D83: 15.872028 | E83: 486.74874 | F83: 296.22319 | G83: 14.135624 | H83: 31.898325 | I83: 24.733785 | J83: 1391.3498 | K83: 797.10755 | L83: 2245.0895
A84: October | B84: 1553.3457 | C84: 100.55116 | D84: 17.144325 | E84: 597.42466 | F84: 332.04431 | G84: 15.065776 | H84: 33.142603 | I84: 28.094851 | J84: 1671.0412 | K84: 944.53475 | L84: 2676.8134
A85: November | B85: 1575.0369 | C85: 129.63246 | D85: 17.605766 | E85: 528.09573 | F85: 320.92765 | G85: 12.030857 | H85: 64.799814 | I85: 23.837718 | J85: 1722.2751 | K85: 861.05424 | L85: 2671.9669
A86: December | B86: 1717.758 | C86: 126.47435 | D86: 16.410309 | E86: 496.18671 | F86: 298.59793 | G86: 11.872135 | H86: 34.125528 | I86: 23.436408 | J86: 1860.6427 | K86: 806.65678 | L86: 2724.8614
A87: Annual | B87: =SUM(B75:B86) -> 18818.04 | C87: =SUM(C75:C86) -> 1337.1744 | D87: =SUM(D75:D86) -> 201.50122 | E87: =SUM(E75:E86) -> 6591.9215 | F87: =SUM(F75:F86) -> 3668.5529 | G87: =SUM(G75:G86) -> 163.87884 | H87: =SUM(H75:H86) -> 517.94876 | I87: =SUM(I75:I86) -> 318.31098 | ... L87: =SUM(L75:L86) -> 31617.329
A88: 2023
A89: January | B89: 1898.9077 | C89: 157.79797 | D89: 17.447544 | E89: 547.72515 | F89: 336.62006 | G89: 10.748984 | H89: 60.370255 | I89: 26.668828 | J89: 2074.1532 | K89: 895.0942 | L89: 3056.2865
A90: February | B90: 1802.8924 | C90: 149.86168 | D90: 15.031304 | E90: 457.87782 | F90: 297.64112 | G90: 9.067291 | H90: 37.024889 | I90: 30.502312 | J90: 1967.7854 | K90: 764.58623 | L90: 2799.8988
A91: March | B91: 1988.6519 | C91: 190.58588 | D91: 16.798058 | E91: 533.65697 | F91: 341.77115 | G91: 10.164518 | H91: 44.79231 | I91: 34.005889 | J91: 2196.0359 | K91: 885.59264 | L91: 3160.4267
A92: April | B92: 1675.4549 | C92: 157.06142 | D92: 15.704398 | E92: 484.27701 | F92: 333.47908 | G92: 10.026701 | H92: 78.41527 | I92: 31.430526 | J92: 1848.2207 | K92: 827.78278 | L92: 2785.8493
A93: May | B93: 1670.0515 | C93: 152.82127 | D93: 16.219208 | E93: 491.63892 | F93: 328.75954 | G93: 11.012465 | H93: 40.826062 | I93: 33.873251 | J93: 1839.092 | K93: 831.41092 | L93: 2745.2022
A94: June | B94: 1414.8678 | C94: 102.69309 | D94: 15.180202 | E94: 466.08228 | F94: 334.40773 | G94: 9.3908745 | H94: 33.615987 | I94: 25.79498 | J94: 1532.7411 | K94: 809.88089 | L94: 2402.0329
A95: July | B95: 1282.8271 | C95: 63.208781 | D95: 14.833164 | E95: 464.86517 | F95: 330.96164 | G95: 14.328892 | H95: 27.477819 | I95: 22.226384 | J95: 1360.869 | K95: 810.1557 | L95: 2220.7289
A96: August | B96: 1237.7005 | C96: 53.723875 | D96: 15.596237 | E96: 472.87972 | F96: 285.81971 | G96: 11.64526 | H96: 27.749007 | I96: 21.251103 | J96: 1307.0206 | K96: 770.34469 | L96: 2126.3654
A97: September | B97: 1293.6877 | C97: 61.112179 | D97: 15.418791 | E97: 459.77849 | F97: 292.51705 | G97: 9.6373402 | H97: 29.805235 | I97: 28.007259 | J97: 1370.2187 | K97: 761.93287 | L97: 2189.964
A98: October | B98: 1417.0389 | C98: 87.343844 | D98: 16.943021 | E98: 533.4542 | F98: 326.54199 | G98: 10.909864 | H98: 25.825302 | I98: 31.579411 | J98: 1521.3257 | K98: 870.90606 | L98: 2449.6365
A99: November | B99: 1454.0112 | C99: 112.25279 | D99: 16.188515 | E99: 503.46511 | F99: 310.61822 | G99: 10.994786 | H99: 47.814239 | I99: 31.751753 | J99: 1582.4525 | K99: 825.07812 | L99: 2487.0966
A100: December | B100: 1552.4591 | C100: 106.09895 | D100: 16.449421 | E100: 488.03394 | F100: 299.71851 | G100: 8.8449526 | H100: 37.802902 | I100: 29.475741 | J100: 1675.0075 | K100: 796.5974 | L100: 2538.8836
...

Sheet Table 4d-Import Volume
A1: Table 4d--Vegetable seed imports: U.S. volume, by group, by month | G1: =HYPERLINK("#'"&"Index'!A1","INDEX") -> INDEX
A2: Month and year | B2: Leguminous vegetable seeds | C2: Other vegetable seeds/1 | D2: Total
B3: ————————— Million pounds —————————
A4: 2017
A5: January | B5: 30.221763 | C5: 7.2244998 | D5: 37.446263
A6: February | B6: 38.805712 | C6: 5.2503727 | D6: 44.056085
A7: March | B7: 45.496766 | C7: 5.9665598 | D7: 51.463326
A8: April | B8: 33.489002 | C8: 5.1403598 | D8: 38.629362
A9: May | B9: 27.151665 | C9: 5.345425 | D9: 32.49709
A10: June | B10: 23.509459 | C10: 5.8108848 | D10: 29.320343
A11: July | B11: 23.915998 | C11: 6.3812339 | D11: 30.297231
A12: August | B12: 44.945544 | C12: 6.9286549 | D12: 51.874199
A13: September | B13: 52.539307 | C13: 6.5305993 | D13: 59.069907
A14: October | B14: 53.884621 | C14: 5.6791321 | D14: 59.563753
A15: November | B15: 51.016012 | C15: 8.2338554 | D15: 59.249868
A16: December | B16: 40.61371 | C16: 10.637401 | D16: 51.251111
A17: Annual | B17: =SUM(B5:B16) -> 465.58956 | C17: =SUM(C5:C16) -> 79.128979 | D17: =SUM(D5:D16) -> 544.71854
A18: 2018
A19: January | B19: 71.1074 | C19: 9.066526 | D19: 80.173926
A20: February | B20: 54.888366 | C20: 8.6271755 | D20: 63.515541
A21: March | B21: 67.92691 | C21: 7.9614743 | D21: 75.888384
A22: April | B22: 72.112243 | C22: 7.0982543 | D22: 79.210497
A23: May | B23: 57.588888 | C23: 8.1242482 | D23: 65.713136
A24: June | B24: 59.849338 | C24: 8.1641607 | D24: 68.013499
A25: July | B25: 44.362708 | C25: 9.8530582 | D25: 54.215766
A26: August | B26: 30.801202 | C26: 9.304052 | D26: 40.105254
A27: September | B27: 34.303275 | C27: 9.2078004 | D27: 43.511076
A28: October | B28: 48.790856 | C28: 10.915739 | D28: 59.706595
A29: November | B29: 37.509044 | C29: 10.714836 | D29: 48.22388
A30: December | B30: 35.319113 | C30: 10.709616 | D30: 46.028728
A31: Annual | B31: =SUM(B19:B30) -> 614.55934 | C31: =SUM(C19:C30) -> 109.74694 | D31: =SUM(D19:D30) -> 724.30628
A32: 2019
A33: January | B33: 53.293333 | C33: 11.169992 | D33: 64.463324
A34: February | B34: 45.067123 | C34: 8.0443042 | D34: 53.111427
A35: March | B35: 54.830803 | C35: 11.233458 | D35: 66.064262
A36: April | B36: 51.558751 | C36: 10.215002 | D36: 61.773753
A37: May | B37: 48.610604 | C37: 10.533213 | D37: 59.143817
A38: June | B38: 43.365811 | C38: 7.448247 | D38: 50.814058
A39: July | B39: 31.381277 | C39: 10.584611 | D39: 41.965889
A40: August | B40: 20.59896 | C40: 10.452859 | D40: 31.051819
A41: September | B41: 28.37283 | C41: 9.0566889 | D41: 37.429518
A42: October | B42: 35.372101 | C42: 9.0198254 | D42: 44.391926
A43: November | B43: 33.606374 | C43: 10.841201 | D43: 44.447575
A44: December | B44: 27.330107 | C44: 11.442794 | D44: 38.772901
A45: Annual | B45: =SUM(B33:B44) -> 473.38807 | C45: =SUM(C33:C44) -> 120.0422 | D45: =SUM(D33:D44) -> 593.43027
A46: 2020
A47: January | B47: 33.572926 | C47: 10.107178 | D47: 43.680104
A48: February | B48: 27.181434 | C48: 8.781142 | D48: 35.962576
A49: March | B49: 51.944017 | C49: 11.092929 | D49: 63.036947
A50: April | B50: 47.0853 | C50: 8.2939865 | D50: 55.379287
A51: May | B51: 29.732932 | C51: 4.741074 | D51: 34.474006
A52: June | B52: 29.729557 | C52: 8.2221312 | D52: 37.951688
A53: July | B53: 23.565718 | C53: 9.1710317 | D53: 32.73675
A54: August | B54: 20.761712 | C54: 11.162714 | D54: 31.924426
A55: September | B55: 34.628579 | C55: 8.3591794 | D55: 42.987758
A56: October | B56: 27.126702 | C56: 11.271916 | D56: 38.398618
A57: November | B57: 25.785842 | C57: 12.262578 | D57: 38.04842
A58: December | B58: 23.022213 | C58: 12.823562 | D58: 35.845775
A59: Annual | B59: =SUM(B47:B58) -> 374.13693 | C59: =SUM(C47:C58) -> 116.28942 | D59: =SUM(D47:D58) -> 490.42635
A60: 2021
A61: January | B61: 28.565139 | C61: 12.034484 | D61: 40.599623
A62: February | B62: 25.202547 | C62: 7.7612218 | D62: 32.963769
A63: March | B63: 37.654062 | C63: 11.112652 | D63: 48.766713
A64: April | B64: 34.98517 | C64: 12.100444 | D64: 47.085613
A65: May | B65: 31.131207 | C65: 9.512003 | D65: 40.64321
A66: June | B66: 33.148113 | C66: 9.8713036 | D66: 43.019416
A67: July | B67: 40.109775 | C67: 7.7678577 | D67: 47.877633
A68: August | B68: 65.223963 | C68: 9.1809304 | D68: 74.404894
A69: September | B69: 75.190967 | C69: 6.6438419 | D69: 81.834809
A70: October | B70: 67.966478 | C70: 7.3632852 | D70: 75.329764
A71: November | B71: 58.14471 | C71: 9.3197489 | D71: 67.464459
A72: December | B72: 50.672016 | C72: 12.450463 | D72: 63.122479
A73: Annual | B73: =SUM(B61:B72) -> 547.99415 | C73: =SUM(C61:C72) -> 115.11823 | D73: =SUM(D61:D72) -> 663.11238
A74: 2022
A75: January | B75: 50.979076 | C75: 16.998267 | D75: 67.977343
A76: February | B76: 51.039582 | C76: 10.886819 | D76: 61.926401
A77: March | B77: 68.176431 | C77: 7.731854 | D77: 75.908285
A78: April | B78: 70.376003 | C78: 6.165452 | D78: 76.541455
A79: May | B79: 88.923531 | C79: 6.9505556 | D79: 95.874086
A80: June | B80: 96.680423 | C80: 9.0105131 | D80: 105.69094
A81: July | B81: 62.403457 | C81: 10.886839 | D81: 73.290296
A82: August | B82: 50.960976 | C82: 7.8023094 | D82: 58.763286
A83: September | B83: 51.509799 | C83: 11.397612 | D83: 62.907412
A84: October | B84: 55.092152 | C84: 9.4456152 | D84: 64.537768
A85: November | B85: 60.824048 | C85: 9.0576524 | D85: 69.8817
A86: December | B86: 45.154986 | C86: 9.0939493 | D86: 54.248935
A87: Annual | B87: =SUM(B75:B86) -> 752.12046 | C87: =SUM(C75:C86) -> 115.42744 | D87: =SUM(D75:D86) -> 867.5479
A88: 2023
A89: January | B89: 62.971919 | C89: 7.8241836 | D89: 70.796103
A90: February | B90: 76.467102 | C90: 9.3763394 | D90: 85.843441
A91: March | B91: 68.988925 | C91: 9.8827853 | D91: 78.87171
A92: April | B92: 63.693871 | C92: 12.214216 | D92: 75.908087
A93: May | B93: 55.178067 | C93: 8.5846616 | D93: 63.762728
A94: June | B94: 57.793181 | C94: 7.561871 | D94: 65.355052
A95: July | B95: 48.436271 | C95: 8.9039196 | D95: 57.340191
A96: August | B96: 57.242544 | C96: 8.707221 | D96: 65.949765
A97: September | B97: 53.800879 | C97: 10.245201 | D97: 64.04608
A98: October | B98: 63.60254 | C98: 13.625926 | D98: 77.228466
A99: November | B99: 62.277503 | C99: 12.977374 | D99: 75.254877
A100: December | B100: 55.610358 | C100: 11.700362 | D100: 67.31072
...

Sheet Table 5a-Export Value
A1: Table 5a--Vegetable exports: U.S. value, by group, by month/1 | O1: =HYPERLINK("#'"&"Index'!A1","INDEX") -> INDEX
A2: Month and Year | B2: Fresh vegetables, excluding potatoes and mushrooms/1 | C2: Fresh potatoes/2 | D2: Fresh mushrooms | E2: Processed vegetables, excluding potatoes and mushrooms/1,3 | F2: Processed potatoes/4 | G2: Processed mushrooms/5 | H2: Dry peas, chickpeas, and lentils | I2: Dry beans/6 | J2: Fresh Vegetable Total | K2: Processed Vegetable Total | L2: Vegetable and Pulses Total
B3: —————————————————————————————————— $ millions ——————————————————————————————————
A4: 2017
A5: January | B5: 184.06643 | C5: 11.95673 | D5: 1.326771 | E5: 140.04233 | F5: 108.45386 | G5: 0.875161 | H5: 42.507166 | I5: 17.759177 | J5: 197.34993 | K5: 249.37136 | L5: 506.98763
A6: February | B6: 180.28745 | C6: 10.913429 | D6: 1.496184 | E6: 136.21787 | F6: 116.19066 | G6: 0.879355 | H6: 44.242304 | I6: 26.987923 | J6: 192.69706 | K6: 253.28788 | L6: 517.21517
A7: March | B7: 202.40155 | C7: 13.382843 | D7: 1.440108 | E7: 146.56003 | F7: 141.49291 | G7: 0.862038 | H7: 56.96395 | I7: 31.315006 | J7: 217.2245 | K7: 288.91497 | L7: 594.41842
A8: April | B8: 223.65898 | C8: 16.785887 | D8: 1.388572 | E8: 138.37009 | F8: 128.82452 | G8: 0.593937 | H8: 52.301901 | I8: 23.224795 | J8: 241.83344 | K8: 267.78854 | L8: 585.14868
A9: May | B9: 229.33584 | C9: 24.490537 | D9: 1.410735 | E9: 149.17422 | F9: 138.53414 | G9: 0.86853 | H9: 38.791341 | I9: 23.072039 | J9: 255.23711 | K9: 288.5769 | L9: 605.67739
A10: June | B10: 208.45307 | C10: 34.807628 | D10: 2.039758 | E10: 156.53161 | F10: 146.83092 | G10: 1.765937 | H10: 41.828035 | I10: 22.603957 | J10: 245.30045 | K10: 305.12847 | L10: 614.86091
A11: July | B11: 174.51084 | C11: 33.228451 | D11: 1.771096 | E11: 147.58191 | F11: 130.35054 | G11: 1.949318 | H11: 19.178014 | I11: 23.33718 | J11: 209.51039 | K11: 279.88177 | L11: 531.90735
A12: August | B12: 148.25284 | C12: 26.582654 | D12: 1.822748 | E12: 154.0762 | F12: 136.25668 | G12: 1.895731 | H12: 30.159688 | I12: 27.435453 | J12: 176.65824 | K12: 292.22862 | L12: 526.482
A13: September | B13: 146.42129 | C13: 17.807941 | D13: 3.186736 | E13: 139.91777 | F13: 128.88413 | G13: 1.336138 | H13: 48.414178 | I13: 30.580015 | J13: 167.41597 | K13: 270.13803 | L13: 516.54819
A14: October | B14: 178.15623 | C14: 15.459759 | D14: 3.331986 | E14: 151.04627 | F14: 139.1077 | G14: 1.157958 | H14: 53.463688 | I14: 37.131888 | J14: 196.94797 | K14: 291.31193 | L14: 578.85548
A15: November | B15: 198.01304 | C15: 17.732505 | D15: 3.978641 | E15: 136.17959 | F15: 131.85814 | G15: 0.723876 | H15: 47.229995 | I15: 30.460385 | J15: 219.72419 | K15: 268.7616 | L15: 566.17617
A16: December | B16: 198.72707 | C16: 16.467839 | D16: 3.513263 | E16: 140.13613 | F16: 128.061 | G16: 0.966507 | H16: 37.351944 | I16: 31.973939 | J16: 218.70818 | K16: 269.16363 | L16: 557.19769
A17: Annual | B17: =SUM(B5:B16) -> 2272.2846 | C17: =SUM(C5:C16) -> 239.6162 | D17: =SUM(D5:D16) -> 26.706598 | E17: =SUM(E5:E16) -> 1735.834 | F17: =SUM(F5:F16) -> 1574.8452 | G17: =SUM(G5:G16) -> 13.874486 | H17: =SUM(H5:H16) -> 512.4322 | I17: =SUM(I5:I16) -> 325.88176 | ... L17: =SUM(L5:L16) -> 6701.4751
A18: 2018
A19: January | B19: 194.5535 | C19: 14.26691 | D19: 3.098143 | E19: 134.83628 | F19: 111.62187 | G19: 0.705263 | H19: 17.285656 | I19: 26.232383 | J19: 211.91855 | K19: 247.16341 | L19: 502.6
A20: February | B20: 181.45538 | C20: 13.639268 | D20: 2.533276 | E20: 127.36376 | F20: 119.21221 | G20: 0.91133 | H20: 15.816153 | I20: 25.359937 | J20: 197.62792 | K20: 247.4873 | L20: 486.29131
A21: March | B21: 219.85489 | C21: 16.550846 | D21: 2.619442 | E21: 141.84626 | F21: 134.23141 | G21: 0.861437 | H21: 19.86915 | I21: 27.801279 | J21: 239.02518 | K21: 276.93911 | L21: 563.63472
A22: April | B22: 205.87331 | C22: 15.021547 | D22: 2.447245 | E22: 138.40174 | F22: 141.232 | G22: 0.654158 | H22: 25.902732 | I22: 27.390877 | J22: 223.3421 | K22: 280.2879 | L22: 556.92361
A23: May | B23: 228.44278 | C23: 25.373377 | D23: 3.042644 | E23: 150.29109 | F23: 131.95106 | G23: 0.861195 | H23: 23.653238 | I23: 27.447027 | J23: 256.8588 | K23: 283.10334 | L23: 591.0624
A24: June | B24: 202.856 | C24: 29.300128 | D24: 2.621147 | E24: 147.70155 | F24: 143.08558 | G24: 1.09997 | H24: 13.776384 | I24: 22.27505 | J24: 234.77727 | K24: 291.8871 | L24: 562.71581
A25: July | B25: 169.09827 | C25: 25.663142 | D25: 2.014899 | E25: 134.58018 | F25: 126.44511 | G25: 0.73567 | H25: 20.216571 | I25: 13.455485 | J25: 196.77631 | K25: 261.76096 | L25: 492.20933
A26: August | B26: 150.36206 | C26: 22.935122 | D26: 2.449963 | E26: 141.53697 | F26: 125.61961 | G26: 0.815727 | H26: 17.962491 | I26: 18.208549 | J26: 175.74715 | K26: 267.97231 | L26: 479.89049
A27: September | B27: 153.52272 | C27: 20.786976 | D27: 3.192538 | E27: 128.93541 | F27: 125.83736 | G27: 0.713576 | H27: 20.353181 | I27: 17.79441 | J27: 177.50224 | K27: 255.48634 | L27: 471.13617
A28: October | B28: 175.49232 | C28: 17.914437 | D28: 5.495615 | E28: 135.7602 | F28: 127.60185 | G28: 0.765939 | H28: 25.980348 | I28: 23.91219 | J28: 198.90237 | K28: 264.12799 | L28: 512.92289
A29: November | B29: 201.97928 | C29: 17.521105 | D29: 4.428882 | E29: 129.93388 | F29: 138.62432 | G29: 0.744198 | H29: 24.046236 | I29: 24.116448 | J29: 223.92927 | K29: 269.30239 | L29: 541.39435
A30: December | B30: 228.58206 | C30: 16.515147 | D30: 4.090045 | E30: 129.15424 | F30: 125.65923 | G30: 0.41579 | H30: 32.224969 | I30: 22.539373 | J30: 249.18725 | K30: 255.22927 | L30: 559.18086
A31: Annual | B31: =SUM(B19:B30) -> 2312.0726 | C31: =SUM(C19:C30) -> 235.488 | D31: =SUM(D19:D30) -> 38.033839 | E31: =SUM(E19:E30) -> 1640.3416 | F31: =SUM(F19:F30) -> 1551.1216 | G31: =SUM(G19:G30) -> 9.284253 | H31: =SUM(H19:H30) -> 257.08711 | I31: =SUM(I19:I30) -> 276.53301 | ... L31: =SUM(L19:L30) -> 6319.9619
A32: 2019
A33: January | B33: 210.08234 | C33: 15.781206 | D33: 3.298227 | E33: 124.12729 | F33: 132.61299 | G33: 0.979974 | H33: 22.156924 | I33: 25.511396 | J33: 229.16177 | K33: 257.72026 | L33: 534.55035
A34: February | B34: 194.60703 | C34: 14.725353 | D34: 2.723572 | E34: 123.11042 | F34: 120.14782 | G34: 0.759044 | H34: 20.241978 | I34: 24.627311 | J34: 212.05596 | K34: 244.01729 | L34: 500.94253
A35: March | B35: 228.33222 | C35: 15.092685 | D35: 3.12173 | E35: 144.10152 | F35: 152.16365 | G35: 0.620849 | H35: 26.604334 | I35: 35.811878 | J35: 246.54664 | K35: 296.88602 | L35: 605.84886
A36: April | B36: 220.63267 | C36: 20.496383 | D36: 2.783472 | E36: 123.51237 | F36: 138.53318 | G36: 0.39928 | H36: 24.664538 | I36: 29.759095 | J36: 243.91252 | K36: 262.44483 | L36: 560.78098
A37: May | B37: 238.85139 | C37: 23.454251 | D37: 2.734772 | E37: 139.54451 | F37: 137.59844 | G37: 0.561969 | H37: 28.64969 | I37: 24.919472 | J37: 265.04041 | K37: 277.70492 | L37: 596.31449
A38: June | B38: 222.4773 | C38: 33.041716 | D38: 1.941774 | E38: 136.52737 | F38: 142.70585 | G38: 0.550547 | H38: 26.005426 | I38: 18.94781 | J38: 257.46079 | K38: 279.78376 | L38: 582.19779
A39: July | B39: 191.89101 | C39: 32.572485 | D39: 2.618187 | E39: 129.12341 | F39: 135.11235 | G39: 0.470645 | H39: 36.671732 | I39: 15.507681 | J39: 227.08168 | K39: 264.7064 | L39: 543.9675
A40: August | B40: 155.52606 | C40: 26.065937 | D40: 2.640936 | E40: 133.57979 | F40: 143.15043 | G40: 0.72556 | H40: 36.881234 | I40: 21.500505 | J40: 184.23294 | K40: 277.45578 | L40: 520.07046
A41: September | B41: 145.053 | C41: 19.598576 | D41: 3.495223 | E41: 124.13975 | F41: 133.436 | G41: 0.657086 | H41: 22.451897 | I41: 19.941841 | J41: 168.1468 | K41: 258.23284 | L41: 468.77338
A42: October | B42: 177.86678 | C42: 19.760279 | D42: 3.723222 | E42: 143.96926 | F42: 150.65166 | G42: 0.384193 | H42: 26.812966 | I42: 23.248789 | J42: 201.35028 | K42: 295.00511 | L42: 546.41714
A43: November | B43: 203.91049 | C43: 17.000401 | D43: 4.082198 | E43: 131.00708 | F43: 147.15057 | G43: 0.40593 | H43: 28.37842 | I43: 28.118024 | J43: 224.99309 | K43: 278.56357 | L43: 560.05311
A44: December | B44: 203.14009 | C44: 16.894024 | D44: 3.644312 | E44: 116.18743 | F44: 137.33202 | G44: 0.514256 | H44: 23.975342 | I44: 27.477846 | J44: 223.67842 | K44: 254.03371 | L44: 529.16532
A45: Annual | B45: =SUM(B33:B44) -> 2392.3704 | C45: =SUM(C33:C44) -> 254.4833 | D45: =SUM(D33:D44) -> 36.807625 | E45: =SUM(E33:E44) -> 1568.9302 | F45: =SUM(F33:F44) -> 1670.5949 | G45: =SUM(G33:G44) -> 7.029333 | H45: =SUM(H33:H44) -> 323.49448 | I45: =SUM(I33:I44) -> 295.37165 | ... L45: =SUM(L33:L44) -> 6549.0819
A46: 2020
A47: January | B47: 206.65187 | C47: 15.722531 | D47: 2.687564 | E47: 115.63994 | F47: 135.90406 | G47: 0.476046 | H47: 27.776725 | I47: 23.369171 | J47: 225.06197 | K47: 252.02005 | L47: 528.22792
A48: February | B48: 190.80028 | C48: 16.112494 | D48: 2.578547 | E48: 112.86338 | F48: 128.07549 | G48: 0.409717 | H48: 26.539039 | I48: 25.194804 | J48: 209.49132 | K48: 241.34859 | L48: 502.57375
A49: March | B49: 206.64541 | C49: 18.714781 | D49: 2.335491 | E49: 131.24769 | F49: 134.75562 | G49: 0.536014 | H49: 37.56236 | I49: 28.885089 | J49: 227.69568 | K49: 266.53933 | L49: 560.68246
A50: April | B50: 186.21581 | C50: 20.219511 | D50: 1.272146 | E50: 128.94982 | F50: 104.93869 | G50: 0.419414 | H50: 43.288239 | I50: 29.792538 | J50: 207.70747 | K50: 234.30793 | L50: 515.09617
A51: May | B51: 221.93903 | C51: 16.616181 | D51: 2.127728 | E51: 115.72647 | F51: 102.78976 | G51: 0.841439 | H51: 42.913297 | I51: 34.147325 | J51: 240.68294 | K51: 219.35766 | L51: 537.10123
A52: June | B52: 201.2679 | C52: 25.531876 | D52: 2.446724 | E52: 121.70632 | F52: 93.357703 | G52: 1.020349 | H52: 35.854776 | I52: 25.391549 | J52: 229.2465 | K52: 216.08437 | L52: 506.57719
A53: July | B53: 191.71035 | C53: 29.532244 | D53: 2.801961 | E53: 116.56434 | F53: 104.41281 | G53: 0.728882 | H53: 28.088787 | I53: 18.917619 | J53: 224.04456 | K53: 221.70603 | L53: 492.75699
A54: August | B54: 161.50271 | C54: 25.49537 | D54: 2.593676 | E54: 121.45502 | F54: 113.57459 | G54: 0.432776 | H54: 51.019723 | I54: 12.156528 | J54: 189.59176 | K54: 235.46238 | L54: 488.23039
A55: September | B55: 151.79095 | C55: 21.529709 | D55: 2.809439 | E55: 125.11763 | F55: 119.35826 | G55: 0.355444 | H55: 42.141546 | I55: 24.708234 | J55: 176.1301 | K55: 244.83133 | L55: 487.81121
A56: October | B56: 200.07512 | C56: 18.652886 | D56: 5.605764 | E56: 137.17732 | F56: 134.31436 | G56: 0.450418 | H56: 41.06855 | I56: 33.729011 | J56: 224.33376 | K56: 271.9421 | L56: 571.07343
A57: November | B57: 200.73157 | C57: 19.087299 | D57: 4.469721 | E57: 125.80819 | F57: 132.3452 | G57: 0.31906 | H57: 36.804 | I57: 33.463642 | J57: 224.28859 | K57: 258.47246 | L57: 553.02869
A58: December | B58: 187.08261 | C58: 16.051009 | D58: 4.266666 | E58: 125.17741 | F58: 127.56139 | G58: 0.445619 | H58: 37.701976 | I58: 36.075984 | J58: 207.40029 | K58: 253.18442 | L58: 534.36267
A59: Annual | B59: =SUM(B47:B58) -> 2306.4136 | C59: =SUM(C47:C58) -> 243.26589 | D59: =SUM(D47:D58) -> 35.995427 | E59: =SUM(E47:E58) -> 1477.4335 | F59: =SUM(F47:F58) -> 1431.388 | G59: =SUM(G47:G58) -> 6.435178 | H59: =SUM(H47:H58) -> 450.75902 | I59: =SUM(I47:I58) -> 325.83149 | ... L59: =SUM(L47:L58) -> 6277.5221
A60: 2021
A61: January | B61: 194.45979 | C61: 16.696307 | D61: 3.078072 | E61: 118.06936 | F61: 127.38511 | G61: 0.425036 | H61: 31.859349 | I61: 38.111999 | J61: 214.23417 | K61: 245.8795 | L61: 530.08502
A62: February | B62: 182.3516 | C62: 14.98457 | D62: 2.991171 | E62: 114.63213 | F62: 125.20583 | G62: 0.650951 | H62: 22.20164 | I62: 31.447878 | J62: 200.32734 | K62: 240.48891 | L62: 494.46577
A63: March | B63: 212.00181 | C63: 20.957542 | D63: 3.095918 | E63: 141.34596 | F63: 150.2006 | G63: 0.590663 | H63: 34.048948 | I63: 37.707913 | J63: 236.05527 | K63: 292.13722 | L63: 599.94935
A64: April | B64: 207.44617 | C64: 23.430834 | D64: 2.480146 | E64: 133.42409 | F64: 149.354 | G64: 0.324288 | H64: 37.061093 | I64: 39.96019 | J64: 233.35715 | K64: 283.10238 | L64: 593.48081
A65: May | B65: 239.05377 | C65: 21.492083 | D65: 2.857814 | E65: 134.98778 | F65: 138.14906 | G65: 0.62017 | H65: 42.262927 | I65: 37.768438 | J65: 263.40366 | K65: 273.75701 | L65: 617.19204
A66: June | B66: 204.77234 | C66: 27.844675 | D66: 2.677505 | E66: 132.44804 | F66: 133.43601 | G66: 0.509744 | H66: 33.791432 | I66: 30.640267 | J66: 235.29452 | K66: 266.39379 | L66: 566.12001
A67: July | B67: 185.29319 | C67: 35.186296 | D67: 2.531811 | E67: 133.31687 | F67: 140.29844 | G67: 0.520855 | H67: 32.691062 | I67: 22.039392 | J67: 223.0113 | K67: 274.13616 | L67: 551.87791
A68: August | B68: 155.38508 | C68: 27.049257 | D68: 2.060005 | E68: 126.69813 | F68: 138.74045 | G68: 0.398457 | H68: 23.610912 | I68: 21.215917 | J68: 184.49434 | K68: 265.83704 | L68: 495.15821
A69: September | B69: 165.05247 | C69: 20.676238 | D69: 2.269026 | E69: 122.63249 | F69: 123.75393 | G69: 0.625795 | H69: 27.032166 | I69: 26.677285 | J69: 187.99773 | K69: 247.01222 | L69: 488.7194
A70: October | B70: 208.68203 | C70: 23.42587 | D70: 4.031034 | E70: 132.96105 | F70: 129.26965 | G70: 0.735345 | H70: 30.844988 | I70: 29.171952 | J70: 236.13894 | K70: 262.96604 | L70: 559.12192
A71: November | B71: 227.98686 | C71: 21.54013 | D71: 3.570948 | E71: 124.45694 | F71: 116.91556 | G71: 0.490558 | H71: 37.092582 | I71: 16.787228 | J71: 253.09794 | K71: 241.86305 | L71: 548.8408
A72: December | B72: 213.72044 | C72: 22.991116 | D72: 3.784797 | E72: 123.19634 | F72: 120.12091 | G72: 0.494937 | H72: 24.767964 | I72: 16.351816 | J72: 240.49635 | K72: 243.81218 | L72: 525.42832
A73: Annual | B73: =SUM(B61:B72) -> 2396.2055 | C73: =SUM(C61:C72) -> 276.27492 | D73: =SUM(D61:D72) -> 35.428247 | E73: =SUM(E61:E72) -> 1538.1692 | F73: =SUM(F61:F72) -> 1592.8295 | G73: =SUM(G61:G72) -> 6.386799 | H73: =SUM(H61:H72) -> 377.26506 | I73: =SUM(I61:I72) -> 347.88027 | ... L73: =SUM(L61:L72) -> 6570.4396
A74: 2022
A75: January | B75: 195.35545 | C75: 18.644863 | D75: 2.499686 | E75: 108.73377 | F75: 97.609786 | G75: 0.408681 | H75: 19.140121 | I75: 17.72517 | J75: 216.5 | K75: 206.75224 | L75: 460.11753
A76: February | B76: 185.97672 | C76: 18.257902 | D76: 3.102371 | E76: 127.06029 | F76: 130.22302 | G76: 0.565575 | H76: 16.77814 | I76: 20.134065 | J76: 207.337 | K76: 257.84889 | L76: 502.09809
A77: March | B77: 214.18334 | C77: 20.433598 | D77: 3.53804 | E77: 152.27117 | F77: 159.56276 | G77: 0.5275 | H77: 19.241718 | I77: 27.003562 | J77: 238.15498 | K77: 312.36143 | L77: 596.76169
A78: April | B78: 232.42864 | C78: 24.714156 | D78: 2.528002 | E78: 142.0974 | F78: 144.92613 | G78: 0.566388 | H78: 23.470345 | I78: 23.833288 | J78: 259.67079 | K78: 287.58993 | L78: 594.56435
A79: May | B79: 243.20297 | C79: 22.644375 | D79: 2.488365 | E79: 149.95302 | F79: 143.27373 | G79: 0.596642 | H79: 37.036654 | I79: 32.111994 | J79: 268.33571 | K79: 293.82339 | L79: 631.30775
A80: June | B80: 226.29702 | C80: 27.53724 | D80: 2.302688 | E80: 142.33278 | F80: 152.91423 | G80: 0.797579 | H80: 30.463684 | I80: 25.47606 | J80: 256.13695 | K80: 296.04459 | L80: 608.12129
A81: July | B81: 197.02843 | C81: 26.159093 | D81: 2.216213 | E81: 129.97868 | F81: 162.97225 | G81: 0.971403 | H81: 29.483661 | I81: 22.017877 | J81: 225.40373 | K81: 293.92233 | L81: 570.8276
A82: August | B82: 167.34719 | C82: 34.306935 | D82: 2.137763 | E82: 143.47645 | F82: 156.12692 | G82: 0.59109 | H82: 31.378331 | I82: 24.902432 | J82: 203.79189 | K82: 300.19446 | L82: 560.26711
A83: September | B83: 174.69639 | C83: 28.448046 | D83: 2.434988 | E83: 136.46357 | F83: 141.06853 | G83: 0.47077 | H83: 33.1375 | I83: 25.786655 | J83: 205.57943 | K83: 278.00288 | L83: 542.50646
A84: October | B84: 199.44082 | C84: 25.52507 | D84: 3.194469 | E84: 132.59698 | F84: 158.3952 | G84: 0.345164 | H84: 43.09872 | I84: 28.538203 | J84: 228.16036 | K84: 291.33735 | L84: 591.13462
A85: November | B85: 216.31851 | C85: 30.405167 | D85: 2.959418 | E85: 127.26885 | F85: 179.241 | G85: 0.872619 | H85: 35.631686 | I85: 23.842567 | J85: 249.6831 | K85: 307.38247 | L85: 616.53982
A86: December | B86: 234.50662 | C86: 26.512627 | D86: 4.188332 | E86: 125.01773 | F86: 152.51806 | G86: 0.507148 | H86: 38.272082 | I86: 26.691795 | J86: 265.20758 | K86: 278.04293 | L86: 608.21439
A87: Annual | B87: =SUM(B75:B86) -> 2486.7821 | C87: =SUM(C75:C86) -> 303.58907 | D87: =SUM(D75:D86) -> 33.590335 | E87: =SUM(E75:E86) -> 1617.2507 | F87: =SUM(F75:F86) -> 1778.8316 | G87: =SUM(G75:G86) -> 7.220559 | H87: =SUM(H75:H86) -> 357.13264 | I87: =SUM(I75:I86) -> 298.06367 | ... L87: =SUM(L75:L86) -> 6882.4607
A88: 2023
A89: January | B89: 203.40922 | C89: 21.992477 | D89: 2.499701 | E89: 127.49904 | F89: 158.79847 | G89: 1.047968 | H89: 34.544814 | I89: 30.894865 | J89: 227.9014 | K89: 287.34548 | L89: 580.68655
A90: February | B90: 175.50764 | C90: 20.314465 | D90: 2.024286 | E90: 129.5762 | F90: 148.6452 | G90: 0.355751 | H90: 26.422742 | I90: 33.484515 | J90: 197.84639 | K90: 278.57715 | L90: 536.3308
A91: March | B91: 208.61071 | C91: 24.993999 | D91: 1.978255 | E91: 150.09769 | F91: 165.87524 | G91: 0.744697 | H91: 36.115421 | I91: 39.238107 | J91: 235.58296 | K91: 316.71763 | L91: 627.65412
A92: April | B92: 203.30949 | C92: 27.284308 | D92: 1.227293 | E92: 136.38925 | F92: 163.60197 | G92: 0.486411 | H92: 49.431488 | I92: 28.782818 | J92: 231.82109 | K92: 300.47764 | L92: 610.51304
A93: May | B93: 251.02717 | C93: 26.156168 | D93: 1.327622 | E93: 138.90482 | F93: 165.01686 | G93: 0.50756 | H93: 40.222524 | I93: 39.529108 | J93: 278.51096 | K93: 304.42924 | L93: 662.69183
A94: June | B94: 225.93105 | C94: 33.499148 | D94: 1.655107 | E94: 127.02787 | F94: 163.44717 | G94: 0.277836 | H94: 42.25442 | I94: 33.749107 | J94: 261.08531 | K94: 290.75288 | L94: 627.84172
A95: July | B95: 193.70242 | C95: 37.974806 | D95: 1.77752 | E95: 121.66835 | F95: 161.56483 | G95: 0.644418 | H95: 28.228434 | I95: 30.986329 | J95: 233.45475 | K95: 283.8776 | L95: 576.54711
A96: August | B96: 166.5068 | C96: 28.86102 | D96: 1.502157 | E96: 140.92479 | F96: 176.78885 | G96: 0.643822 | H96: 43.979913 | I96: 31.399216 | J96: 196.86997 | K96: 318.35746 | L96: 590.60656
A97: September | B97: 159.34521 | C97: 31.121163 | D97: 2.676674 | E97: 134.804 | F97: 172.05984 | G97: 0.517646 | H97: 58.548635 | I97: 43.906225 | J97: 193.14305 | K97: 307.38149 | L97: 602.9794
A98: October | B98: 183.73263 | C98: 29.418168 | D98: 4.1122 | E98: 145.88079 | F98: 175.37008 | G98: 0.576587 | H98: 45.458736 | I98: 53.269638 | J98: 217.263 | K98: 321.82745 | L98: 637.81883
A99: November | B99: 198.70961 | C99: 30.633378 | D99: 2.502408 | E99: 147.85245 | F99: 165.65501 | G99: 0.638309 | H99: 59.883789 | I99: 50.203626 | J99: 231.84539 | K99: 314.14577 | L99: 656.07858
A100: December | B100: 217.73683 | C100: 27.108393 | D100: 1.824784 | E100: 126.27058 | F100: 135.04178 | G100: 0.768796 | H100: 46.404817 | I100: 46.740898 | J100: 246.67 | K100: 262.08116 | L100: 601.89688
...

Sheet Table 5b-Export Value
A1: Table 5b--Vegetable seed exports: U.S. value, by group, by month | G1: =HYPERLINK("#'"&"Index'!A1","INDEX") -> INDEX
A2: Month and Year | B2: Leguminous vegetable seeds | C2: Other vegetable seeds/1 | D2: Total
B3: ————————— Million U.S. dollars —————————
A4: 2017
A5: January | B5: 14.345215 | C5: 43.776086 | D5: 58.121301
A6: February | B6: 15.169071 | C6: 42.233899 | D6: 57.40297
A7: March | B7: 22.374225 | C7: 51.129675 | D7: 73.5039
A8: April | B8: 17.893209 | C8: 33.588456 | D8: 51.481665
A9: May | B9: 17.001377 | C9: 34.146295 | D9: 51.147672
A10: June | B10: 9.498816 | C10: 29.337812 | D10: 38.836628
A11: July | B11: 8.669732 | C11: 20.121331 | D11: 28.791063
A12: August | B12: 8.534485 | C12: 32.836878 | D12: 41.371363
A13: September | B13: 17.277781 | C13: 32.30936 | D13: 49.587141
A14: October | B14: 17.087121 | C14: 38.04826 | D14: 55.135381
A15: November | B15: 18.086532 | C15: 46.755947 | D15: 64.842479
A16: December | B16: 17.784649 | C16: 47.332683 | D16: 65.117332
A17: Annual | B17: =SUM(B5:B16) -> 183.72221 | C17: =SUM(C5:C16) -> 451.61668 | D17: =SUM(D5:D16) -> 635.33889
A18: 2018
A19: January | B19: 14.727972 | C19: 41.444138 | D19: 56.17211
A20: February | B20: 18.721961 | C20: 46.858294 | D20: 65.580255
A21: March | B21: 21.611998 | C21: 46.139358 | D21: 67.751356
A22: April | B22: 15.692755 | C22: 32.642922 | D22: 48.335677
A23: May | B23: 11.542422 | C23: 22.46863 | D23: 34.011052
A24: June | B24: 7.23577 | C24: 19.842322 | D24: 27.078092
A25: July | B25: 6.517183 | C25: 22.62814 | D25: 29.145323
A26: August | B26: 5.406981 | C26: 22.961213 | D26: 28.368194
A27: September | B27: 9.675408 | C27: 29.862025 | D27: 39.537433
A28: October | B28: 14.803373 | C28: 47.224681 | D28: 62.028054
A29: November | B29: 12.833254 | C29: 45.977034 | D29: 58.810288
A30: December | B30: 10.162875 | C30: 54.584443 | D30: 64.747318
A31: Annual | B31: =SUM(B19:B30) -> 148.93195 | C31: =SUM(C19:C30) -> 432.6332 | D31: =SUM(D19:D30) -> 581.56515
A32: 2019
A33: January | B33: 12.56383 | C33: 59.077762 | D33: 71.641592
A34: February | B34: 14.842066 | C34: 51.496477 | D34: 66.338543
A35: March | B35: 19.883709 | C35: 45.682606 | D35: 65.566315
A36: April | B36: 14.799194 | C36: 34.6397 | D36: 49.438894
A37: May | B37: 17.25453 | C37: 27.007419 | D37: 44.261949
A38: June | B38: 5.951669 | C38: 25.029275 | D38: 30.980944
A39: July | B39: 6.84438 | C39: 22.516024 | D39: 29.360404
A40: August | B40: 6.831606 | C40: 26.747119 | D40: 33.578725
A41: September | B41: 9.823945 | C41: 32.883908 | D41: 42.707853
A42: October | B42: 12.675102 | C42: 43.804774 | D42: 56.479876
A43: November | B43: 10.733886 | C43: 49.008133 | D43: 59.742019
A44: December | B44: 12.724708 | C44: 53.183988 | D44: 65.908696
A45: Annual | B45: =SUM(B33:B44) -> 144.92862 | C45: =SUM(C33:C44) -> 471.07719 | D45: =SUM(D33:D44) -> 616.00581
A46: 2020
A47: January | B47: 13.019491 | C47: 44.649449 | D47: 57.66894
A48: February | B48: 11.530036 | C48: 45.077286 | D48: 56.607322
A49: March | B49: 17.653996 | C49: 46.502281 | D49: 64.156277
A50: April | B50: 13.580667 | C50: 31.023989 | D50: 44.604656
A51: May | B51: 10.691938 | C51: 25.825 | D51: 36.516938
A52: June | B52: 5.734729 | C52: 27.682782 | D52: 33.417511
A53: July | B53: 6.287052 | C53: 28.546847 | D53: 34.833899
A54: August | B54: 6.930943 | C54: 37.369895 | D54: 44.300838
A55: September | B55: 12.709402 | C55: 26.083713 | D55: 38.793115
A56: October | B56: 14.479612 | C56: 29.734791 | D56: 44.214403
A57: November | B57: 16.174597 | C57: 38.261516 | D57: 54.436113
A58: December | B58: 18.443519 | C58: 52.909446 | D58: 71.352965
A59: Annual | B59: =SUM(B47:B58) -> 147.23598 | C59: =SUM(C47:C58) -> 433.667 | D59: =SUM(D47:D58) -> 580.90298
A60: 2021
A61: January | B61: 14.729785 | C61: 42.473506 | D61: 57.203291
A62: February | B62: 16.391285 | C62: 43.605787 | D62: 59.997072
A63: March | B63: 21.264242 | C63: 42.53756 | D63: 63.801802
A64: April | B64: 15.742151 | C64: 33.932087 | D64: 49.674238
A65: May | B65: 11.316457 | C65: 23.080695 | D65: 34.397152
A66: June | B66: 5.194532 | C66: 30.605403 | D66: 35.799935
A67: July | B67: 5.556901 | C67: 25.317166 | D67: 30.874067
A68: August | B68: 7.827839 | C68: 26.295231 | D68: 34.12307
A69: September | B69: 6.642429 | C69: 34.791843 | D69: 41.434272
A70: October | B70: 7.300364 | C70: 34.83228 | D70: 42.132644
A71: November | B71: 9.921994 | C71: 35.952966 | D71: 45.87496
A72: December | B72: 13.332571 | C72: 47.935006 | D72: 61.267577
A73: Annual | B73: =SUM(B61:B72) -> 135.22055 | C73: =SUM(C61:C72) -> 421.35953 | D73: =SUM(D61:D72) -> 556.58008
A74: 2022
A75: January | B75: 11.909716 | C75: 37.300103 | D75: 49.209819
A76: February | B76: 13.829527 | C76: 39.470946 | D76: 53.300473
A77: March | B77: 17.939361 | C77: 46.16255 | D77: 64.101911
A78: April | B78: 22.542409 | C78: 25.786402 | D78: 48.328811
A79: May | B79: 15.31546 | C79: 22.691816 | D79: 38.007276
A80: June | B80: 10.686223 | C80: 27.199834 | D80: 37.886057
A81: July | B81: 9.883392 | C81: 26.638268 | D81: 36.52166
A82: August | B82: 11.602752 | C82: 26.696666 | D82: 38.299418
A83: September | B83: 8.784689 | C83: 32.091893 | D83: 40.876582
A84: October | B84: 13.963736 | C84: 31.784825 | D84: 45.748561
A85: November | B85: 13.049705 | C85: 30.826559 | D85: 43.876264
A86: December | B86: 15.569724 | C86: 51.169158 | D86: 66.738882
A87: Annual | B87: =SUM(B75:B86) -> 165.07669 | C87: =SUM(C75:C86) -> 397.81902 | D87: =SUM(D75:D86) -> 562.89571
A88: 2023
A89: January | B89: 18.70575 | C89: 35.177676 | D89: 53.883426
A90: February | B90: 21.297711 | C90: 41.941509 | D90: 63.23922
A91: March | B91: 22.295805 | C91: 41.242617 | D91: 63.538422
A92: April | B92: 26.377077 | C92: 28.174266 | D92: 54.551343
A93: May | B93: 20.128849 | C93: 21.498375 | D93: 41.627224
A94: June | B94: 12.483773 | C94: 22.708162 | D94: 35.191935
A95: July | B95: 12.315938 | C95: 19.724964 | D95: 32.040902
A96: August | B96: 13.764942 | C96: 27.912785 | D96: 41.677727
A97: September | B97: 12.871259 | C97: 26.780127 | D97: 39.651386
A98: October | B98: 18.449341 | C98: 29.644922 | D98: 48.094263
A99: November | B99: 23.015434 | C99: 35.217124 | D99: 58.232558
A100: December | B100: 23.744217 | C100: 41.716335 | D100: 65.460552
...

Sheet Table 5c-Export Volume
A1: Table 5c--Vegetable exports: U.S. volume, by group, by month/1 | O1: =HYPERLINK("#'"&"Index'!A1","INDEX") -> INDEX
A2: Month and Year | B2: Fresh vegetables, excluding potatoes and mushrooms/1 | C2: Fresh potatoes/2 | D2: Fresh mushrooms | E2: Processed vegetables, excluding potatoes and mushrooms/1,3 | F2: Processed potatoes/4 | G2: Processed mushrooms/5 | H2: Dry peas, chickpeas, and lentils | I2: Dry beans/6 | J2: Fresh Vegetable Total | K2: Processed Vegetable Total | L2: Vegetable and Pulses Total
B3: —————————————————————————————————— Million pounds ——————————————————————————————————
A4: 2017
A5: January | B5: 372.12426 | C5: 62.158061 | D5: 0.76243566 | E5: 270.47623 | F5: 189.0849 | G5: 0.37631365 | H5: 139.66615 | I5: 47.639562 | J5: 435.04476 | K5: 459.93745 | L5: 1082.2879
A6: February | B6: 344.73936 | C6: 67.902976 | D6: 0.79678809 | E6: 260.33346 | F6: 197.97002 | G6: 0.56609638 | H6: 145.06325 | I6: 72.636039 | J6: 413.43912 | K6: 458.86957 | L6: 1090.008
A7: March | B7: 376.20671 | C7: 81.712009 | D7: 0.69844429 | E7: 279.47587 | F7: 245.13803 | G7: 0.48238245 | H7: 176.94496 | I7: 84.896437 | J7: 458.61716 | K7: 525.09627 | L7: 1245.5548
A8: April | B8: 370.36754 | C8: 98.592483 | D8: 0.75911109 | E8: 268.65187 | F8: 221.20839 | G8: 0.33792676 | H8: 162.48384 | I8: 57.362367 | J8: 469.71913 | K8: 490.19819 | L8: 1179.7635
A9: May | B9: 403.41836 | C9: 135.50387 | D9: 0.67436981 | E9: 297.75109 | F9: 236.55081 | G9: 0.51723533 | H9: 133.87705 | I9: 58.737966 | J9: 539.59659 | K9: 534.81913 | L9: 1267.0307
A10: June | B10: 383.94173 | C10: 172.84492 | D10: 0.83944975 | E10: 304.9443 | F10: 249.71745 | G10: 0.86553264 | H10: 161.50774 | I10: 59.553835 | J10: 557.6261 | K10: 555.52728 | L10: 1334.215
A11: July | B11: 311.24707 | C11: 170.45165 | D11: 1.0437499 | E11: 286.76031 | F11: 218.93012 | G11: 0.80349015 | H11: 65.360235 | I11: 60.229613 | J11: 482.74248 | K11: 506.49392 | L11: 1114.8262
A12: August | B12: 281.83859 | C12: 112.26017 | D12: 1.1278254 | E12: 293.36078 | F12: 227.94363 | G12: 0.86018863 | H12: 100.9783 | I12: 71.763925 | J12: 395.22659 | K12: 522.1646 | L12: 1090.1334
A13: September | B13: 275.57114 | C13: 76.643794 | D13: 1.3431399 | E13: 273.51654 | F13: 216.3548 | G13: 0.56001603 | H13: 137.34406 | I13: 82.535335 | J13: 353.55807 | K13: 490.43135 | L13: 1063.8688
A14: October | B14: 328.01213 | C14: 66.925001 | D14: 1.4471121 | E14: 306.2291 | F14: 240.33013 | G14: 0.4806893 | H14: 150.25502 | I14: 97.755313 | J14: 396.38424 | K14: 547.03992 | L14: 1191.4345
A15: November | B15: 376.20227 | C15: 82.666212 | D15: 1.6154835 | E15: 260.71658 | F15: 221.12619 | G15: 0.39912708 | H15: 144.13545 | I15: 81.818219 | J15: 460.48397 | K15: 482.2419 | L15: 1168.6795
A16: December | B16: 369.12456 | C16: 76.777436 | D16: 1.5496998 | E16: 267.46978 | F16: 217.92248 | G16: 0.53575857 | H16: 110.42475 | I16: 86.390534 | J16: 447.45169 | K16: 485.92802 | L16: 1130.195
A17: Annual | B17: =SUM(B5:B16) -> 4192.7937 | C17: =SUM(C5:C16) -> 1204.4386 | D17: =SUM(D5:D16) -> 12.657609 | E17: =SUM(E5:E16) -> 3369.6859 | F17: =SUM(F5:F16) -> 2682.2769 | G17: =SUM(G5:G16) -> 6.784757 | H17: =SUM(H5:H16) -> 1628.0408 | I17: =SUM(I5:I16) -> 861.31914 | ... L17: =SUM(L5:L16) -> 13957.997
A18: 2018
A19: January | B19: 352.50967 | C19: 67.388318 | D19: 1.6535111 | E19: 260.78537 | F19: 185.68865 | G19: 0.56067742 | H19: 50.92268 | I19: 67.957071 | J19: 421.5515 | K19: 447.0347 | L19: 987.46595
A20: February | B20: 343.25879 | C20: 62.598912 | D20: 1.3537794 | E20: 246.94221 | F20: 203.4676 | G20: 0.44284916 | H20: 52.037498 | I20: 67.132132 | J20: 407.21148 | K20: 450.85266 | L20: 977.23378
A21: March | B21: 388.76781 | C21: 75.302869 | D21: 1.4000809 | E21: 270.83607 | F21: 228.46297 | G21: 0.52549826 | H21: 78.039556 | I21: 74.871899 | J21: 465.47076 | K21: 499.82455 | L21: 1118.2068
A22: April | B22: 386.77319 | C22: 69.419704 | D22: 1.3090079 | E22: 261.24703 | F22: 241.22351 | G22: 0.34107276 | H22: 102.03237 | I22: 69.767095 | J22: 457.5019 | K22: 502.81161 | L22: 1132.113
A23: May | B23: 427.12019 | C23: 99.644037 | D23: 1.7627611 | E23: 287.18729 | F23: 222.02285 | G23: 0.44129711 | H23: 92.297877 | I23: 72.158837 | J23: 528.52698 | K23: 509.65143 | L23: 1202.6351
A24: June | B24: 381.72391 | C24: 128.87585 | D24: 1.4693567 | E24: 274.58602 | F24: 241.8134 | G24: 0.50020242 | H24: 47.36779 | I24: 59.381557 | J24: 512.06911 | K24: 516.89962 | L24: 1135.7181
A25: July | B25: 315.72026 | C25: 116.61044 | D25: 1.0541315 | E25: 249.64383 | F25: 213.21266 | G25: 0.3289341 | H25: 75.105851 | I25: 38.467944 | J25: 433.38483 | K25: 463.18543 | L25: 1010.1441
A26: August | B26: 287.31734 | C26: 103.73179 | D26: 1.3801665 | E26: 268.58149 | F26: 209.994 | G26: 0.32394725 | H26: 72.52717 | I26: 51.14586 | J26: 392.4293 | K26: 478.89944 | L26: 995.00177
A27: September | B27: 288.18445 | C27: 94.708396 | D27: 1.53033 | E27: 234.57797 | F27: 206.79452 | G27: 0.36203431 | H27: 75.742328 | I27: 50.31509 | J27: 384.42318 | K27: 441.73452 | L27: 952.21511
A28: October | B28: 334.00093 | C28: 80.218594 | D28: 1.7609842 | E28: 253.8079 | F28: 211.77337 | G28: 0.39178128 | H28: 88.93938 | I28: 64.388387 | J28: 415.98051 | K28: 465.97306 | L28: 1035.2813
A29: November | B29: 364.87076 | C29: 85.971777 | D29: 1.7376262 | E29: 245.94464 | F29: 235.78328 | G29: 0.44753839 | H29: 94.503942 | I29: 65.114649 | J29: 452.58016 | K29: 482.17547 | L29: 1094.3742
A30: December | B30: 389.44908 | C30: 76.07605 | D30: 1.9497131 | E30: 247.5823 | F30: 208.70923 | G30: 0.23983208 | H30: 138.67615 | I30: 61.911039 | J30: 467.47484 | K30: 456.53136 | L30: 1124.5934
A31: Annual | B31: =SUM(B19:B30) -> 4259.6964 | C31: =SUM(C19:C30) -> 1060.5467 | D31: =SUM(D19:D30) -> 18.361449 | E31: =SUM(E19:E30) -> 3101.7221 | F31: =SUM(F19:F30) -> 2608.9461 | G31: =SUM(G19:G30) -> 4.9056645 | H31: =SUM(H19:H30) -> 968.19259 | I31: =SUM(I19:I30) -> 742.61156 | ... L31: =SUM(L19:L30) -> 12764.983
A32: 2019
A33: January | B33: 393.17662 | C33: 73.159835 | D33: 1.8468653 | E33: 235.61698 | F33: 227.25915 | G33: 0.61503239 | H33: 89.65375 | I33: 68.953671 | J33: 468.18332 | K33: 463.49116 | L33: 1090.2819
A34: February | B34: 346.3853 | C34: 74.420873 | D34: 1.4960172 | E34: 231.2191 | F34: 200.14442 | G34: 0.40873924 | H34: 82.520775 | I34: 64.876543 | J34: 422.30219 | K34: 431.77226 | L34: 1001.4718
A35: March | B35: 375.61325 | C35: 95.336432 | D35: 1.7274673 | E35: 274.35509 | F35: 260.55179 | G35: 0.33857051 | H35: 110.77069 | I35: 99.253096 | J35: 472.67715 | K35: 535.24544 | L35: 1217.9464
A36: April | B36: 380.56564 | C36: 109.44848 | D36: 1.5287625 | E36: 235.82864 | F36: 229.87315 | G36: 0.22547778 | H36: 109.61387 | I36: 84.128666 | J36: 491.54289 | K36: 465.92727 | L36: 1151.2127
A37: May | B37: 408.69506 | C37: 114.5004 | D37: 1.5042317 | E37: 269.27351 | F37: 231.33209 | G37: 0.30433713 | H37: 125.91412 | I37: 70.100275 | J37: 524.69969 | K37: 500.90994 | L37: 1221.624
A38: June | B38: 376.15602 | C38: 144.40888 | D38: 1.0255596 | E38: 255.85382 | F38: 239.59781 | G38: 0.20734917 | H38: 113.41206 | I38: 52.576169 | J38: 521.59046 | K38: 495.65897 | L38: 1183.2377
A39: July | B39: 308.27097 | C39: 168.417 | D39: 1.4660145 | E39: 238.43491 | F39: 226.2375 | G39: 0.27286394 | H39: 173.23868 | I39: 43.451423 | J39: 478.15398 | K39: 464.94528 | L39: 1159.7894
A40: August | B40: 259.19931 | C40: 116.32131 | D40: 1.4539045 | E40: 249.32238 | F40: 237.0247 | G40: 0.2491929 | H40: 175.1985 | I40: 59.124083 | J40: 376.97452 | K40: 486.59627 | L40: 1097.8934
A41: September | B41: 247.37607 | C41: 82.395288 | D41: 1.2566239 | E41: 226.05692 | F41: 223.27991 | G41: 0.40348562 | H41: 105.14839 | I41: 55.93903 | J41: 331.02798 | K41: 449.74031 | L41: 941.85571
A42: October | B42: 304.89646 | C42: 83.980784 | D42: 1.2069559 | E42: 263.41465 | F42: 254.36954 | G42: 0.17114926 | H42: 123.97539 | I42: 64.680799 | J42: 390.0842 | K42: 517.95534 | L42: 1096.6957
A43: November | B43: 366.59671 | C43: 70.395514 | D43: 1.4530006 | E43: 234.46318 | F43: 244.97078 | G43: 0.22351346 | H43: 131.39544 | I43: 75.712724 | J43: 438.44523 | K43: 479.65748 | L43: 1125.2109
A44: December | B44: 384.736 | C44: 71.131441 | D44: 1.5259185 | E44: 209.81814 | F44: 230.28203 | G44: 0.22126254 | H44: 106.31353 | I44: 70.791641 | J44: 457.39336 | K44: 440.32143 | L44: 1074.82
A45: Annual | B45: =SUM(B33:B44) -> 4151.6674 | C45: =SUM(C33:C44) -> 1203.9162 | D45: =SUM(D33:D44) -> 17.491322 | E45: =SUM(E33:E44) -> 2923.6573 | F45: =SUM(F33:F44) -> 2804.9229 | G45: =SUM(G33:G44) -> 3.6409739 | H45: =SUM(H33:H44) -> 1447.1552 | I45: =SUM(I33:I44) -> 809.58812 | ... L45: =SUM(L33:L44) -> 13362.039
A46: 2020
A47: January | B47: 352.5199 | C47: 81.482488 | D47: 1.3437594 | E47: 206.34829 | F47: 226.07651 | G47: 0.25765425 | H47: 122.17903 | I47: 57.890619 | J47: 435.34614 | K47: 432.68246 | L47: 1048.0982
A48: February | B48: 337.98157 | C48: 78.609014 | D48: 1.3288958 | E48: 206.95983 | F48: 215.40366 | G48: 0.15368204 | H48: 116.46118 | I48: 67.714715 | J48: 417.91948 | K48: 422.51716 | L48: 1024.6125
A49: March | B49: 356.07965 | C49: 84.378739 | D49: 1.218226 | E49: 246.92051 | F49: 228.15204 | G49: 0.20258277 | H49: 169.77425 | I49: 71.019839 | J49: 441.67662 | K49: 475.27513 | L49: 1157.7458
A50: April | B50: 346.33427 | C50: 81.774693 | D50: 0.68492554 | E50: 242.18263 | F50: 172.3149 | G50: 0.1387347 | H50: 190.17941 | I50: 75.885278 | J50: 428.79389 | K50: 414.63626 | L50: 1109.4948
A51: May | B51: 401.76419 | C51: 77.71914 | D51: 1.2813377 | E51: 216.7512 | F51: 172.83278 | G51: 0.29089334 | H51: 189.75106 | I51: 84.187869 | J51: 480.76467 | K51: 389.87487 | L51: 1144.5785
A52: June | B52: 346.05636 | C52: 120.12248 | D52: 1.3422161 | E52: 225.84767 | F52: 151.07708 | G52: 0.44005811 | H52: 163.35433 | I52: 59.949139 | J52: 467.52105 | K52: 377.3648 | L52: 1068.1893
A53: July | B53: 323.19263 | C53: 137.3828 | D53: 1.7236291 | E53: 209.6039 | F53: 171.55785 | G53: 0.23919715 | H53: 135.30057 | I53: 43.182933 | J53: 462.29906 | K53: 381.40094 | L53: 1022.1835
A54: August | B54: 274.21234 | C54: 118.29687 | D54: 1.5554098 | E54: 258.84172 | F54: 184.19672 | G54: 0.19111874 | H54: 250.05563 | I54: 27.196857 | J54: 394.06462 | K54: 443.22956 | L54: 1114.5467
A55: September | B55: 262.06296 | C55: 92.29282 | D55: 1.6411012 | E55: 233.59576 | F55: 196.73886 | G55: 0.13287481 | H55: 194.20428 | I55: 63.960216 | J55: 355.99688 | K55: 430.4675 | L55: 1044.6289
A56: October | B56: 360.72138 | C56: 79.534916 | D56: 2.4856106 | E56: 246.10562 | F56: 218.60459 | G56: 0.16944289 | H56: 190.6749 | I56: 87.94782 | J56: 442.74191 | K56: 464.87966 | L56: 1186.2443
A57: November | B57: 329.85998 | C57: 85.657376 | D57: 1.8653422 | E57: 224.5343 | F57: 221.47831 | G57: 0.13893973 | H57: 165.1159 | I57: 85.631683 | J57: 417.3827 | K57: 446.15155 | L57: 1114.2818
A58: December | B58: 335.51255 | C58: 70.680433 | D58: 1.5842661 | E58: 226.99351 | F58: 213.63782 | G58: 0.1845666 | H58: 169.98052 | I58: 94.436794 | J58: 407.77725 | K58: 440.81589 | L58: 1113.0105
A59: Annual | B59: =SUM(B47:B58) -> 4026.2978 | C59: =SUM(C47:C58) -> 1107.9318 | D59: =SUM(D47:D58) -> 18.054719 | E59: =SUM(E47:E58) -> 2744.6849 | F59: =SUM(F47:F58) -> 2372.0711 | G59: =SUM(G47:G58) -> 2.5397451 | H59: =SUM(H47:H58) -> 2057.031 | I59: =SUM(I47:I58) -> 819.00376 | ... L59: =SUM(L47:L58) -> 13147.615
A60: 2021
A61: January | B61: 341.57644 | C61: 81.210398 | D61: 1.6723892 | E61: 210.86613 | F61: 213.80534 | G61: 0.14293671 | H61: 140.93768 | I61: 91.972771 | J61: 424.45923 | K61: 424.81441 | L61: 1082.1841
A62: February | B62: 329.19497 | C62: 68.951806 | D62: 1.7186312 | E62: 206.08319 | F62: 218.29949 | G62: 0.22393895 | H62: 93.089608 | I62: 73.573511 | J62: 399.86541 | K62: 424.60662 | L62: 991.13515
A63: March | B63: 382.05911 | C63: 118.26211 | D63: 1.6848696 | E63: 259.59035 | F63: 259.86561 | G63: 0.22361708 | H63: 143.44368 | I63: 86.647509 | J63: 502.00609 | K63: 519.67957 | L63: 1251.7768
A64: April | B64: 394.35298 | C64: 115.25121 | D64: 1.3902483 | E64: 249.99648 | F64: 259.68262 | G64: 0.17811367 | H64: 146.57324 | I64: 89.693072 | J64: 510.99443 | K64: 509.85721 | L64: 1257.118
A65: May | B65: 449.0849 | C65: 108.32509 | D65: 1.513092 | E65: 244.27651 | F65: 228.92735 | G65: 0.31324381 | H65: 161.69792 | I65: 86.678663 | J65: 558.92309 | K65: 473.5171 | L65: 1280.8168
A66: June | B66: 390.88052 | C66: 148.9363 | D66: 1.352375 | E66: 235.09432 | F66: 216.44626 | G66: 0.22814317 | H66: 126.96719 | I66: 66.16487 | J66: 541.16919 | K66: 451.76872 | L66: 1186.07
A67: July | B67: 326.17506 | C67: 184.74318 | D67: 1.3952153 | E67: 244.01995 | F67: 232.04696 | G67: 0.25810399 | H67: 115.98745 | I67: 50.972308 | J67: 512.31345 | K67: 476.32501 | L67: 1155.5982
A68: August | B68: 254.46701 | C68: 129.55057 | D68: 1.0828798 | E68: 226.90637 | F68: 230.56141 | G68: 0.16743447 | H68: 81.517176 | I68: 48.05884 | J68: 385.10045 | K68: 457.63521 | L68: 972.31168
A69: September | B69: 270.80455 | C69: 87.283516 | D69: 0.95334937 | E69: 218.46611 | F69: 210.91173 | G69: 0.30328993 | H69: 86.664282 | I69: 67.505501 | J69: 359.04142 | K69: 429.68113 | L69: 942.89233
A70: October | B70: 324.45872 | C70: 94.337905 | D70: 1.1883886 | E70: 242.93367 | F70: 212.5254 | G70: 0.33616747 | H70: 90.435683 | I70: 67.039728 | J70: 419.98501 | K70: 455.79524 | L70: 1033.2557
A71: November | B71: 343.76382 | C71: 88.333044 | D71: 0.85951181 | E71: 227.13003 | F71: 189.75737 | G71: 0.26612 | H71: 123.49344 | I71: 34.479905 | J71: 432.95638 | K71: 417.15352 | L71: 1008.0832
A72: December | B72: 364.17828 | C72: 90.659852 | D72: 1.2231224 | E72: 219.15581 | F72: 186.21771 | G72: 0.37850725 | H72: 81.273159 | I72: 32.086466 | J72: 456.06125 | K72: 405.75203 | L72: 975.1729
A73: Annual | B73: =SUM(B61:B72) -> 4170.9964 | C73: =SUM(C61:C72) -> 1315.845 | D73: =SUM(D61:D72) -> 16.034073 | E73: =SUM(E61:E72) -> 2784.5189 | F73: =SUM(F61:F72) -> 2659.0472 | G73: =SUM(G61:G72) -> 3.0196165 | H73: =SUM(H61:H72) -> 1392.0805 | I73: =SUM(I61:I72) -> 794.87314 | ... L73: =SUM(L61:L72) -> 13136.415
A74: 2022
A75: January | B75: 320.41042 | C75: 75.057565 | D75: 1.1120535 | E75: 188.73452 | F75: 156.45758 | G75: 0.17863396 | H75: 54.475969 | I75: 35.684542 | J75: 396.58004 | K75: 345.37073 | L75: 832.11128
A76: February | B76: 305.65118 | C76: 75.7834 | D76: 1.3913594 | E76: 223.57296 | F76: 211.0418 | G76: 0.24644815 | H76: 45.051036 | I76: 39.417557 | J76: 382.82594 | K76: 434.86121 | L76: 902.15574
A77: March | B77: 325.64823 | C77: 103.12288 | D77: 1.643555 | E77: 268.28715 | F77: 255.88349 | G77: 0.22303947 | H77: 50.164444 | I77: 54.529277 | J77: 430.41467 | K77: 524.39367 | L77: 1059.5021
A78: April | B78: 383.04266 | C78: 111.69916 | D78: 1.0366819 | E78: 246.04 | F78: 229.13076 | G78: 0.30778957 | H78: 63.028591 | I78: 46.781012 | J78: 495.7785 | K78: 475.47855 | L78: 1081.0667
A79: May | B79: 397.55534 | C79: 102.81885 | D79: 0.98103061 | E79: 268.51699 | F79: 215.53313 | G79: 0.28463221 | H79: 91.386753 | I79: 64.280455 | J79: 501.35523 | K79: 484.33475 | L79: 1141.3572
A80: June | B80: 390.25236 | C80: 116.19229 | D80: 0.8990429 | E80: 259.32151 | F80: 227.59143 | G80: 0.33291124 | H80: 75.468344 | I80: 52.201802 | J80: 507.3437 | K80: 487.24585 | L80: 1122.2597
A81: July | B81: 303.58994 | C81: 119.5869 | D81: 0.96458633 | E81: 221.75747 | F81: 247.09417 | G81: 0.36589019 | H81: 74.482584 | I81: 43.935274 | J81: 424.14143 | K81: 469.21753 | L81: 1011.7768
A82: August | B82: 272.93177 | C82: 124.40491 | D82: 0.94250263 | E82: 253.6631 | F82: 218.6317 | G82: 0.19663691 | H82: 83.934174 | I82: 50.589784 | J82: 398.27919 | K82: 472.49144 | L82: 1005.2946
A83: September | B83: 258.10026 | C83: 96.261339 | D83: 0.7878263 | E83: 227.53584 | F83: 193.95759 | G83: 0.21297095 | H83: 82.134113 | I83: 59.483181 | J83: 355.14943 | K83: 421.7064 | L83: 918.47313
A84: October | B84: 265.95528 | C84: 87.139036 | D84: 0.76876955 | E84: 216.90611 | F84: 207.85979 | G84: 0.20766443 | H84: 113.92727 | I84: 64.977603 | J84: 353.86309 | K84: 424.97356 | L84: 957.74153
A85: November | B85: 268.61853 | C85: 106.71062 | D85: 0.83482445 | E85: 211.64684 | F85: 244.96457 | G85: 0.39182978 | H85: 99.986677 | I85: 51.408041 | J85: 376.16397 | K85: 457.00324 | L85: 984.56193
A86: December | B86: 299.33744 | C86: 95.288629 | D86: 1.6043193 | E86: 209.83416 | F86: 195.90113 | G86: 0.23853796 | H86: 101.78532 | I86: 52.553225 | J86: 396.23039 | K86: 405.97382 | L86: 956.54276
A87: Annual | B87: =SUM(B75:B86) -> 3791.0934 | C87: =SUM(C75:C86) -> 1214.0656 | D87: =SUM(D75:D86) -> 12.966552 | E87: =SUM(E75:E86) -> 2795.8166 | F87: =SUM(F75:F86) -> 2604.0471 | G87: =SUM(G75:G86) -> 3.1869848 | H87: =SUM(H75:H86) -> 935.82528 | I87: =SUM(I75:I86) -> 615.84175 | ... L87: =SUM(L75:L86) -> 11972.843
A88: 2023
A89: January | B89: 305.78794 | C89: 82.291874 | D89: 1.1895725 | E89: 213.79463 | F89: 210.66027 | G89: 0.73233375 | H89: 86.481499 | I89: 61.945343 | J89: 389.26939 | K89: 425.18723 | L89: 962.88346
A90: February | B90: 288.43927 | C90: 77.584416 | D90: 0.83967241 | E90: 219.81926 | F90: 190.54162 | G90: 0.18749874 | H90: 68.124836 | I90: 64.030056 | J90: 366.86336 | K90: 410.54838 | L90: 909.56663
A91: March | B91: 349.73998 | C91: 92.849337 | D91: 0.90913346 | E91: 248.73806 | F91: 212.12139 | G91: 0.3055166 | H91: 94.208392 | I91: 74.620245 | J91: 443.49845 | K91: 461.16497 | L91: 1073.4921
A92: April | B92: 321.89629 | C92: 109.96378 | D92: 0.44894274 | E92: 231.04097 | F92: 218.28249 | G92: 0.21010495 | H92: 134.66964 | I92: 54.121521 | J92: 432.30901 | K92: 449.53357 | L92: 1070.6337
A93: May | B93: 399.67712 | C93: 92.73322 | D93: 0.52992293 | E93: 238.58442 | F93: 203.99263 | G93: 0.19170516 | H93: 104.89887 | I93: 74.971318 | J93: 492.94026 | K93: 442.76875 | L93: 1115.5792
A94: June | B94: 362.08693 | C94: 134.75329 | D94: 0.64063026 | E94: 214.30819 | F94: 199.45203 | G94: 0.094199115 | H94: 111.07406 | I94: 66.412389 | J94: 497.48084 | K94: 413.85441 | L94: 1088.8217
A95: July | B95: 299.89018 | C95: 166.11501 | D95: 0.78602954 | E95: 206.46934 | F95: 193.20935 | G95: 0.31514639 | H95: 77.723977 | I95: 62.157686 | J95: 466.79122 | K95: 399.99384 | L95: 1006.6667
A96: August | B96: 273.64766 | C96: 101.72336 | D96: 0.64348746 | E96: 230.19774 | F96: 218.74343 | G96: 0.26862004 | H96: 132.46818 | I96: 61.406496 | J96: 376.0145 | K96: 449.20979 | L96: 1019.099
A97: September | B97: 251.66574 | C97: 109.16903 | D97: 0.80461891 | E97: 217.89773 | F97: 213.42749 | G97: 0.26860461 | H97: 185.40491 | I97: 98.895865 | J97: 361.63939 | K97: 431.59382 | L97: 1077.534
A98: October | B98: 300.09141 | C98: 105.14949 | D98: 1.1434694 | E98: 239.67473 | F98: 210.72462 | G98: 0.25475517 | H98: 113.03956 | I98: 116.58289 | J98: 406.38438 | K98: 450.6541 | L98: 1086.6609
A99: November | B99: 325.17876 | C99: 108.88686 | D99: 0.75985626 | E99: 239.14725 | F99: 198.11483 | G99: 0.26619054 | H99: 150.3598 | I99: 96.082022 | J99: 434.82548 | K99: 437.52827 | L99: 1118.7956
A100: December | B100: 350.02108 | C100: 96.743525 | D100: 0.58468576 | E100: 214.59639 | F100: 162.95825 | G100: 0.44525881 | H100: 111.51926 | I100: 88.99642 | J100: 447.3493 | K100: 377.99991 | L100: 1025.8649
...

Sheet Table 5d-Export Volume
A1: Table 5d--Vegetable seed exports: U.S. volume, by group, by month | G1: =HYPERLINK("#'"&"Index'!A1","INDEX") -> INDEX
A2: Month and Year | B2: Leguminous vegetable seeds | C2: Other vegetable seeds/1 | D2: Total
B3: ————————— Million pounds —————————
A4: 2017
A5: January | B5: 29.923872 | C5: 4.8349402 | D5: 34.758812
A6: February | B6: 32.720244 | C6: 5.3064936 | D6: 38.026738
A7: March | B7: 48.115181 | C7: 6.6196682 | D7: 54.734849
A8: April | B8: 39.996275 | C8: 4.9419703 | D8: 44.938245
A9: May | B9: 41.510901 | C9: 4.6079347 | D9: 46.118836
A10: June | B10: 22.119759 | C10: 4.2550143 | D10: 26.374773
A11: July | B11: 24.387661 | C11: 3.6758445 | D11: 28.063506
A12: August | B12: 19.024207 | C12: 4.5250607 | D12: 23.549267
A13: September | B13: 38.707163 | C13: 4.1707999 | D13: 42.877963
A14: October | B14: 43.104435 | C14: 4.6838089 | D14: 47.788244
A15: November | B15: 42.353175 | C15: 5.407128 | D15: 47.760303
A16: December | B16: 36.388017 | C16: 5.3425634 | D16: 41.730581
A17: Annual | B17: =SUM(B5:B16) -> 418.35089 | C17: =SUM(C5:C16) -> 58.371227 | D17: =SUM(D5:D16) -> 476.72212
A18: 2018
A19: January | B19: 26.728468 | C19: 5.1767317 | D19: 31.905199
A20: February | B20: 26.821613 | C20: 6.3915295 | D20: 33.213142
A21: March | B21: 33.601747 | C21: 5.3173513 | D21: 38.919098
A22: April | B22: 29.357778 | C22: 5.722378 | D22: 35.080156
A23: May | B23: 21.339336 | C23: 3.6761597 | D23: 25.015496
A24: June | B24: 16.419804 | C24: 3.8991793 | D24: 20.318984
A25: July | B25: 14.057924 | C25: 4.1299394 | D25: 18.187863
A26: August | B26: 11.081811 | C26: 3.9460055 | D26: 15.027817
A27: September | B27: 24.868818 | C27: 3.9717247 | D27: 28.840542
A28: October | B28: 43.146945 | C28: 5.1986545 | D28: 48.345599
A29: November | B29: 26.245148 | C29: 5.4349812 | D29: 31.680129
A30: December | B30: 18.951478 | C30: 6.0560719 | D30: 25.00755
A31: Annual | B31: =SUM(B19:B30) -> 292.62087 | C31: =SUM(C19:C30) -> 58.920707 | D31: =SUM(D19:D30) -> 351.54158
A32: 2019
A33: January | B33: 21.573489 | C33: 6.25005 | D33: 27.823539
A34: February | B34: 20.977882 | C34: 5.9167265 | D34: 26.894608
A35: March | B35: 31.590981 | C35: 5.5760087 | D35: 37.16699
A36: April | B36: 25.611756 | C36: 5.0997198 | D36: 30.711476
A37: May | B37: 28.554859 | C37: 4.6466897 | D37: 33.201548
A38: June | B38: 13.045991 | C38: 4.0945861 | D38: 17.140577
A39: July | B39: 14.073255 | C39: 3.4784888 | D39: 17.551744
A40: August | B40: 16.966117 | C40: 3.5583072 | D40: 20.524424
A41: September | B41: 24.001343 | C41: 3.6550637 | D41: 27.656407
A42: October | B42: 37.823145 | C42: 4.3264374 | D42: 42.149582
A43: November | B43: 24.133514 | C43: 4.8671895 | D43: 29.000704
A44: December | B44: 24.855012 | C44: 5.3145427 | D44: 30.169555
A45: Annual | B45: =SUM(B33:B44) -> 283.20734 | C45: =SUM(C33:C44) -> 56.78381 | D45: =SUM(D33:D44) -> 339.99115
A46: 2020
A47: January | B47: 20.205805 | C47: 6.5627846 | D47: 26.76859
A48: February | B48: 23.155348 | C48: 5.9036112 | D48: 29.058959
A49: March | B49: 26.83369 | C49: 7.1405853 | D49: 33.974275
A50: April | B50: 27.628355 | C50: 4.8798682 | D50: 32.508223
A51: May | B51: 20.929177 | C51: 3.4764584 | D51: 24.405635
A52: June | B52: 12.556772 | C52: 3.5757766 | D52: 16.132549
A53: July | B53: 12.102137 | C53: 3.3765713 | D53: 15.478708
A54: August | B54: 13.178749 | C54: 3.6841537 | D54: 16.862903
A55: September | B55: 28.757005 | C55: 3.9926642 | D55: 32.749669
A56: October | B56: 35.917348 | C56: 3.9254386 | D56: 39.842787
A57: November | B57: 38.175391 | C57: 4.7287215 | D57: 42.904112
A58: December | B58: 36.497331 | C58: 5.9720184 | D58: 42.46935
A59: Annual | B59: =SUM(B47:B58) -> 295.93711 | C59: =SUM(C47:C58) -> 57.218652 | D59: =SUM(D47:D58) -> 353.15576
A60: 2021
A61: January | B61: 30.71784 | C61: 5.5108158 | D61: 36.228656
A62: February | B62: 28.832022 | C62: 6.143968 | D62: 34.97599
A63: March | B63: 37.183928 | C63: 7.102668 | D63: 44.286596
A64: April | B64: 27.78422 | C64: 4.9514193 | D64: 32.735639
A65: May | B65: 20.037079 | C65: 4.1999847 | D65: 24.237063
A66: June | B66: 9.4495858 | C66: 4.4968459 | D66: 13.946432
A67: July | B67: 11.483158 | C67: 3.4002336 | D67: 14.883392
A68: August | B68: 15.676159 | C68: 4.1953991 | D68: 19.871558
A69: September | B69: 13.994384 | C69: 4.5360529 | D69: 18.530437
A70: October | B70: 15.739698 | C70: 4.5189605 | D70: 20.258659
A71: November | B71: 15.035542 | C71: 5.8720256 | D71: 20.907567
A72: December | B72: 22.598601 | C72: 4.1925992 | D72: 26.7912
A73: Annual | B73: =SUM(B61:B72) -> 248.53222 | C73: =SUM(C61:C72) -> 59.120972 | D73: =SUM(D61:D72) -> 307.65319
A74: 2022
A75: January | B75: 17.12509 | C75: 4.6919352 | D75: 21.817025
A76: February | B76: 18.84934 | C76: 5.3466662 | D76: 24.196007
A77: March | B77: 23.70899 | C77: 6.4271782 | D77: 30.136168
A78: April | B78: 36.611921 | C78: 4.4979659 | D78: 41.109887
A79: May | B79: 24.501256 | C79: 3.4967806 | D79: 27.998037
A80: June | B80: 21.153806 | C80: 4.3082669 | D80: 25.462073
A81: July | B81: 17.824076 | C81: 2.7697798 | D81: 20.593856
A82: August | B82: 16.002619 | C82: 3.8685329 | D82: 19.871152
A83: September | B83: 15.307938 | C83: 3.7661304 | D83: 19.074069
A84: October | B84: 23.199603 | C84: 4.2599989 | D84: 27.459602
A85: November | B85: 20.020987 | C85: 3.5942624 | D85: 23.61525
A86: December | B86: 25.393357 | C86: 4.3277095 | D86: 29.721067
A87: Annual | B87: =SUM(B75:B86) -> 259.69898 | C87: =SUM(C75:C86) -> 51.355207 | D87: =SUM(D75:D86) -> 311.05419
A88: 2023
A89: January | B89: 24.874104 | C89: 4.2654024 | D89: 29.139507
A90: February | B90: 27.692388 | C90: 4.7689912 | D90: 32.461379
A91: March | B91: 34.329991 | C91: 4.9407467 | D91: 39.270738
A92: April | B92: 46.211701 | C92: 4.0551101 | D92: 50.266811
A93: May | B93: 36.285363 | C93: 3.3767565 | D93: 39.66212
A94: June | B94: 22.902261 | C94: 3.1714731 | D94: 26.073734
A95: July | B95: 19.959745 | C95: 3.181535 | D95: 23.14128
A96: August | B96: 23.694135 | C96: 3.4684755 | D96: 27.162611
A97: September | B97: 22.647156 | C97: 2.9069515 | D97: 25.554107
A98: October | B98: 33.138287 | C98: 3.9921615 | D98: 37.130448
A99: November | B99: 42.112252 | C99: 4.8109804 | D99: 46.923232
A100: December | B100: 36.593038 | C100: 5.3905977 | D100: 41.983636
...

Sheet Table 6-Trade Percent
A1: Table 6--Vegetables: Percent of U.S. supply and availability accounted for by trade/1 | O1: =HYPERLINK("#'"&"Index'!A1","INDEX") -> INDEX
B2: --------------------------------------- Fresh Market ---------------------------------------- | H2: ------------------------------------------- Processing -------------------------------------------- | N2: ------------------------------------- Total --------------------------------------
B3: ————— Million lbs., fresh weight ————— | F3: ———— Percent ———— | H3: ————— Million lbs., fresh weight ————— | L3: ———— Percent ———— | N3: ————— Million lbs., fresh weight —————— | R3: ——— Percent ———
A4: Year | B4: Exports | C4: Imports | D4: Total supply/2 | E4: Total availability | F4: Percent of supply exported/3 | G4: Percent of availability imported/4 | H4: Exports | I4: Imports | J4: Total supply/2 | K4: Total availability | L4: Percent of supply exported/3 | M4: Percent of availability imported/4 | N4: Exports | O4: Imports | P4: Total supply/2 | Q4: Total availability | R4: Percent of supply exported/3 | S4: Percent of availability imported/4
A5: 1990 | B5: 2513.868 | C5: 3106.387 | D5: 36410.587 | E5: 31932.695 | F5: 6.9042227 | G5: 9.7279199 | H5: 2931.834 | I5: 3500.117 | J5: 56595.716 | K5: 32262.059 | L5: 5.1803108 | M5: 10.849019 | N5: 5445.702 | O5: 6606.504 | P5: 93006.303 | Q5: 64194.754 | R5: 5.8551967 | S5: 10.291346
A6: 1991 | B6: 2714.687 | C6: 3133.089 | D6: 35912.262 | E6: 31448.822 | F6: 7.5592203 | G6: 9.9625003 | H6: 3187.58 | I6: 3330.943 | J6: 60310.226 | K6: 33449.254 | L6: 5.285306 | M6: 9.9581982 | N6: 5902.267 | O6: 6464.032 | P6: 96222.488 | Q6: 64898.076 | R6: 6.1339788 | S6: 9.960283
A7: 1992 | B7: 2939.398 | C7: 2810.86 | D7: 38126.332 | E7: 33248.029 | F7: 7.709627 | G7: 8.4542154 | H7: 4038.859 | I7: 3360.906 | J7: 58312.407 | K7: 33055.71 | L7: 6.926243 | M7: 10.167399 | N7: 6978.257 | O7: 6171.766 | P7: 96438.739 | Q7: 66303.739 | R7: 7.235948 | S7: 9.3083227
A8: 1993 | B8: 2992.151 | C8: 3674.058 | D8: 40247.863 | E8: 35284.398 | F8: 7.4343102 | G8: 10.412699 | H8: 4274.693 | I8: 3605.985 | J8: 56230.923 | K8: 33997.87 | L8: 7.6020324 | M8: 10.606503 | N8: 7266.844 | O8: 7280.043 | P8: 96478.786 | Q8: 69282.268 | R8: 7.5320641 | S8: 10.507801
A9: 1994 | B9: 3374.866 | C9: 3617.803 | D9: 42801.414 | E9: 37287.303 | F9: 7.8849404 | G9: 9.7025065 | H9: 4554.131 | I9: 3908.809 | J9: 60030.85 | K9: 33930.545 | L9: 7.5863177 | M9: 11.52003 | N9: 7928.997 | O9: 7526.612 | P9: 102832.26 | Q9: 71217.848 | R9: 7.7106121 | S9: 10.568435
A10: 1995 | B10: 3195.391 | C10: 4346.65 | D10: 41808.33 | E10: 36459.296 | F10: 7.642953 | G10: 11.921925 | H10: 4761.769 | I10: 3830.906 | J10: 61885.675 | K10: 34307.873 | L10: 7.6944608 | M10: 11.166259 | N10: 7957.16 | O10: 8177.556 | P10: 103694 | Q10: 70767.169 | R10: 7.6736934 | S10: 11.555579
A11: 1996 | B11: 3215.674 | C11: 5053.34 | D11: 43363.439 | E11: 38038.993 | F11: 7.4156342 | G11: 13.284631 | H11: 5122.411 | I11: 4129.152 | J11: 63166.031 | K11: 34319.863 | L11: 8.1094394 | M11: 12.031377 | N11: 8338.085 | O11: 9182.492 | P11: 106529.47 | Q11: 72358.856 | R11: 7.8270219 | S11: 12.690212
A12: 1997 | B12: 3335.77 | C12: 5106.381 | D12: 46388.884 | E12: 40761.435 | F12: 7.1908822 | G12: 12.527481 | H12: 5983.983 | I12: 4315.004 | J12: 61728.013 | K12: 34057.93 | L12: 9.6941125 | M12: 12.669601 | N12: 9319.753 | O12: 9421.385 | P12: 108116.9 | Q12: 74819.365 | R12: 8.6200707 | S12: 12.592174
A13: 1998 | B13: 3348.411 | C13: 5923.322 | D13: 46003.915 | E13: 40379.618 | F13: 7.2785349 | G13: 14.669089 | H13: 5778.103 | I13: 4831.32 | J13: 58693.187 | K13: 34630.538 | L13: 9.8445889 | M13: 13.951039 | N13: 9126.514 | O13: 10754.642 | P13: 104697.1 | Q13: 75010.156 | R13: 8.7170646 | S13: 14.337581
A14: 1999 | B14: 3495.554 | C14: 5629.391 | D14: 48372.089 | E14: 42220.099 | F14: 7.2263863 | G14: 13.333439 | H14: 5420.771 | I14: 5944.939 | J14: 63457.24 | K14: 34761.069 | L14: 8.5423996 | M14: 17.10229 | N14: 8916.325 | O14: 11574.33 | P14: 111829.33 | Q14: 76981.168 | R14: 7.9731543 | S14: 15.035275
A15: 2000 | B15: 3789.27 | C15: 5514.546 | D15: 48793.491 | E15: 42614.634 | F15: 7.7659334 | G15: 12.940498 | H15: 5356.604 | I15: 5254.297 | J15: 63557.5 | K15: 34865.071 | L15: 8.4279652 | M15: 15.070375 | N15: 9145.874 | O15: 10768.843 | P15: 112350.99 | Q15: 77479.705 | R15: 8.140448 | S15: 13.898921
A16: 2001 | B16: 3765.151 | C16: 6157.135 | D16: 48630.448 | E16: 42463.738 | F16: 7.7423737 | G16: 14.499748 | H16: 5306.202 | I16: 6104.918 | J16: 60086.481 | K16: 33179.299 | L16: 8.8309415 | M16: 18.39978 | N16: 9071.353 | O16: 12262.053 | P16: 108716.93 | Q16: 75643.037 | R16: 8.3440114 | S16: 16.210419
... A39: 2024 | B39: 3778.471 | C39: 18254.344 | D39: 55966.393 | E39: 50314.114 | F39: 6.7513213 | G39: 36.280762 | H39: 9599.782 | I39: 17158.979 | J39: 64574.842 | K39: 32392.41 | L39: 14.866133 | M39: 52.972221 | N39: 13378.253 | O39: 35413.323 | P39: 120541.24 | Q39: 82706.524 | R39: 11.098487 | S39: 42.818053
A40: Most recent year is preliminary.
A41: 1/ Includes 30 major fresh vegetables. Excludes potatoes, sweet potatoes, mushrooms, and melons.
A42: 2/ Equals production plus imports and includes the net change in onion stocks and nets out onion shrinkage.
A43: 3/ Percent of U.S. supply of vegetables exported.
A44: 4/ Percent of U.S. availability of vegetables accounted for by imports.
A45: Source: USDA, Economic Research Service.

Sheet Table 7-Import Percent
A1: Table 7--Vegetables, fresh market: Share of availability imported/1 | O1: =HYPERLINK("#'"&"Index'!A1","INDEX") -> INDEX
A2: Year/3 | B2: Artichokes | C2: Asparagus/4 | D2: Beans, snap/green | E2: Broccoli | F2: Cabbage | G2: Carrots | H2: Cauliflower | I2: Celery/2 | J2: Cucumbers | K2: Eggplant/2 | L2: Garlic/2 | M2: Lettuce, head | N2: Lettuce, leaf/romaine | O2: Mushrooms | P2: Onions | Q2: Peppers, bell/2 | R2: Potatoes | S2: Pumpkins | T2: Radishes | U2: Spinach | V2: Squash | W2: Sweet corn | X2: Sweet potatoes | Y2: Tomatoes | Z2: Fresh, all/1
A3: 1980 | B3: 43.754675 | C3: 10.81832 | D3: 8.4720172 | E3: 0.20891158 | F3: 1.6363125 | G3: 7.7604055 | H3: 2.8261711 | I3: 0.29188993 | J3: 35.952246 | K3: 33.854646 | L3: 12.49694 | M3: 0.25869897 | N3: NA | O3: 0.2672225 | P3: 5.520599 | Q3: 26.510425 | R3: 1.8757204 | S3: NA | T3: 12.122378 | U3: NA | V3: 16.53637 | W3: 0.064399333 | X3: 0.25511949 | Y3: 22.30682 | Z3: 7.738438
A4: 1981 | B4: 38.045375 | C4: 12.275172 | D4: 6.8766669 | E4: 0.23410339 | F4: 0.3147182 | G4: 6.2468908 | H4: 3.5600763 | I4: 0.44250063 | J4: 40.726245 | K4: 32.922201 | L4: 13.192612 | M4: 0.1990015 | N4: NA | O4: 0.29266908 | P4: 5.9267457 | Q4: 19.82207 | R4: 3.7215309 | S4: NA | T4: 4.8441778 | U4: NA | V4: 15.125753 | W4: 0.025534052 | X4: 0.73508793 | Y4: 18.573955 | Z4: 7.0610258
A5: 1982 | B5: 41.44427 | C5: 18.406819 | D5: 5.6126461 | E5: 0.026399476 | F5: 1.3388276 | G5: 6.8549439 | H5: 3.5064935 | I5: 0.59269142 | J5: 31.340673 | K5: 28.751048 | L5: 19.62368 | M5: 0.25216325 | N5: NA | O5: 0.33548801 | P5: 6.2294886 | Q5: 24.460223 | R5: 4.3734774 | S5: NA | T5: 6.7081819 | U5: NA | V5: 18.268418 | W5: 0.02347564 | X5: 0.8231594 | Y5: 19.810301 | Z5: 7.5170896
A6: 1983 | B6: 50.029053 | C6: 19.974923 | D6: 8.1589065 | E6: 0.063051172 | F6: 1.601859 | G6: 8.3322373 | H6: 3.7707391 | I6: 0.63396968 | J6: 36.745061 | K6: 32.722731 | L6: 12.964674 | M6: 0.40695242 | N6: NA | O6: 0.25080471 | P6: 7.6198682 | Q6: 19.751027 | R6: 2.9921574 | S6: NA | T6: 8.3547441 | U6: NA | V6: 19.170115 | W6: 0.16196694 | X6: 1.5914148 | Y6: 23.389893 | Z6: 9.0541598
A7: 1984 | B7: 53.191489 | C7: 14.904477 | D7: 8.1715937 | E7: 0.62176171 | F7: 7.0718878 | G7: 10.222813 | H7: 3.1307978 | I7: 0.42815678 | J7: 35.30963 | K7: 35.740072 | L7: 21.516145 | M7: 0.55303917 | N7: NA | O7: 0.24792477 | P7: 8.5290413 | Q7: 25.364772 | R7: 2.8484677 | S7: NA | T7: 13.58934 | U7: NA | V7: 21.471255 | W7: 0.56750018 | X7: 1.5246424 | Y7: 24.565697 | Z7: 10.107435
A8: 1985 | B8: 47.601476 | C8: 16.2508 | D8: 8.4996472 | E8: 0.72555634 | F8: 1.8766183 | G8: 9.5484204 | H8: 3.7163703 | I8: 0.78014055 | J8: 36.314182 | K8: 29.304029 | L8: 14.220256 | M8: 0.66963099 | N8: NA | O8: 0.24223236 | P8: 8.6738865 | Q8: 23.692342 | R8: 3.6758085 | S8: NA | T8: 12.038553 | U8: NA | V8: 19.152438 | W8: 0.4452259 | X8: 1.718116 | Y8: 24.028715 | Z8: 9.2847846
A9: 1986 | B9: 55.708574 | C9: 16.569409 | D9: 11.021729 | E9: 1.1593396 | F9: 1.3705527 | G9: 7.3699052 | H9: 2.624073 | I9: 0.96000614 | J9: 38.553459 | K9: 31.789849 | L9: 25.006781 | M9: 0.39399909 | N9: NA | O9: 0.33940294 | P9: 7.9713527 | Q9: 18.914388 | R9: 2.9318916 | S9: NA | T9: 16.85233 | U9: NA | V9: 18.89487 | W9: 0.52653646 | X9: 1.6612986 | Y9: 25.81063 | Z9: 9.7849922
A10: 1987 | B10: 51.762754 | C10: 20.660405 | D10: 9.2684942 | E10: 3.0280353 | F10: 1.3202907 | G10: 4.9049298 | H10: 2.6661515 | I10: 1.7114881 | J10: 38.692895 | K10: 30.052265 | L10: 17.410606 | M10: 0.29316587 | N10: NA | O10: 0.26840721 | P10: 11.912399 | Q10: 19.368975 | R10: 3.460551 | S10: NA | T10: 17.824454 | U10: NA | V10: 21.897734 | W10: 1.0138759 | X10: 1.7540097 | Y10: 23.89304 | Z10: 9.4811708
A11: 1988 | B11: 47.389558 | C11: 22.675201 | D11: 10.586233 | E11: 3.8927672 | F11: 1.3910538 | G11: 6.7537249 | H11: 2.7157738 | I11: 1.8543878 | J11: 36.257508 | K11: 38.807531 | L11: 15.742292 | M11: 0.56449422 | N11: NA | O11: 0.40125958 | P11: 11.925147 | Q11: 18.256429 | R11: 3.9766274 | S11: NA | T11: 17.073433 | U11: NA | V11: 18.779156 | W11: 0.83562783 | X11: 1.9084913 | Y11: 19.803617 | Z11: 8.8062149
A12: 1989 | B12: 48.838641 | C12: 24.44558 | D12: 10.434287 | E12: 2.952343 | F12: 2.6940423 | G12: 6.180309 | H12: 3.4108798 | I12: 2.3259588 | J12: 38.269101 | K12: 38.399189 | L12: 17.732051 | M12: 0.50175473 | N12: 2.6662128 | O12: 0.23237396 | P12: 9.9685061 | Q12: 21.004142 | R12: 5.4162454 | S12: 0.62758735 | T12: 13.307653 | U12: 4.2235632 | V12: 22.73572 | W12: 1.317637 | X12: 2.075082 | Y12: 20.832684 | Z12: 9.0909228
A13: 1990 | B13: 50.417248 | C13: 29.823546 | D13: 11.237007 | E13: 2.5247997 | F13: 4.2306674 | G13: 5.8872779 | H13: 4.0328467 | I13: 2.2616589 | J13: 33.74783 | K13: 35.935936 | L13: 22.899027 | M13: 0.24782497 | N13: 1.2830525 | O13: 0.40888917 | P13: 10.135245 | Q13: 38.866488 | R13: 5.8500075 | S13: 0.71093257 | T13: 14.630167 | U13: 1.490953 | V13: 22.016039 | W13: 0.87134149 | X13: 1.7359467 | Y13: 20.496974 | Z13: 9.7279199
A14: 1991 | B14: 45.181856 | C14: 34.441271 | D14: 8.7403734 | E14: 2.6095131 | F14: 2.1873907 | G14: 7.006857 | H14: 3.6183546 | I14: 2.5136346 | J14: 33.141118 | K14: 41.994247 | L14: 19.448144 | M14: 0.31959114 | N14: 0.81923611 | O14: 0.69428568 | P14: 12.476054 | Q14: 33.106338 | R14: 4.8422394 | S14: 0.69767893 | T14: 19.595104 | U14: 1.1071271 | V14: 21.78673 | W14: 0.89976589 | X14: 1.7559066 | Y14: 20.428599 | Z14: 9.9625003
A15: 1992 | B15: 53.272286 | C15: 37.712286 | D15: 6.2939624 | E15: 2.3620412 | F15: 1.7734301 | G15: 6.3062426 | H15: 3.7906526 | I15: 1.7381349 | J15: 34.160532 | K15: 30.820215 | L15: 17.322988 | M15: 0.31997827 | N15: 0.49183239 | O15: 0.93600031 | P15: 10.196508 | Q15: 31.299041 | R15: 3.2345575 | S15: 0.82849938 | T15: 21.409026 | U15: 1.0237117 | V15: 23.251732 | W15: 0.64515478 | X15: 1.6634454 | Y15: 10.891338 | Z15: 8.4542154
A16: 1993 | B16: 56.98724 | C16: 46.940857 | D16: 6.4246806 | E16: 3.6664361 | F16: 2.3962473 | G16: 4.3005316 | H16: 2.0584451 | I16: 2.0266528 | J16: 37.029265 | K16: 32.681337 | L16: 26.06707 | M16: 0.51494188 | N16: 0.51824164 | O16: 0.74712152 | P16: 11.414383 | Q16: 33.172292 | R16: 5.4615969 | S16: 0.67235904 | T16: 26.096653 | U16: 1.541891 | V16: 24.663073 | W16: 0.35322552 | X16: 1.6779881 | Y16: 21.740001 | Z16: 10.412699
A17: 1994 | B17: 62.798435 | C17: 43.980314 | D17: 5.7583461 | E17: 1.950888 | F17: 2.16264 | G17: 4.7580906 | H17: 1.9906103 | I17: 1.5107086 | J17: 38.869284 | K17: 34.558824 | L17: 20.554287 | M17: 0.31270664 | N17: 0.59497994 | O17: 0.6304665 | P17: 12.220833 | Q17: 23.399912 | R17: 4.9166892 | S17: 0.6616088 | T17: 29.008624 | U17: 0.78518451 | V17: 25.377668 | W17: 0.49522353 | X17: 1.5118333 | Y17: 20.439915 | Z17: 9.7025065
A18: 1995 | B18: 64.74753 | C18: 53.316956 | D18: 8.6385901 | E18: 3.7220017 | F18: 3.6313719 | G18: 7.4487213 | H18: 3.0018332 | I18: 3.0620575 | J18: 38.261165 | K18: 43.650794 | L18: 19.425506 | M18: 0.87665906 | N18: 0.74463845 | O18: 0.92918114 | P18: 10.205042 | Q18: 28.552621 | R18: 5.2198613 | S18: 0.77851573 | T18: 33.813512 | U18: 1.8328979 | V18: 29.919234 | W18: 0.74412758 | X18: 1.9576909 | Y18: 30.491472 | Z18: 11.921925
A19: 1996 | B19: 68.403797 | C19: 48.854842 | D19: 10.156534 | E19: 4.4039626 | F19: 3.556851 | G19: 6.6640659 | H19: 3.6199095 | I19: 2.9815001 | J19: 42.91499 | K19: 42.043344 | L19: 16.215123 | M19: 0.48641741 | N19: 1.0561975 | O19: 1.2984042 | P19: 12.653033 | Q19: 29.658371 | R19: 7.3246055 | S19: 0.81062361 | T19: 25.510267 | U19: 2.4314319 | V19: 34.75565 | W19: 1.0485979 | X19: 1.8446359 | Y19: 34.628256 | Z19: 13.284631
A20: 1997 | B20: 67.980259 | C20: 49.302616 | D20: 12.477332 | E20: 5.2192483 | F20: 3.5661219 | G20: 5.7894832 | H20: 7.8040681 | I20: 3.8101125 | J20: 38.083015 | K20: 37.196196 | L20: 15.319021 | M20: 0.60247994 | N20: 1.5893817 | O20: 2.0108264 | P20: 11.203754 | Q20: 31.946632 | R20: 5.9239719 | S20: 0.75011977 | T20: 20.266298 | U20: 1.8871789 | V20: 33.277197 | W20: 1.0186163 | X20: 1.4890502 | Y20: 34.678762 | Z20: 12.527481
A21: 1998 | B21: 74.732899 | C21: 54.418598 | D21: 9.4455735 | E21: 5.7762647 | F21: 3.8589359 | G21: 6.812506 | H21: 7.9692155 | I21: 5.9359029 | J21: 40.361237 | K21: 43.423804 | L21: 35.886991 | M21: 0.37149668 | N21: 1.7510502 | O21: 2.955611 | P21: 11.779225 | Q21: 38.050799 | R21: 8.1996376 | S21: 0.72236367 | T21: 30.947818 | U21: 2.1076371 | V21: 35.569268 | W21: 1.5520534 | X21: 1.6809413 | Y21: 36.575498 | Z21: 14.669089
A22: 1999 | B22: 71.581271 | C22: 56.977276 | D22: 8.2776474 | E22: 5.835018 | F22: 3.8573668 | G22: 7.1511328 | H22: 3.5511364 | I22: 4.6319698 | J22: 39.886304 | K22: 38.437554 | L22: 28.378348 | M22: 0.41541032 | N22: 1.3397631 | O22: 3.4116419 | P22: 11.30652 | Q22: 34.598768 | R22: 6.9308154 | S22: 0.94929068 | T22: 29.698564 | U22: 1.3291751 | V22: 33.063725 | W22: 2.0923662 | X22: 1.7076133 | Y22: 30.664204 | Z22: 13.333439
A23: 2000 | B23: 72.873793 | C23: 58.997704 | D23: 8.7025695 | E23: 6.6462354 | F23: 3.5784125 | G23: 6.4438793 | H23: 3.5660797 | I23: 3.6359391 | J23: 42.562287 | K23: 37.650353 | L23: 29.026848 | M23: 0.48098948 | N23: 1.3837322 | O23: 4.2838509 | P23: 9.0551909 | Q23: 33.797752 | R23: 6.0498652 | S23: 1.3024104 | T23: 25.85927 | U23: 1.8631417 | V23: 30.86946 | W23: 2.0253835 | X23: 1.291327 | Y23: 30.020068 | Z23: 12.940498
... A47: 2024 | B47: 83.800963 | C47: 105.66618 | D47: 57.377943 | E47: 33.179431 | F47: 15.060155 | G47: 26.902518 | H47: 21.689306 | I47: 13.825297 | J47: 91.641515 | K47: 61.606496 | L47: 54.692652 | M47: 5.3439515 | N47: 9.1506868 | O47: 25.773437 | P47: 21.272128 | Q47: 76.391621 | R47: 12.213926 | S47: 5.3085799 | T47: 27.000457 | U47: 10.190933 | V47: 65.55108 | W47: 14.589278 | X47: 10.874545 | Y47: 72.328084 | Z47: 36.280762
A48: NA = Not available. Most recent year is preliminary.
A49: 1/ Excludes potatoes, sweet potatoes, and mushrooms.
A50: 2/ Includes fresh and processing.
A51: 3/ Beginning in 2012, data coverage for melons is included in the Fruit and Tree Nuts Yearbook.
A52: 4/ Shares larger than 100 percent are possible when imports exceed domestic availability.
A53: Source: USDA, Economic Research Service.

Sheet Table 8-Export Percent
A1: Table 8--Vegetables, fresh market: Share of supply exported/1 | O1: =HYPERLINK("#'"&"Index'!A1","INDEX") -> INDEX
A2: Year/3 | B2: Artichokes | C2: Asparagus | D2: Beans, snap/green | E2: Broccoli | F2: Cabbage | G2: Carrots | H2: Cauliflower | I2: Celery/2 | J2: Cucumbers | K2: Eggplant/2 | L2: Garlic/2 | M2: Lettuce, head | N2: Lettuce, leaf/romaine | O2: Mushrooms | P2: Onions | Q2: Peppers, bell/2 | R2: Potatoes | S2: Pumpkins | T2: Radishes | U2: Spinach | V2: Squash | W2: Sweet corn | X2: Sweet potatoes | Y2: Tomatoes | Z2: Fresh, all/1
A3: 1980 | B3: 2.9048656 | C3: 22.288779 | D3: 9.2187699 | E3: 16.606786 | F3: 3.8403928 | G3: 6.7381317 | H3: 11.510791 | I3: 10.478082 | J3: 5.4809242 | K3: NA | L3: 9.9504728 | M3: 7.6912177 | N3: NA | O3: 0.21967567 | P3: 7.7984329 | Q3: 9.1901603 | R3: 2.3046662 | S3: NA | T3: 16.814727 | U3: 14.77145 | V3: NA | W3: 2.9908493 | X3: 1.3968336 | Y3: 8.5797282 | Z3: 7.1184399
A4: 1981 | B4: 2.8813559 | C4: 21.433367 | D4: 7.4885032 | E4: 16.090379 | F4: 4.6707096 | G4: 9.2837341 | H4: 13.309452 | I4: 10.69561 | J4: 5.9797608 | K4: NA | L4: 16.27027 | M4: 8.3428881 | N4: NA | O4: 0.66135274 | P4: 11.368594 | Q4: 10.328901 | R4: 3.6428551 | S4: NA | T4: 17.478225 | U4: 15.036965 | V4: NA | W4: 2.8589707 | X4: 1.4622384 | Y4: 8.6027642 | Z4: 8.1157786
A5: 1982 | B5: 2.2506394 | C5: 16.957103 | D5: 6.7576613 | E5: 14.800697 | F5: 3.7027385 | G5: 8.3891013 | H5: 12.698413 | I5: 10.557507 | J5: 5.3467082 | K5: NA | L5: 12.199902 | M5: 7.9134638 | N5: NA | O5: 0.48741197 | P5: 3.9396057 | Q5: 9.3762311 | R5: 2.7139887 | S5: NA | T5: 16.288037 | U5: 12.952945 | V5: NA | W5: 3.2299554 | X5: 0.85920483 | Y5: 7.6380792 | Z5: 6.4624904
A6: 1983 | B6: 1.8254421 | C6: 14.331991 | D6: 6.9256518 | E6: 14.806804 | F6: 3.0528467 | G6: 7.8480092 | H6: 13.42387 | I6: 10.801098 | J6: 5.0214439 | K6: NA | L6: 9.9357764 | M6: 8.9565112 | N6: NA | O6: 0.46178633 | P6: 5.4815594 | Q6: 8.6089608 | R6: 2.3701968 | S6: NA | T6: 14.733057 | U6: 14.640618 | V6: NA | W6: 3.3517438 | X6: 1.0988993 | Y6: 8.2564369 | Z6: 6.9378459
A7: 1984 | B7: 1.8703784 | C7: 19.062795 | D7: 5.7332807 | E7: 14.275137 | F7: 3.671918 | G7: 8.3164065 | H7: 12.924071 | I7: 10.689521 | J7: 4.7383922 | K7: NA | L7: 13.010803 | M7: 8.1506018 | N7: NA | O7: 0.36459993 | P7: 6.8726222 | Q7: 8.1089778 | R7: 3.0600332 | S7: NA | T7: 16.782737 | U7: 14.393798 | V7: NA | W7: 3.0649964 | X7: 1.1942364 | Y7: 7.2297973 | Z7: 6.944032
A8: 1985 | B8: 2.4009604 | C8: 16.708198 | D8: 7.1685474 | E8: 14.574047 | F8: 2.8998757 | G8: 7.9890626 | H8: 13.456985 | I8: 11.201494 | J8: 5.0647821 | K8: NA | L8: 7.1942446 | M8: 8.2220638 | N8: NA | O8: 0.45348516 | P8: 4.0211915 | Q8: 7.5211756 | R8: 2.9009571 | S8: NA | T8: 16.364589 | U8: 11.583378 | V8: NA | W8: 3.3417203 | X8: 1.1848014 | Y8: 7.0981438 | Z8: 6.2231153
A9: 1986 | B9: 2.3850824 | C9: 10.815975 | D9: 9.0547829 | E9: 14.017122 | F9: 2.9811225 | G9: 9.3317838 | H9: 12.988087 | I9: 12.04177 | J9: 5.2604699 | K9: NA | L9: 15.966011 | M9: 9.4635714 | N9: NA | O9: 0.67686102 | P9: 5.6510626 | Q9: 8.2227351 | R9: 2.8174328 | S9: NA | T9: 16.748304 | U9: 15.430806 | V9: NA | W9: 3.5821203 | X9: 1.4415118 | Y9: 6.9963325 | Z9: 7.0953115
A10: 1987 | B10: 2.1906694 | C10: 17.786483 | D10: 8.5738075 | E10: 14.675506 | F10: 2.9691974 | G10: 7.955584 | H10: 14.671942 | I10: 11.652447 | J10: 4.5838827 | K10: NA | L10: 7.8443677 | M10: 7.970908 | N10: NA | O10: 0.62478777 | P10: 5.8732793 | Q10: 8.0250784 | R10: 3.0260402 | S10: NA | T10: 15.388591 | U10: 14.796163 | V10: NA | W10: 3.8823756 | X10: 1.2970026 | Y10: 6.8470523 | Z10: 6.5660815
A11: 1988 | B11: 2.9029463 | C11: 20.952323 | D11: 10.885053 | E11: 10.932101 | F11: 2.2060564 | G11: 8.6595555 | H11: 18.680986 | I11: 11.251772 | J11: 6.4424218 | K11: 12.932605 | L11: 10.664911 | M11: 6.0850181 | N11: NA | O11: 0.67742396 | P11: 6.3389944 | Q11: 7.9029143 | R11: 3.354787 | S11: NA | T11: 15.593851 | U11: 16.504204 | V11: NA | W11: 2.9565478 | X11: 1.2123382 | Y11: 5.7698209 | Z11: 6.195801
A12: 1989 | B12: 2.5474905 | C12: 23.19998 | D12: 9.0261076 | E12: 14.627096 | F12: 2.2814878 | G12: 7.5062436 | H12: 16.13613 | I12: 10.7167 | J12: 5.9459459 | K12: 11.796247 | L12: 16.438356 | M12: 6.1333298 | N12: 6.1641648 | O12: 0.24442306 | P12: 4.9602102 | Q12: 7.8141082 | R12: 3.6424178 | S12: 0.13101565 | T12: 11.393108 | U12: 16.155556 | V12: 0.26337587 | W12: 3.6415581 | X12: 1.1202443 | Y12: 6.6760278 | Z12: 6.2438085
A13: 1990 | B13: 2.9807557 | C13: 21.154345 | D13: 12.012856 | E13: 16.63665 | F13: 2.6301482 | G13: 7.109616 | H13: 18.946901 | I13: 11.013994 | J13: 6.6286847 | K13: 13.05483 | L13: 14.956214 | M13: 5.4095888 | N13: 12.166947 | O13: 1.9166645 | P13: 6.7385193 | Q13: 9.320431 | R13: 2.7235337 | S13: 1.5006752 | T13: 12.842264 | U13: 12.392438 | V13: 1.0601097 | W13: 4.1878883 | X13: 1.146428 | Y13: 7.0178655 | Z13: 6.9042227
A14: 1991 | B14: 2.6474424 | C14: 19.630299 | D14: 12.342568 | E14: 19.395085 | F14: 3.4471539 | G14: 8.3902178 | H14: 21.922348 | I14: 12.558049 | J14: 6.5979514 | K14: 13.083333 | L14: 14.536031 | M14: 6.9970623 | N14: 13.094961 | O14: 3.4511093 | P14: 6.1292771 | Q14: 9.4962281 | R14: 2.6145797 | S14: 1.5085613 | T14: 15.411223 | U14: 11.690176 | V14: 1.0170156 | W14: 4.3742316 | X14: 1.4123552 | Y14: 7.159302 | Z14: 7.5592203
A15: 1992 | B15: 2.1241908 | C15: 21.651764 | D15: 10.753694 | E15: 18.821483 | F15: 3.6727597 | G15: 7.5719022 | H15: 25.68822 | I15: 12.001175 | J15: 6.0913363 | K15: 14.031339 | L15: 13.880856 | M15: 6.7127114 | N15: 13.982816 | O15: 2.8713083 | P15: 5.9813433 | Q15: 9.4049708 | R15: 4.1528787 | S15: 2.0402674 | T15: 15.367711 | U15: 11.541861 | V15: 1.2203458 | W15: 5.0657878 | X15: 1.58228 | Y15: 8.4761476 | Z15: 7.709627
A16: 1993 | B16: 1.962349 | C16: 24.088786 | D16: 9.4596356 | E16: 21.164701 | F16: 3.2091726 | G16: 6.1970227 | H16: 23.613646 | I16: 11.89671 | J16: 5.5280495 | K16: 13.40861 | L16: 13.435034 | M16: 6.8033809 | N16: 14.923866 | O16: 3.2874823 | P16: 6.7570989 | Q16: 5.8142773 | R16: 3.9697165 | S16: 1.8436735 | T16: 13.947532 | U16: 13.601321 | V16: 1.3954924 | W16: 3.99156 | X16: 2.0589713 | Y16: 7.5365796 | Z16: 7.4343102
A17: 1994 | B17: 1.7379106 | C17: 24.776101 | D17: 8.0944868 | E17: 18.836969 | F17: 3.2783665 | G17: 4.8499933 | H17: 28.533083 | I17: 11.888053 | J17: 5.2253796 | K17: 11.917098 | L17: 13.248004 | M17: 6.2443937 | N17: 12.976395 | O17: 2.2031671 | P17: 11.625068 | Q17: 5.9523857 | R17: 4.7710939 | S17: 1.6059887 | T17: 15.030757 | U17: 11.725581 | V17: 1.2526984 | W17: 3.3496865 | X17: 1.6253941 | Y17: 7.3888451 | Z17: 7.8849404
A18: 1995 | B18: 2.0269662 | C18: 21.530185 | D18: 9.5067911 | E18: 19.548554 | F18: 4.0310884 | G18: 6.0156795 | H18: 34.028723 | I18: 11.701998 | J18: 4.9063826 | K18: 13.69863 | L18: 11.235109 | M18: 6.0111582 | N18: 12.665648 | O18: 1.8114971 | P18: 9.3131684 | Q18: 5.4617229 | R18: 4.2609551 | S18: 1.5960994 | T18: 16.367756 | U18: 13.536148 | V18: 1.4000306 | W18: 4.9888857 | X18: 1.9958248 | Y18: 6.0524216 | Z18: 7.642953
A19: 1996 | B19: 1.7301309 | C19: 16.900994 | D19: 10.248565 | E19: 18.617609 | F19: 4.0898489 | G19: 5.9251147 | H19: 33.40508 | I19: 11.966032 | J19: 4.2330071 | K19: 11.117226 | L19: 11.475273 | M19: 6.6947584 | N19: 12.462685 | O19: 1.871478 | P19: 8.1560335 | Q19: 5.7733859 | R19: 4.3334174 | S19: 1.569556 | T19: 16.84869 | U19: 14.260225 | V19: 1.36889 | W19: 3.8939133 | X19: 2.022274 | Y19: 5.922398 | Z19: 7.4156342
A20: 1997 | B20: 1.7000456 | C20: 15.765069 | D20: 13.623732 | E20: 17.630392 | F20: 3.6510122 | G20: 5.6367896 | H20: 28.078818 | I20: 12.581981 | J20: 3.9334907 | K20: 11.031025 | L20: 13.764515 | M20: 5.7187231 | N20: 12.338418 | O20: 2.0386991 | P20: 7.964588 | Q20: 6.2657938 | R20: 4.9354004 | S20: 1.5577673 | T20: 14.715799 | U20: 9.0242144 | V20: 1.2744675 | W20: 5.2190564 | X20: 2.1976545 | Y20: 6.7502576 | Z20: 7.1908822
A21: 1998 | B21: 1.5060655 | C21: 14.558229 | D21: 14.269837 | E21: 17.733134 | F21: 4.034646 | G21: 8.8545953 | H21: 30.419762 | I21: 13.207249 | J21: 2.763512 | K21: 9.252649 | L21: 10.22213 | M21: 6.1614517 | N21: 13.387708 | O21: 2.2344636 | P21: 8.380654 | Q21: 5.6255353 | R21: 4.7893996 | S21: 1.4059302 | T21: 14.314492 | U21: 11.222395 | V21: 1.1969765 | W21: 3.5037916 | X21: 3.0003154 | Y21: 5.3085783 | Z21: 7.2785349
A22: 1999 | B22: 2.0352034 | C22: 13.226108 | D22: 12.046895 | E22: 16.063978 | F22: 3.9601388 | G22: 9.2146163 | H22: 27.963748 | I22: 12.945567 | J22: 2.7327243 | K22: 10.833301 | L22: 6.6536503 | M22: 5.308603 | N22: 12.439258 | O22: 1.9872615 | P22: 8.3279341 | Q22: 6.3506961 | R22: 4.3025696 | S22: 1.6026049 | T22: 17.096288 | U22: 12.264395 | V22: 1.2914962 | W22: 3.3917601 | X22: 3.2846545 | Y22: 5.9072908 | Z22: 7.2263863
A23: 2000 | B23: 1.7050447 | C23: 12.794514 | D23: 10.718519 | E23: 19.309076 | F23: 3.2105684 | G23: 9.6140649 | H23: 24.82548 | I23: 12.885254 | J23: 3.0878499 | K23: 9.2820146 | L23: 7.7427365 | M23: 5.3468625 | N23: 13.431175 | O23: 2.1354483 | P23: 9.6219977 | Q23: 6.3841198 | R23: 4.8360593 | S23: 2.1986673 | T23: 13.880968 | U23: 9.956738 | V23: 1.2812375 | W23: 3.8326731 | X23: 2.8071748 | Y23: 7.1101305 | Z23: 7.7659334
... A47: 2024 | B47: 1.1455879 | C47: 10.873617 | D47: 10.804127 | E47: 1.729372 | F47: 5.2279006 | G47: 7.5907993 | H47: 29.534383 | I47: 10.916999 | J47: 0.90651009 | K47: 6.378691 | L47: 3.4753484 | M47: 5.0329949 | N47: 8.6474774 | O47: 1.0155842 | P47: 8.7577012 | Q47: 2.9295899 | R47: 11.890912 | S47: 1.2026229 | T47: 8.6638186 | U47: 16.088321 | V47: 0.93309439 | W47: 9.3233692 | X47: 19.493398 | Y47: 2.7078079 | Z47: 6.7513213
A48: NA = Not available. Most recent year is preliminary.
A49: 1/ Excludes potatoes, sweet potatoes, and mushrooms.
A50: 2/ Includes fresh and processing.
A51: 3/ Beginning in 2012, data coverage for melons is included in the Fruit and Tree Nuts Yearbook.
A52: Source: USDA, Economic Research Service.

Sheet Table 9-World Veg
A1: Table 9--Selected vegetable production in leading countries and the world/1 | O1: =HYPERLINK("#'"&"Index'!A1","INDEX") -> INDEX
A2: Commodity/country | B2: 2005 | C2: 2006 | D2: 2007 | E2: 2008 | F2: 2009 | G2: 2010 | H2: 2011 | I2: 2012 | J2: 2013 | K2: 2014 | L2: 2015 | M2: 2016 | N2: 2017 | O2: 2018 | P2: 2019 | Q2: 2020 | R2: 2021 | S2: 2022 | T2: 2023
B3: ------------------------------------------------------------------------------------------ Million hundredweight (cwt) ----------------------------------------------------------------------------------------
A4: Potatoes
A5: China | B5: 1562.4046 | C5: 1421.6836 | D5: 1405.9536 | E5: 1511.7865 | F5: 1539.5867 | G5: 1687.2303 | H5: 1798.3763 | I5: 1859.786 | J5: 1893.3184 | K5: 1855.3107 | L5: 1826.0654 | M5: 1872.3524 | N5: 1950.6826 | O5: 1989.8732 | P5: 1973.1367 | Q5: 2045.8892 | R5: 2080.0609 | S5: 2034.8441 | T5: 2059.7783
A6: India | B6: 634.65997 | C6: 643.18965 | D6: 630.51307 | E6: 764.07789 | F6: 758.18935 | G6: 806.3912 | H6: 933.42373 | I6: 914.54334 | J6: 999.65498 | K6: 1022.8344 | L6: 1058.417 | M6: 957.18073 | N6: 1071.5565 | O6: 1131.1916 | P6: 1106.4998 | Q6: 1070.6085 | R6: 1195.5665 | S6: 1238.4685 | T6: 1325.9038
A7: Ukraine | B7: 429.07235 | C7: 429.17597 | D7: 421.12689 | E7: 430.90219 | F7: 433.56317 | G7: 412.37455 | H7: 534.57674 | I7: 512.57902 | J7: 490.71799 | K7: 522.34881 | L7: 459.42713 | M7: 479.51168 | N7: 489.6073 | O7: 496.12747 | P7: 446.85902 | Q7: 459.39891 | R7: 470.82613 | S7: 460.74858 | T7: 470.87706
A8: United States | B8: 423.78787 | C8: 440.69785 | D8: 444.87491 | E8: 415.05488 | F8: 432.60142 | G8: 404.54889 | H8: 430.03687 | I8: 464.96988 | J8: 434.65181 | K8: 442.17001 | L8: 441.20483 | M8: 450.324 | N8: 450.92082 | O8: 450.2182 | P8: 424.41884 | Q8: 420.01995 | R8: 412.6391 | S8: 402.05383 | T8: 440.75001
A9: Russia | B9: 620.31429 | C9: 623.02031 | D9: 599.55242 | E9: 635.9532 | F9: 686.38609 | G9: 466.06897 | H9: 720.50281 | I9: 651.08065 | J9: 665.77658 | K9: 694.48577 | L9: 741.7627 | M9: 495.23498 | N9: 478.57152 | O9: 493.72422 | P9: 486.66752 | Q9: 432.26819 | R9: 403.34739 | S9: 416.40192 | T9: 427.13318
A10: Other | B10: 3334.724 | C10: 3225.0965 | D10: 3405.2023 | E10: 3458.2112 | F10: 3444.4181 | G10: 3471.6451 | H10: 3719.6323 | I10: 3582.5838 | J10: 3592.0086 | K10: 3608.2853 | L10: 3534.4659 | M10: 3554.9637 | N10: 3699.8673 | O10: 3480.0633 | P10: 3627.0341 | Q10: 3703.2886 | R10: 3675.0325 | S10: 3679.537 | T10: 3721.0811
A11: World | B11: 7004.9631 | C11: 6782.8638 | D11: 6907.2232 | E11: 7215.9858 | F11: 7294.7449 | G11: 7248.259 | H11: 8136.5488 | I11: 7985.5427 | J11: 8076.1283 | K11: 8145.435 | L11: 8061.343 | M11: 7809.5674 | N11: 8141.2061 | O11: 8041.1979 | P11: 8064.6159 | Q11: 8131.4734 | R11: 8237.4725 | S11: 8232.0538 | T11: 8445.5234
A12: Tomatoes
A13: China | B13: 694.45593 | C13: 714.29753 | D13: 793.66392 | E13: 878.05685 | F13: 997.94419 | G13: 1030.8812 | H13: 1084.6806 | I13: 1059.4796 | J13: 1114.4849 | K13: 1156.8981 | L13: 1222.8156 | M13: 1263.5373 | N13: 1303.1291 | O13: 1343.0409 | P13: 1386.0349 | Q13: 1425.1348 | R13: 1466.8513 | S13: 1505.7157 | T13: 1545.8742
A14: India | B14: 194.56671 | C14: 216.5027 | D14: 221.67474 | E14: 227.1422 | F14: 245.7889 | G14: 274.10506 | H14: 364.33583 | I14: 411.22814 | J14: 401.83645 | K14: 413.05599 | L14: 361.22731 | M14: 412.96979 | N14: 456.53312 | O14: 435.61126 | P14: 419.0325 | Q14: 453.04982 | R14: 466.96099 | S14: 456.22448 | T14: 450.29404
A15: Turkey | B15: 221.56451 | C15: 217.26279 | D15: 219.06341 | E15: 242.18555 | F15: 236.89924 | G15: 221.6086 | H15: 242.5841 | I15: 250.2246 | J15: 260.58632 | K15: 261.24771 | L15: 278.11307 | M15: 277.78237 | N15: 281.0893 | O15: 267.86157 | P15: 283.11734 | Q15: 291.09862 | R15: 288.70094 | S15: 286.60086 | T15: 293.21473
A16: United States | B16: 262.75276 | C16: 270.22431 | D16: 312.7296 | E16: 302.04798 | F16: 340.779 | G16: 309.81553 | H16: 303.39347 | I16: 319.20171 | J16: 304.86792 | K16: 349.98374 | L16: 321.44359 | M16: 283.89026 | N16: 245.56447 | O16: 278.07096 | P16: 239.39951 | Q16: 241.166 | R16: 230.28851 | S16: 225.628 | T16: 272.713
A17: Egypt | B17: 167.55127 | C17: 189.06993 | D17: 190.45782 | E17: 202.91555 | F17: 226.60293 | G17: 188.3848 | H17: 178.69041 | I17: 190.15348 | J17: 182.77531 | K17: 182.72002 | L17: 170.58984 | M17: 161.39407 | N17: 148.3491 | O17: 149.42386 | P17: 150.23308 | Q17: 143.16705 | R17: 140.8598 | S17: 140.38133 | T17: 136.92942
